Workbook

Sheet Form Responses 1

Sheet Batteries
I1: Density | L1: Charge | N1: Discharge
C2: MJ / kg | I2: Wh / kg | J2: kWh / kg | L2: kcal / h | N2: kW / kg | Q2: kW
C3: Energy | D3: Charge | F3: Discharge | I3: Energy | J3: Useable | L3: Synthesis | M3: Eff | N3: Power | O3: Eff | Q3: Heat
B4: Li - Ion | C4: =J4*3600 / 1000 -> 0.9 | D4: =I4*3600/(N4*1000) / 60 * 1/O4 -> 16.666667 | E4: min | F4: =I4*3600/(N4*1000) / 60 * O4 -> 13.5 | G4: min | I4: 250 | J4: =I4/1000 -> 0.25 | N4: 1 | O4: 0.9 | Q4: =N4/O4*(1-O4) -> 0.11111111
B5: Solid state | C5: =J5*3600 / 1000 -> 1.8 | D5: =I5*3600/(N5*1000) / 60 * 1/O5 -> 16.666667 | E5: min | F5: =I5*3600/(N5*1000) / 60 * O5 -> 13.5 | G5: min | I5: 500 | J5: =I5/1000 -> 0.5 | N5: 2 | O5: 0.9 | Q5: =N5/O5*(1-O5) -> 0.22222222
A6: Bio | B6: Carbs | C6: =J6*3600 / 1000 -> 5.4 | D6: =(I6/1000)/(L6/860) * 1/M6 -> 23.888889 | E6: h | F6: =(I6/1000)/(N6/3600)/60*O6 -> 45 | G6: min | I6: 5000 | J6: =I6*O6/1000 -> 1.5 | L6: 200 | M6: 0.9 | N6: 2 | O6: 0.3 | Q6: =N6/O6*(1-O6) -> 4.6666667
A7: Bio | B7: Sugar cell (+) | C7: =J7*3600 / 1000 -> 10.8 | D7: =(I7/1000)/(L7/860) * 1/M7 -> 15.925926 | E7: h | F7: =(I7/1000)/(N7/3600)/60*O7 -> 18 | G7: min | I7: 5000 | J7: =I7*O7/1000 -> 3 | L7: 300 | M7: 0.9 | N7: 10 | O7: 0.6 | Q7: =N7/O7*(1-O7) -> 6.6666667
A8: Bio | B8: Graisse | C8: =J8*3600 / 1000 -> 10.8 | D8: =(I8/1000)/(L8/860) * 1/M8 -> 35.833333 | E8: h | F8: =(I8/1000)/(N8/3600)/3600*O8 -> 60 | G8: h | I8: 10000 | J8: =I8*O8/1000 -> 3 | L8: 300 | M8: 0.8 | N8: 0.05 | O8: 0.3 | Q8: =N8/O8*(1-O8) -> 0.11666667
A9: Bio | B9: Fat cell (+) | C9: =J9*3600 / 1000 -> 21.6 | D9: =(I9/1000)/(L9/860) * 1/M9 -> 19.111111 | E9: h | F9: =(I9/1000)/(N9/3600)/3600*O9 -> 6 | G9: h | I9: 10000 | J9: =I9*O9/1000 -> 6 | L9: 500 | M9: 0.9 | N9: 1 | O9: 0.6 | Q9: =N9/O9*(1-O9) -> 0.66666667
B10: Graphene | C10: =J10*3600 / 1000 -> 0.36 | D10: =I10*3600/(N10*1000) * 1/O10 -> 4 | E10: sec | F10: =I10*3600/(N10*1000) * O10 -> 3.24 | G10: sec | I10: 100 | J10: =I10/1000 -> 0.1 | M10: 0.9 | N10: 100 | O10: 0.9 | Q10: 0
B11: RTG (Voyager) | C11: =J11*3600 / 1000 -> 18 | D11: - | I11: 10000 | J11: =I11/2000 -> 5 | N11: 1e-06 | O11: 1
B12: Tritium | C12: =J12*3600 / 1000 -> 1800000 | D12: - | F12: 10 | G12: ans | I12: 1000000000 | J12: =I12/2000 -> 500000 | N12: 0.001 | O12: 1
B13: Nickel 63 | C13: =J13*3600 / 1000 -> 1800 | D13: - | F13: 50 | G13: ans | I13: 1000000 | J13: =I13/2000 -> 500 | N13: 1e-06 | O13: 1
B14: Carbon 14 | C14: =J14*3600 / 1000 -> 1800 | D14: - | F14: 2000 | G14: ans | I14: 1000000 | J14: =I14/2000 -> 500 | N14: 1e-09 | O14: 1
B15: Li - Air | C15: =J15*3600 / 1000 -> 5.04 | D15: - | F15: =I15*3600/(N15*1000) / 3600 * 1/O15 -> 1.4285714 | G15: h | I15: 2000 | J15: =I15*O15/1000 -> 1.4 | N15: 2 | O15: 0.7

Sheet Sheet46
B3: Activity | C3: Metabolic power (W) | D3: Mechanical power (W) | E3: Implied efficiency
B4: Rest / quiet sitting | C4: 80 – 120 W | D4: ~5 – 20 W (postural) | E4: ~5–20% (very low useful work)
B5: Standing (light activity) | C5: 120 – 180 W | D5: 20 – 50 W | E5: ~15–30%
B6: Walking (5 km/h) | C6: 200 – 350 W | D6: 60 – 120 W | E6: ~20–35%
B7: Brisk walk / power walk | C7: 300 – 450 W | D7: 80 – 150 W | E7: ~25–35%
B8: Easy jogging (8 km/h) | C8: 500 – 700 W | D8: 150 – 250 W | E8: ~25–35%
B9: Steady run (10 km/h) | C9: 700 – 900 W | D9: 200 – 350 W | E9: ~25–35%
B10: Marathon pace (elite ~20 km/h unrealistic; typical marathon pace) | C10: 600 – 900 W (sustained hours) | D10: 150 – 300 W | E10: ~25–35%
B11: Hard run / threshold (race pace) | C11: 900 – 1,500 W | D11: 250 – 500 W | E11: ~25–35%
B12: All-out sprint (100 m, elite) | C12: 2,000 – 6,000 W (short, seconds) | D12: 500 – 1,500 W | E12: ~~20–30% (mechanical peak may be higher for limbs)
B13: Short explosive burst (single jump, lift) | C13: 1,000 – 10,000 W (very short) | D13: 200 – 3,000 W (depending on task) | E13: highly variable
B14: Max instantaneous leg muscle power (elite) | C14: — (metabolic supplied from ATP/PCr + glycolysis) | D14: ~1,000–3,000 W (legs peak, for <1 s) | E14: n/a (burst systems + elastic storage)

Sheet Augments 2
U1: Battery | AA1: Density
G2: time | J2: km/h | K2: degats | M2: kN/kg | N2: kW/kg | O2: kW / kg | P2: kg | Q2: %total | R2: MW | S2: MW | U2: kg | V2: MJ | W2: sec | X2: kg | Y2: %total | AA2: MJ / kg | AB2: kW / kg
B3: Corps | D3: Indice | E3: Cout | G3: Battery | H3: Load | J3: Sprint | K3: Punch | M3: Strength | N3: Power | O3: Heat | P3: Mass | Q3: Muscle | R3: Power | S3: Heat | U3: Mass | V3: Energy | W3: Time | X3: Water | Y3: Mass | Z3: Eff | AA3: Energy | AB3: Power
B4: Bio | C4: Standard | D4: 3 | E4: 0 | G4: 30 | H4: x 1 | J4: 20 | K4: 0+ | M4: 1 | N4: 1 | O4: =N4/0.3 * (0.7) -> 2.3333333 | P4: 70 | Q4: 0.3 | R4: =N4*P4*Q4/1000 / Z4 -> 0.07 | S4: =O4*P4*Q4/1000 -> 0.049 | U4: 0.5 | V4: =U4*AA4 -> 2.5 | W4: =V4/R4 -> 35.714286 | X4: =S4/2.5*W4 -> 0.7 | Y4: =(U4+X4)/P4 *100*1.15 -> 1.9714286 | Z4: 0.3 | AA4: 5 | AB4: 1
B5: Bio | C5: Athlétique | D5: 4 | E5: 2 | G5: 45 | H5: x 3 | J5: 35 | K5: 0+ | M5: 1.5 | N5: 2 | O5: =N5/0.3 * (0.7) -> 4.6666667 | P5: 80 | Q5: 0.4 | R5: =N5*P5*Q5/1000 / Z5 -> 0.21333333 | S5: =O5*P5*Q5/1000 -> 0.14933333 | U5: 2 | V5: =U5*AA5 -> 10 | W5: =V5/R5 -> 46.875 | X5: =S5/2.5*W5 -> 2.8 | Y5: =(U5+X5)/P5 *100*1.15 -> 6.9 | Z5: 0.3 | AA5: 5 | AB5: 2
B6: Bio | C6: Transhumain | D6: 5 | E6: 5 | G6: 60 | H6: x 5 | J6: 70 | K6: 1+ | M6: 3 | N6: 10 | O6: =N6/0.6 * (0.4) -> 6.6666667 | P6: 90 | Q6: 0.5 | R6: =N6*P6*Q6/ 1000 / Z6 -> 0.75 | S6: =O6*P6*Q6/1000 -> 0.3 | U6: 4 | V6: =U6*AA6 -> 40 | W6: =V6/R6 -> 53.333333 | X6: =S6/2.5*W6 -> 6.4 | Y6: =(U6+X6)/P6 *100*1.15 -> 13.288889 | Z6: 0.6 | AA6: 10 | AB6: 10
C7: Metahumain | D7: 6 | E7: 10 | G7: 20 | H7: x 10 | J7: 100 | K7: 2+ | M7: 10 | N7: 50 | O7: =N7/0.6 * (0.4) -> 33.333333 | P7: 100 | Q7: 0.5 | R7: =N7*P7*Q7/1000 / Z7 -> 4.1666667 | S7: =O7*P7*Q7/1000 -> 1.6666667 | U7: 8 | V7: =U7*AA7 -> 80 | W7: =V7/R7 -> 19.2 | X7: =S7/2.5*W7 -> 12.8 | Y7: =(U7+X7)/P7 *100*1.15 -> 23.92 | Z7: 0.6 | AA7: 10 | AB7: 10
G9: minutes | H9: kg | L9: Flops | N9: W/kg | O9: W | P9: %total | Q9: MJ | R9: MW
B10: Processeur | D10: Indice | E10: Cout | G10: Battery | H10: Mass | J10: Ref | L10: Perf | N10: Power | O10: Power | P10: Battery | Q10: Energy | R10: Heat
C11: Free | D11: 3 | E11: 0 | G11: =Q11*10^6/O11/60 -> 200 | H11: 0.1 | J11: Smartphone | L11: e11 | N11: 50 | O11: =N11*H11 -> 5 | P11: 0.3 | Q11: =H11*2*P11 -> 0.06 | R11: =O11*10^-6 -> 5e-06
C12: Pro | D12: 4 | E12: 2 | G12: =Q12*10^6/O12/60 -> 100 | H12: 1 | J12: Laptop | L12: e12 | N12: 50 | O12: =N12*H12 -> 50 | P12: 0.15 | Q12: =H12*2*P12 -> 0.3 | R12: =O12*10^-6 -> 5e-05
C13: Gamer | D13: 5 | E13: 5 | G13: =Q13*10^6/O13/60 -> 30 | H13: 10 | J13: Gaming laptop | L13: e13 | N13: 100 | O13: =N13*H13 -> 1000 | P13: 0.09 | Q13: =H13*2*P13 -> 1.8 | R13: =O13*10^-6 -> 0.001
C14: Hacker | D14: 6 | E14: 10 | G14: =Q14*10^6/O14/60 -> 5 | H14: 50 | J14: Custom rig | L14: e14 | N14: 600 | O14: =N14*H14 -> 30000 | P14: 0.09 | Q14: =H14*2*P14 -> 9 | R14: =O14*10^-6 -> 0.03
C15: Maison | D15: 3+2D | E15: 2 | H15: 10 | J15: Desktop | L15: e13 | N15: 50 | O15: 1000 | R15: =O15*10^-6 -> 0.001
C16: Magasin | D16: 4+2D | E16: 4 | H16: 100 | L16: e14 | N16: 50 | O16: 10000 | R16: =O16*10^-6 -> 0.01
C17: Serveur | D17: 5+3D | E17: 8 | H17: 10 ton | N17: 100 | O17: 1000000 | R17: =O17*10^-6 -> 1
C18: Mainframe | D18: 6+4D | E18: 14 | H18: 500 ton | J18: Supercomputer | L18: e18 | N18: 600 | O18: 100000000 | R18: =O18*10^-6 -> 100
C19: Oversize | D19: +1D | E19: +1 | G19: = | H19: x 10 | L19: x 10 | N19: x 10 | O19: x 10 | R19: x 10
C20: Miniaturized | D20: -1D | E20: +1 | G20: = | H20: / 10 | L20: / 10 | N20: / 10 | O20: / 10 | R20: / 10
G22: kg | H22: % / sec | I22: kg | K22: g | L22: g | M22: m/s
B23: Jambes | D23: Indice | E23: Cout | G23: Masse | H23: Power | I23: Load | K23: Sprint | L23: Jump | M23: Speed | P23: Taille | Q23: Mass | R23: Load | S23: Scale
C24: Standard | D24: 3 | E24: 0 | G24: 30 | H24: 0 | I24: x 1 | K24: 0.5 | L24: 2 | M24: 5 | P24: -4 | Q24: 1 g | R24: 50 g | S24: x 50
C25: Athlétique | D25: 4 | E25: 0 | G25: 40 | H25: 0 | I25: x 3 | K25: 1 | L25: 3 | M25: 10 | P25: -3 | Q25: 100 g | R25: 1 kg | S25: x 10
C26: Transhumain | D26: 5 | E26: 1 | G26: 40 | H26: 1 | I26: x 5 | K26: 2 | L26: 5 | M26: 20 | P26: -2 | Q26: 1 kg | R26: 5 kg | S26: x 5
C27: Metahumain | D27: 6 | E27: 2 | G27: 40 | H27: 5 | I27: x 10 | K27: 5 | L27: 10 | M27: 40 | P27: -1 | Q27: 10 kg | R27: 20 kg | S27: x 2
C28: Speedrun | D28: 6 | E28: 3 | G28: 40 | H28: 5 | I28: x 1 | K28: 10 | L28: 5 | M28: 100 | P28: 0 | Q28: 100 kg | R28: 100 kg | S28: x 1
B29: Bio | C29: Cricket | P29: 1 | Q29: 1 t | R29: 500 kg | S29: / 2
C30: Spring | D30: 6 | E30: 3 | G30: 20 | H30: 5 | I30: x 1 | K30: 1 | L30: 20 | M30: 100 | P30: 2 | Q30: 10 t | R30: 2 t | S30: / 5
B31: Bio | C31: Cheetah | D31: 5 | E31: 1 | G31: 30 | H31: 0 | K31: 1 | L31: 5 | M31: 30 | P31: 3 | Q31: 100 t | R31: 10 t | S31: / 10
C32: Roues | E32: 0 | G32: 20 | H32: 1 | I32: x10 | K32: 1 | L32: 0 | M32: 100
C33: Chenilles | E33: 0 | G33: 20 | H33: 1 | I33: x100 | K33: 1 | L33: 0 | M33: 20
B34: Bio | C34: Spider | E34: 1 | H34: 0
E36: %corps | G36: % / sec | J36: degats | L36: m/s | M36: kJ
B37: Bras | D37: Cout | E37: Masse | G37: Power | H37: Lift | J37: Melee | L37: Swing | M37: Punch
C38: Standard | D38: 0 | E38: 3 | G38: 0 | H38: x 1 | J38: 0+ | L38: 10 | M38: 0.2
C39: Athlétique | D39: 0 | E39: 5 | G39: 0 | H39: x 3 | J39: 0+ | L39: 20 | M39: 1
C40: Transhumain | D40: 0 | E40: 10 | G40: 1 | H40: x 5 | J40: 1+ | L40: 50 | M40: 5
C41: Metahumain | D41: 1 | E41: 10 | G41: 2 | H41: x 10 | J41: 2+ | L41: 100 | M41: 50
B42: Bio | C42: Gorille | D42: 1 | E42: 20 | G42: 0 | H42: x 20 | J42: 1+ | L42: 20 | M42: 5
C43: Gunslinger | D43: 3 | E43: 10 | G43: 1 | H43: x 1 | J43: 0+ | L43: 10 | M43: 0.5
B44: Bio | C44: Mantis | D44: 3 | E44: 10 | G44: 2 | H44: x 1 | J44: 3+ | L44: 300 | M44: 500
C45: Tinker | D45: 1 | E45: 1 | G45: 0 | H45: x 1 | J45: 0+ | L45: 20 | M45: 0.2
C46: Heavy duty | D46: 0 | E46: 20 | G46: 1 | H46: x 100 | J46: 0+ | L46: 10 | M46: 1
B47: Bio | C47: Tentacule | D47: 0 | E47: 5 | G47: 1 | H47: x 1 | J47: 0+ | L47: 5 | M47: 0.1
G49: %total | H49: kW / kg | L49: g | M49: m/s
B50: Ailes | D50: Taille | E50: Cout | G50: Masse | H50: Power | K50: Turn | L50: Accel | M50: Speed
B51: Bio | C51: Venusien | D51: 0 | E51: 1 | G51: 0.3 | H51: 1 hour | K51: 90° | L51: 1 / 5 | M51: 40+ | O51: Accel : sustained / dive
B52: Bio | C52: Swan | D52: -1 | E52: 1 | G52: 0.3 | H52: 1 hour | K52: 90° | L52: 1 / 5 | M52: 30+ | O52: Dive : speed x 2
B53: Bio | C53: Falcon | D53: -2 | E53: 1 | G53: 0.3 | H53: 1 hour | K53: 90° | L53: 2 / 20 | M53: 40+
B54: Bio | C54: Hummingbird | D54: -3 | E54: 1 | G54: 0.3 | H54: 1 hour | K54: 90° | L54: 2 / 10 | M54: 10+
B55: Bio | C55: Dragonfly | D55: -4 | E55: 1 | H55: 1 hour | K55: 180° | L55: 5 / 10 | M55: 20
B57: Helices | D57: Taille | E57: Cout | G57: Masse | H57: Power | K57: Turn | L57: Accel | M57: Speed
C58: eVTOL | D58: 0 - 1 | E58: 2 | G58: 0.4 | H58: 10 min | K58: 180° | L58: 10 | M58: 100
C59: Helico | D59: 1 - 2 | E59: 2 | G59: 0.6 | H59: 1 hour | K59: 180° | L59: 0.5 | M59: 100
C60: Thopter | D60: -1 | E60: 2 | G60: 0.4 | H60: 10 min | K60: 180° | L60: 30 | M60: 100
C61: Minidrone | D61: -2 | E61: 2 | G61: 0.4 | H61: 10 min | K61: 180° | L61: 50 | M61: 30
C62: Microdrone | D62: -4 | E62: 2 | G62: 0.4 | H62: 10 min | K62: 180° | L62: 30 | M62: 20
B64: Rockets / jets | D64: Taille | E64: Cout | G64: Masse | H64: Power | I64: Load | K64: Turn | L64: Accel | M64: Speed
C65: Jet suit | D65: 0 | E65: 2 | G65: 0.3 | H65: 10 min | I65: x 1 | K65: 180° | L65: 0.5 | M65: 50
C66: Booster 'DDE' | D66: 1 | E66: 11 | G66: 0.3 | H66: 1 sec | I66: x 1 | K66: 45° | L66: 50 | M66: 100
C67: F-16 | D67: 2 | E67: 12 | G67: 0.6 | H67: 1 hour | I67: / 10 | K67: 90° | L67: 10 | M67: 1000
C68: Rocket | D68: 2+ | E68: 7+ | G68: 0.6 | H68: 10 sec | K68: 45° | L68: 20 | M68: 1000
C69: ICF - MH | D69: 3+ | E69: 13+ | G69: 0.3 | H69: 1 hour | K69: 45° | L69: 10 | M69: -
C70: Boeing | D70: 3 | G70: 1.3 | H70: 10 hour | K70: 45° | L70: 0.2 | M70: 300

Sheet Engines
C1: GW | D1: km/s | E1: kN | F1: kg/sec | G1: t | H1: kN / kg | I1: GW / t | K1: t | L1: g
C2: Power | D2: Ve | E2: Thrust | F2: Fuel | G2: Mass | H2: T / m | I2: P / m | K2: ship | L2: accel
B3: Supersonic jet | C3: 0.03 | D3: 1 | E3: 100 | F3: 150 | G3: 1 | H3: =E3/G3/1000 -> 0.1 | I3: =C3/G3 -> 0.03 | K3: 3 | L3: =E3/K3/10 -> 3.3333333
B4: Merlin 1D | C4: 2600 | D4: 3 | E4: =2*C4/D4*O4 -> 936 | F4: 274 | G4: 0.5 | H4: =E4/G4/1000 -> 1.872 | I4: =C4/G4 -> 5200 | K4: =G4*10 -> 5 | L4: =E4/K4/10 -> 18.72 | N4: n | O4: 0.54
B5: Raptor 2 | C5: 8000 | D5: 3.5 | E5: 2300 | F5: 705 | G5: 1.6 | H5: =E5/G5/1000 -> 1.4375 | I5: =C5/G5 -> 5000 | K5: =G5*10 -> 16 | L5: =E5/K5/10 -> 14.375
B6: Saturn V | C6: 20000 | D6: 2.5 | E6: 7740 | G6: 8.4 | H6: =E6/G6/1000 -> 0.92142857 | I6: =C6/G6 -> 2380.9524 | K6: =G6*10 -> 84 | L6: =E6/K6/10 -> 9.2142857
B7: MICFAM MH 1 | C7: 100 | D7: 400 | E7: 500 | F7: 2.2 | G7: 1 | H7: =E7/G7/1000 -> 0.5 | I7: =C7/G7 -> 100 | K7: =G7*10 -> 10 | L7: =E7/K7/10 -> 5
B8: MICFAM MH 2 | C8: 100 | D8: 200 | E8: 1000 | F8: 5 | G8: 1 | H8: =E8/G8/1000 -> 1 | I8: =C8/G8 -> 100 | K8: =G8*10 -> 10 | L8: =E8/K8/10 -> 10
B9: MICFAM MH 3 | C9: 100 | D9: 100 | E9: 2000 | F9: 20 | G9: 1 | H9: =E9/G9/1000 -> 2 | I9: =C9/G9 -> 100 | K9: =G9*10 -> 10 | L9: =E9/K9/10 -> 20
B10: MICFAM Cruise | C10: 100 | D10: 11000 | E10: =2*C10*1000/D10 -> 18.181818 | F10: =E10/D10 -> 0.0016528926 | G10: 1 | H10: =E10/G10/1000 -> 0.018181818 | I10: =C10/G10 -> 100 | K10: =G10*10 -> 10 | L10: =E10/K10/10 -> 0.18181818
B11: Epstein | C11: 5500 | D11: 11000 | E11: =2*C11*1000/D11 -> 1000 | F11: =E11/D11 -> 0.090909091 | G11: =C11/100 -> 55 | H11: =E11/G11/1000 -> 0.018181818 | I11: =C11/G11 -> 100 | K11: =G11*10 -> 550 | L11: =E11/K11/10 -> 0.18181818
B12: Booster DDE | C12: =G12*5000 -> 125 | D12: 5 | E12: =2*C12/D12*O12 -> 50 | F12: =E12/D12 -> 10 | G12: 0.025 | H12: =E12/G12/1000 -> 2 | I12: =C12/G12 -> 5000 | K12: 0.1 | L12: =E12/K12/10 -> 50 | N12: n | O12: 1
B13: Jet suit | C13: 0.0008 | E13: 1.4 | F13: =0.832/60*1.5 -> 0.0208 | G13: 0.0025 | H13: =E13/G13/1000 -> 0.56 | I13: =C13/G13 -> 0.32 | K13: 0.1 | L13: =E13/K13/10 -> 1.4
J15: Mass ratio | K15: 2 | M15: Wet mass | N15: 100 | P15: t
H16: kN / kg
B17: Gen T | C17: Tp (TW) | D17: Ve (km/s) | E17: T (kN) | F17: Fuel | G17: Mass (t) | H17: T / m | J17: dV (km/s) | K17: dV (c) | M17: accel (g) | P17: Horse power
B18: AM Beam MAX | C18: 500 | D18: 100000 | E18: 10000 | F18: D+A | G18: 10 | H18: =E18/G18 -> 1000 | J18: =$D18*LN($K$15) -> 69314.718 | K18: =$D18*LN($K$15)*1000/299792458 -> 0.23120901 | M18: =E18/$N$15/10 -> 10 | P18: =C18*1000000000/735 -> 6.8027211e+08
A19: =D19*E19/2/1000000 -> 500 | B19: ICF MAX | C19: 500 | D19: 10000 | E19: 100000 | F19: P | G19: 1000 | H19: =E19/G19 -> 100 | J19: =$D19*LN($K$15) -> 6931.4718 | K19: =$D19*LN($K$15)*1000/299792458 -> 0.023120901 | M19: =E19/$N$15/10 -> 100 | P19: =C19*1000000000/735 -> 6.8027211e+08
B20: Low gear | D20: 20000 | E20: 50000 | F20: P+H | H20: =E20/G20 -> #DIV/0! | J20: =$D20*LN($K$15) -> 13862.944 | K20: =$D20*LN($K$15)*1000/299792458 -> 0.046241802 | M20: =E20/$N$15/10 -> 50 | P20: =C20*1000000000/735 -> 0
B21: NSWR MAX | C21: 30 | D21: 4700 | E21: 13000 | F21: U | H21: =E21/G21 -> #DIV/0! | J21: =$D21*LN($K$15) -> 3257.7917 | K21: =$D21*LN($K$15)*1000/299792458 -> 0.010866824 | M21: =E21/$N$15/10 -> 13 | P21: =C21*1000000000/735 -> 40816327
B22: Orion MAX | C22: 39 | D22: 9800 | E22: 8000 | F22: P | G22: 8 | H22: =E22/G22 -> 1000 | J22: =$D22*LN($K$15) -> 6792.8424 | K22: =$D22*LN($K$15)*1000/299792458 -> 0.022658483 | M22: =E22/$N$15/10 -> 8 | P22: =C22*1000000000/735 -> 53061224
B23: ICF Exacting | C23: 10 | D23: 7000 | E23: =2*C23*1000000/D23 -> 2857.1429 | F23: P | G23: =C23/3 -> 3.3333333 | H23: =E23/G23 -> 857.14286 | J23: =$D23*LN($K$15) -> 4852.0303 | K23: =$D23*LN($K$15)*1000/299792458 -> 0.016184631 | M23: =E23/$N$15/10 -> 2.8571429 | P23: =C23*1000000000/735 -> 13605442
B24: Low gear | D24: 20000 | E24: 1050 | F24: P+H | H24: =E24/G24 -> #DIV/0! | J24: =$D24*LN($K$15) -> 13862.944 | K24: =$D24*LN($K$15)*1000/299792458 -> 0.046241802 | M24: =E24/$N$15/10 -> 1.05 | P24: =C24*1000000000/735 -> 0 | S24: =3000/40 -> 75 | T24: =3/40 -> 0.075
B25: ICF Stratios | C25: 42 | D25: 7000 | E25: =2*C25*1000000/D25 -> 12000 | F25: P | G25: =C25/3 -> 14 | H25: =E25/G25 -> 857.14286 | J25: =$D25*LN($K$15) -> 4852.0303 | K25: =$D25*LN($K$15)*1000/299792458 -> 0.016184631 | M25: =E25/$N$15/10 -> 12 | N25: 13h | P25: =C25*1000000000/735 -> 57142857
B26: Low gear | D26: 20000 | E26: =2*C25*1000000/D26 -> 4200 | F26: P+H | H26: =E26/G26 -> #DIV/0! | J26: =$D26*LN($K$15) -> 13862.944 | K26: =$D26*LN($K$15)*1000/299792458 -> 0.046241802 | M26: =E26/$N$15/10 -> 4.2 | P26: =C26*1000000000/735 -> 0
B27: AM Beam Stratios | C27: =D27*E27/2/1000000 -> 75 | D27: 50000 | E27: 3000 | F27: D+A | G27: 10 | H27: =E27/G27 -> 300 | J27: =$D27*LN($K$15) -> 34657.359 | K27: =$D27*LN($K$15)*1000/299792458 -> 0.11560451 | M27: =E27/$N$15/10 -> 3 | P27: =C27*1000000000/735 -> 1.0204082e+08
B28: ICF Nestor | C28: =D28*E28/2/1000000 -> 350 | D28: 7000 | E28: 100000 | F28: P | G28: =C28/3 -> 116.66667 | H28: =E28/G28 -> 857.14286 | J28: =$D28*LN($K$15) -> 4852.0303 | K28: =$D28*LN($K$15)*1000/299792458 -> 0.016184631 | M28: =E28/$N$15/10 -> 100 | N28: 13h | P28: =C28*1000000000/735 -> 4.7619048e+08
B29: Firefly | C29: 12 | D29: 12890 | E29: 1900 | H29: =E29/G29 -> #DIV/0! | J29: =$D29*LN($K$15) -> 8934.6672 | K29: =$D29*LN($K$15)*1000/299792458 -> 0.029802842 | M29: =E29/$N$15/10 -> 1.9 | P29: =C29*1000000000/735 -> 16326531
B30: Epstein | C30: 5.5 | D30: 11000 | E30: =2*C30*1000000/D30 -> 1000 | F30: D+T | G30: =C30/3 -> 1.8333333 | H30: =E30/G30 -> 545.45455 | J30: =$D30*LN($K$15) -> 7624.619 | K30: =$D30*LN($K$15)*1000/299792458 -> 0.025432991 | M30: =E30/$N$15/10 -> 1 | P30: =C30*1000000000/735 -> 7482993.2
B31: Epstein 2 | C31: 100 | D31: 19000 | E31: =2*C31*1000000/D31 -> 10526.316 | G31: =C31/3 -> 33.333333 | H31: =E31/G31 -> 315.78947
B32: AV:T | D32: 1000 | F32: D+H | H32: =E32/G32 -> #DIV/0! | J32: =$D32*LN($K$15) -> 693.14718 | K32: =$D32*LN($K$15)*1000/299792458 -> 0.0023120901 | M32: =E32/$N$15/10 -> 0 | P32: =C32*1000000000/735 -> 0
B33: Cruise | C33: 0.1 | E33: 245 | H33: =E33/G33 -> #DIV/0! | J33: =$D33*LN($K$15) -> 0 | K33: =$D33*LN($K$15)*1000/299792458 -> 0 | M33: =E33/$N$15/10 -> 0.245 | P33: =C33*1000000000/735 -> 136054.42
B34: Combat | C34: 2.5 | E34: 50000 | H34: =E34/G34 -> #DIV/0! | J34: =$D34*LN($K$15) -> 0 | K34: =$D34*LN($K$15)*1000/299792458 -> 0 | M34: =E34/$N$15/10 -> 50 | P34: =C34*1000000000/735 -> 3401360.5
B35: MI Fusion Icarus | C35: 8 | D35: 8922 | E35: =1.78*1000 -> 1780 | F35: D | H35: =E35/G35 -> #DIV/0! | J35: =$D35*LN($K$15) -> 6184.2591 | K35: =$D35*LN($K$15)*1000/299792458 -> 0.020628468 | M35: =E35/$N$15/10 -> 1.78 | P35: =C35*1000000000/735 -> 10884354
B36: Orion MAX | C36: 39 | D36: 9800 | E36: 8000 | F36: P | G36: 10 | H36: =E36/G36 -> 800 | J36: =$D36*LN($K$15) -> 6792.8424 | K36: =$D36*LN($K$15)*1000/299792458 -> 0.022658483 | M36: =E36/$N$15/10 -> 8 | P36: =C36*1000000000/735 -> 53061224
B37: Orion 10k | C37: 24 | D37: 120 | E37: 400000 | F37: D | G37: 3250 | H37: =E37/G37 -> 123.07692 | J37: =$D37*LN($K$15) -> 83.177662 | K37: =$D37*LN($K$15)*1000/299792458 -> 0.00027745081 | M37: =E37/$N$15/10 -> 400 | P37: =C37*1000000000/735 -> 32653061
B38: Orion 4k | C38: 1.6 | D38: 39 | E38: 80000 | F38: D | G38: 1700 | H38: =E38/G38 -> 47.058824 | J38: =$D38*LN($K$15) -> 27.03274 | K38: =$D38*LN($K$15)*1000/299792458 -> 9.0171515e-05 | M38: =E38/$N$15/10 -> 80 | P38: =C38*1000000000/735 -> 2176870.7
B39: Orion USAF | C39: 33 | D39: 33 | E39: 2000 | F39: D | G39: 3250 | H39: =E39/G39 -> 0.61538462 | J39: =$D39*LN($K$15) -> 22.873857 | K39: =$D39*LN($K$15)*1000/299792458 -> 7.6298974e-05 | M39: =E39/$N$15/10 -> 2 | P39: =C39*1000000000/735 -> 44897959
B40: Orion Fusion | C40: 10.7 | D40: 73 | E40: 292 | F40: D | G40: 200 | H40: =E40/G40 -> 1.46 | J40: =$D40*LN($K$15) -> 50.599744 | K40: =$D40*LN($K$15)*1000/299792458 -> 0.00016878258 | M40: =E40/$N$15/10 -> 0.292 | P40: =C40*1000000000/735 -> 14557823
B41: Orion Fission | C41: 5.7 | D41: 43 | E41: 263 | F41: U | H41: =E41/G41 -> #DIV/0! | J41: =$D41*LN($K$15) -> 29.805329 | K41: =$D41*LN($K$15)*1000/299792458 -> 9.9419875e-05 | M41: =E41/$N$15/10 -> 0.263 | P41: =C41*1000000000/735 -> 7755102
M42: =E42/$N$15/10 -> 0 | P42: =C42*1000000000/735 -> 0
B43: Gen G | C43: Tp (GW)
B44: Slough Fusion | D44: 50 | F44: D | H44: Small waste heat | J44: =$D44*LN($K$15) -> 34.657359 | K44: =$D44*LN($K$15)*1000/299792458 -> 0.00011560451 | M44: =E44/$N$15/10 -> 0 | P44: =C44*1000000000/735 -> 0
B45: Cruise | C45: =2.6/1000 -> 0.0026 | E45: 0.1 | J45: =$D45*LN($K$15) -> 0 | K45: =$D45*LN($K$15)*1000/299792458 -> 0 | M45: =E45/$N$15/10 -> 0.0001 | P45: =C45*1000000000/735 -> 3537.415
B46: Combat | C46: 0.3 | E46: 14 | J46: =$D46*LN($K$15) -> 0 | K46: =$D46*LN($K$15)*1000/299792458 -> 0 | M46: =E46/$N$15/10 -> 0.014 | P46: =C46*1000000000/735 -> 408163.27
B47: MT Fusion THIO | D47: 760 | F47: D | J47: =$D47*LN($K$15) -> 526.79186 | K47: =$D47*LN($K$15)*1000/299792458 -> 0.0017571885 | M47: =E47/$N$15/10 -> 0 | P47: =C47*1000000000/735 -> 0
B48: 40 Hz pulses | C48: =25 -> 25 | E48: 66 | J48: =$D48*LN($K$15) -> 0 | K48: =$D48*LN($K$15)*1000/299792458 -> 0 | M48: =E48/$N$15/10 -> 0.066 | P48: =C48*1000000000/735 -> 34013605
B49: 200 Hz pulses | C49: 128 | E49: 340 | J49: =$D49*LN($K$15) -> 0 | K49: =$D49*LN($K$15)*1000/299792458 -> 0 | M49: =E49/$N$15/10 -> 0.34 | P49: =C49*1000000000/735 -> 1.7414966e+08
J50: =$D50*LN($K$15) -> 0 | K50: =$D50*LN($K$15)*1000/299792458 -> 0 | M50: =E50/$N$15/10 -> 0 | P50: =C50*1000000000/735 -> 0
B51: IC Fusion D-T | C51: =20 -> 20 | D51: 170 | E51: 240 | F51: D+T | J51: =$D51*LN($K$15) -> 117.83502 | K51: =$D51*LN($K$15)*1000/299792458 -> 0.00039305532 | M51: =E51/$N$15/10 -> 0.24 | P51: =C51*1000000000/735 -> 27210884
B52: IC Fusion D-D | C52: 0.1 | D52: 78 | E52: 3 | F52: D | J52: =$D52*LN($K$15) -> 54.06548 | K52: =$D52*LN($K$15)*1000/299792458 -> 0.00018034303 | M52: =E52/$N$15/10 -> 0.003 | P52: =C52*1000000000/735 -> 136054.42

Sheet MICFAM
B2: =1/500 -> 0.002
C4: F=ve​P​=1.5×1053.8×1012​=25.3×106N=25.3MN
C5: a=mF​=300,00025.3×106​=84.3m/s2≈8.6g
A8: COMBAT MODE | L8: FOR 10 SECONDS BURST
B9: Power | C9: P | D9: 5 | E9: TW | F9: =D9*10^12 -> 5000000000000 | H9: MICFAM | I9: 100 | J9: MW/kg | K9: Engine | M9: Thrust | O9: Delta v | Q9: Heatsink | S9: Fuel | U9: Delta v | W9: Heat | Y9: Fuel
B10: Exhaust velocity | C10: Ve | D10: 400 | E10: kms | F10: =D10*10^3 -> 400000 | I10: =I9/1000 -> 0.1 | J10: TW/t | M10: 10 | N10: g | O10: 10 | P10: km/r | Q10: 15 | R10: % | S10: 15 | T10: % | U10: 1 | V10: km/s | W10: 1 | X10: TJ | Y10: 2 | AA10: t
B11: Nozzle eff | C11: n | D11: 0.99 | E11: ratio | I11: =D9*10 -> 50 | J11: t | M11: 5 | N11: g | O11: =$M11/$M$10*O$10 -> 5 | P11: km/r | Q11: =$M11/$M$10*Q$10 -> 7.5 | R11: % | S11: =$M11/$M$10*S$10 -> 7.5 | T11: % | U11: =$M11/$M$10*U$10 -> 0.5 | W11: =$M11/$M$10*W$10 -> 0.5 | Y11: =$M11/$M$10*Y$10 -> 1
A12: F = 2Pn / Ve | B12: Thrust | C12: F | D12: =2*F9*D11/F10*10^-6 -> 24.75 | E12: MN | M12: 2 | N12: g | O12: =$M12/$M$10*O$10 -> 2 | P12: km/r | Q12: =$M12/$M$10*Q$10 -> 3 | R12: % | S12: =$M12/$M$10*S$10 -> 3 | T12: % | U12: =$M12/$M$10*U$10 -> 0.2 | W12: =$M12/$M$10*W$10 -> 0.2 | Y12: =$M12/$M$10*Y$10 -> 0.4
B13: Ship mass | C13: m | D13: 500 | E13: t | H13: MH | I13: 15 | J13: t | M13: 1 | N13: g | O13: =$M13/$M$10*O$10 -> 1 | P13: km/r | Q13: =$M13/$M$10*Q$10 -> 1.5 | R13: % | S13: =$M13/$M$10*S$10 -> 1.5 | T13: % | U13: =$M13/$M$10*U$10 -> 0.1 | W13: =$M13/$M$10*W$10 -> 0.1 | Y13: =$M13/$M$10*Y$10 -> 0.2
B14: Acceleration | C14: a | D14: =F14/9.81 -> 5.0458716 | E14: g | F14: =D12*10^6/(D13*10^3) -> 49.5 | G14: m/s² | H14: LiH | I14: 10 | J14: t | K14: Heat sink
F15: =5*550/D13*D9/4 -> 6.875 | I15: 20 | J15: MJ / kg
A16: m = F / Ve | B16: Mass flow | C16: m | D16: =(D12*10^6)/(D10*10^3) -> 61.875 | E16: kg/s | I16: =(I14*10^3)*I15*10^-6 -> 0.2 | J16: TJ
B17: Brayton cycle | D17: 35 | E17: %
B18: Waste heat | C18: h | D18: =D9*(1-D11)* (100-D17)/100 * 10^3 -> 32.5 | E18: GW = GJ/s | F18: =D21/D9 -> 0.12375
H19: ETHER | I19: 1 | J19: t | K19: Radiator
B20: burn time | C20: t | D20: 10 | E20: s | F20: =F14*D20/1000 -> 0.495 | G20: km/s | I20: 200 | J20: MW/t
B21: fuel used | C21: m | D21: =D16*D20*10^-3 -> 0.61875 | E21: t | F21: =D21/I13*100 -> 4.125 | G21: % fuel tank | I21: =I19*I20 -> 200 | J21: MW
B22: waste heat | C22: h | D22: =D18*D20*10^-3 -> 0.325 | E22: TJ | F22: =D22/I16*100 -> 162.5 | G22: % of heat sink | I22: =I21*10^-3 -> 0.2 | J22: GW
B23: speed | C23: delta v | D23: =F14*10^-3*D20 -> 0.495 | E23: km/s | I23: =I22*10^-3 -> 0.0002 | J23: TW
B24: displacement | C24: d | D24: =1/2 * F14* D20^2 * 10^-3 -> 2.475 | E24: km
I25: =I22*540 -> 108
A27: CRUISE MODE
B28: Power | C28: P | D28: 5 | E28: TW | F28: =D28*10^12 -> 5000000000000 | H28: =60*60*24 -> 86400 | J28: =D28/D32*30 -> 0.3
B29: Exhaust velocity | C29: Ve | D29: 10000 | E29: kms | F29: =D29*10^3 -> 10000000 | H29: D | I29: 25 | J29: t | Q29: AU | R29: 0.1 | S29: 1 | T29: 2 | U29: 3 | V29: 4 | W29: 5 | X29: 10 | Y29: 15 | Z29: 20
B30: Nozzle eff | C30: n | D30: 0.99 | E30: ratio | L30: Accel phase | N30: 10 | O30: j | R30: =2* sqrt(R29*1.496*10^11 / ($F$33)) / 86400 -> 2.0120995 | S30: =2* sqrt(S29*1.496*10^11 / ($F$33)) / 86400 -> 6.3628173 | T30: =2* sqrt(T29*1.496*10^11 / ($F$33)) / 86400 -> 8.9983826 | U30: =2* sqrt(U29*1.496*10^11 / ($F$33)) / 86400 -> 11.020723 | V30: =2* sqrt(V29*1.496*10^11 / ($F$33)) / 86400 -> 12.725635 | W30: =2* sqrt(W29*1.496*10^11 / ($F$33)) / 86400 -> 14.227692 | X30: =2* sqrt(X29*1.496*10^11 / ($F$33)) / 86400 -> 20.120995 | Y30: =2* sqrt(Y29*1.496*10^11 / ($F$33)) / 86400 -> 24.643086 | Z30: =2* sqrt(Z29*1.496*10^11 / ($F$33)) / 86400 -> 28.455384 | AA30: d
A31: F = 2Pn / Ve | B31: Thrust | C31: F | D31: =2*F28*D30/F29*10^-6 -> 0.99 | E31: MN | I31: 0.5 | J31: g | L31: delta v | N31: =F34*N30 -> 1710.72 | O31: km/s | R31: =$G$35*R30 -> 17.210694 | S31: =$G$35*S30 -> 54.424994 | T31: =$G$35*T30 -> 76.968565 | U31: =$G$35*U30 -> 94.266855 | V31: =$G$35*V30 -> 108.84999 | W31: =$G$35*W30 -> 121.69799 | X31: =$G$35*X30 -> 172.10694 | Y31: =$G$35*Y30 -> 210.7871 | Z31: =$G$35*Z30 -> 243.39597 | AA31: % fuel
B32: Ship mass | C32: m | D32: 500 | E32: t | I32: =I31*10 -> 5 | J32: m/s | N32: =N31*3600*24/(150*10^6) -> 0.98537472 | O32: AU/j | Q32: AU | R32: 0.1 | S32: 1 | T32: 2 | U32: 3 | V32: 4 | W32: 5 | X32: 10 | Y32: 15 | Z32: 20
B33: Acceleration | C33: a | D33: =F33/9.81 -> 0.20183486 | E33: g | F33: =D31*10^6/(D32*10^3) -> 1.98 | G33: m/s² | I33: =I32*D32*10^-3 -> 2.5 | J33: MN | L33: distance | N33: =1/2*N31*N30*3600*24/(150*10^6) -> 4.9268736 | O33: AU | R33: =(R29-$N$33*2)/$N$32 + $N$30 * 2 -> 10.101484 | S33: =(S29-$N$33*2)/$N$32 + $N$30 * 2 -> 11.014842 | T33: =(T29-$N$33*2)/$N$32 + $N$30 * 2 -> 12.029685 | U33: =(U29-$N$33*2)/$N$32 + $N$30 * 2 -> 13.044527 | V33: =(V29-$N$33*2)/$N$32 + $N$30 * 2 -> 14.059369 | W33: =(W29-$N$33*2)/$N$32 + $N$30 * 2 -> 15.074212 | X33: =(X29-$N$33*2)/$N$32 + $N$30 * 2 -> 20.148424 | Y33: =(Y29-$N$33*2)/$N$32 + $N$30 * 2 -> 25.222635 | Z33: =(Z29-$N$33*2)/$N$32 + $N$30 * 2 -> 30.296847 | AA33: d
F34: =F33*86400*10^-3 -> 171.072 | G34: km/s/j | I34: =I33*F29 / (2*D30*10^-6) * 10^-12 -> 12.626263 | J34: TW | L34: fuel used | N34: =G35*N30 -> 85.536 | O34: % | R34: =min($N$34*2,R31) -> 17.210694 | S34: =min($N$34*2,S31) -> 54.424994 | T34: =min($N$34*2,T31) -> 76.968565 | U34: =min($N$34*2,U31) -> 94.266855 | V34: =min($N$34*2,V31) -> 108.84999 | W34: =min($N$34*2,W31) -> 121.69799 | X34: =min($N$34*2,X31) -> 171.072 | Y34: =min($N$34*2,Y31) -> 171.072 | Z34: =min($N$34*2,Z31) -> 171.072 | AA34: % fuel
A35: m = F / Ve | B35: Mass flow | C35: m | D35: =(D31*10^6)/(D29*10^3) -> 0.099 | E35: kg/s | G35: =D35*86400*10^-3 -> 8.5536 | H35: t/j
B36: Brayton cycle | D36: 35 | E36: %
B37: Waste heat | C37: h | D37: =D28*(1-D30)* (100-D36)/100 * 10^3 -> 32.5 | E37: GW = GJ/s | F37: =D37*10^3 -> 32500 | G37: GW
L38: mass ratio | N38: 1.5
B39: burn time | C39: t | D39: 0.1 | E39: s | G39: =G35/D28 -> 1.71072 | L39: Total delta v | N39: =D29*ln(N38) -> 4054.6511 | O39: km/s
B40: fuel used | C40: m | D40: =D35*D39*10^-3 -> 9.9e-06 | E40: t | I40: =I29/G35 -> 2.922746 | J40: j | N40: =N39*3600*24/(150*10^6) -> 2.335479 | O40: AU/j
B41: waste heat | C41: h | D41: =D37*D39-I23*D39 -> 3.24998 | E41: TJ
B42: speed | C42: delta v | D42: =F33*10^-3*D39 -> 0.000198 | E42: km/s | G42: =D42*24/D43 -> 0.0010527572 | H42: km/s/j
B43: time to cool | C43: cd | D43: =D41/$I$23/60/60 -> 4.5138611 | E43: h
A46: ANTIMATTER MODE
B47: Power | C47: P | D47: 5 | E47: TW | F47: =D47*10^12 -> 5000000000000
B48: Exhaust velocity | C48: Ve | D48: 50000 | E48: kms | F48: =D48*10^3 -> 50000000
B49: Nozzle eff | C49: n | D49: 0.99 | E49: ratio | L49: Accel phase | N49: 300 | O49: j | R49: =N49/360 -> 0.83333333
A50: F = 2Pn / Ve | B50: Thrust | C50: F | D50: =2*F47*D49/F48*10^-6 -> 0.198 | E50: MN | L50: delta v | N50: =F52*N49 -> 118.8 | O50: km/s
B51: Ship mass | C51: m | D51: 500 | E51: t | N51: =N50*3600*24/(150*10^6) -> 0.0684288 | O51: AU/j
B52: Acceleration | C52: a | D52: =F52/9.81 -> 0.040366972 | E52: g | F52: =D50*10^6/(D51*10^3) -> 0.396 | G52: m/s² | L52: distance | N52: =1/2*N50*N49*3600*24/(150*10^6) -> 10.26432 | O52: AU
L53: fuel used | N53: =G54*N49 -> 102.6432 | O53: %
A54: m = F / Ve | B54: Mass flow | C54: m | D54: =(D50*10^6)/(D48*10^3) -> 0.00396 | E54: kg/s | G54: =D54*86400*10^-3 -> 0.342144 | H54: t/j
B55: Brayton cycle | D55: 35 | E55: %
B56: Waste heat | C56: h | D56: =D47*(1-D49)* (100-D55)/100 * 10^3 -> 32.5 | E56: GW = GJ/s
B58: burn time | C58: t | D58: 1000 | E58: s | L58: mass ratio | N58: 3
B59: fuel used | C59: m | D59: =D54*D58*10^-3 -> 0.00396 | E59: t | L59: Total delta v | N59: =D48*ln(N58) -> 54930.614 | O59: km/s
B60: waste heat | C60: h | D60: =D55*D58-I43*D58 -> 35000 | E60: TJ | N60: =N59*3600*24/(150*10^6) -> 31.640034 | O60: AU/j
B61: speed | C61: delta v | D61: =F52*10^-3*D58 -> 0.396 | E61: km/s | F61: =D61*3600*24/(150*10^6) -> 0.000228096 | G61: AU/j | H61: =D61/300000 -> 1.32e-06 | I61: c | N61: =N59/300000 -> 0.18310205 | O61: c
B62: time to cool | C62: cd | D62: =D60/$I$23/60/60 -> 48611.111 | E62: h
A64: E = P * t | B64: Energy needed | C64: E | D64: =D47*D58 -> 5000 | E64: TJ | F64: =1.8*10^2 -> 180 | G64: TJ (for 1g of matter + 1g of antimatter)
B65: Antimatter needed | C65: m | D65: =D64/F64 -> 27.777778 | E65: g

Sheet Batterie humaine
M2: Target mass | N2: 100 | O2: kg | S2: energy | U2: a | W2: carry
C3: Cooling : continuous 2 kW, burst 10 kW (vapor). (100 - 500 W/m²K) | L3: 5 | M3: Muscles | N3: 50 | O3: % | Q3: =N3/100*$C$18 -> 50 | R3: kg | S3: =Q3*0.02 -> 1 | T3: MW | U3: =$C$38/3*Q3/Q9 /10 -> 50 | V3: g | W3: =Q3*4-Q9 -> 100 | X3: kg
L4: 4 | M4: CPU | N4: 10 | O4: % | Q4: =N4/100*$C$18 -> 10 | R4: kg | S4: =Q4/50 -> 0.2 | T4: MW
B5: h (passive) | C5: 0.5 | D5: kW/m² K | G5: Q_conv | H5: =C5*C12*C8 -> 20 | I5: kW | J5: Q_conv = h · A · ΔT | M5: Bones | N5: 15 | O5: % | Q5: =N5/100*$C$18 -> 15 | R5: kg
B6: h (active) | C6: 1 | D6: kW/m² K | G6: Q_conv | H6: =C6*C12*C8 -> 40 | I6: kW | M6: Organs | N6: 15 | O6: % | Q6: =N6/100*$C$18 -> 15 | R6: kg
G7: structure | H7: =0.002*C12*1000 -> 4 | I7: kg | J7: 2 mm CNM | M7: Battery | N7: 10 | O7: % | Q7: =N7/100*$C$18 -> 10 | R7: kg | S7: =0.25*Q7 -> 2.5 | T7: MJ
B8: ΔT | C8: 20 | D8: K | G8: cooling | H8: =C12*4 -> 8 | I8: kg
M9: Actual | Q9: =sum(Q3:Q7) -> 100 | R9: kg
J11: 100 | K11: W | M11: Target mass | N11: 200 | O11: kg | S11: energy | U11: a | W11: carrying cap
B12: Factor | C12: 2 | H12: =C13+C14+C15+C16 -> 25 | I12: kg | J12: =100*60/1000 -> 6 | K12: kJ / min | L12: 6 | M12: Muscles | N12: 50 | O12: % | Q12: =N12/100*$N$11 -> 100 | R12: kg | S12: =Q12*0.02 -> 2 | T12: MW | U12: =$C$38/3*Q12/Q19 /10 -> 50 | V12: g | W12: =Q12*4-Q19 -> 200 | X12: kg
B13: Hardware | C13: =C12/2 -> 1 | D13: kg | F13: energy | J13: =J12*60/1000 -> 0.36 | K13: MJ / h | L13: 4 | M13: CPU | N13: 10 | O13: % | Q13: =N13/100*$N$11 -> 20 | R13: kg | S13: =Q13/50 -> 0.4 | T13: MW
B14: Water | C14: =C12*3 -> 6 | D14: kg | E14: 2500 | F14: kJ / kg | H14: =E14/1000*C14 -> 15 | I14: MJ | J14: =H15/J13 -> 14 | K14: h | M14: Bones | N14: 10 | O14: % | Q14: =N14/100*$N$11 -> 20 | R14: kg
B15: Graphene | C15: =7*C12 -> 14 | D15: kg | E15: =100*3600/1000 -> 360 | F15: kW / kg | H15: =E15/1000*C15 -> 5.04 | I15: MJ | J15: =J14*60 -> 840 | K15: min | M15: Organs | N15: 10 | O15: % | Q15: =N15/100*$N$11 -> 20 | R15: kg
B16: Fat | C16: =C12*2 -> 4 | D16: kg | E16: =10500*360/1000 -> 3780 | F16: kW / kg | H16: =E16/1000*C16 -> 15.12 | I16: MJ
M17: Battery | N17: 20 | O17: % | Q17: =N17/100*$N$11 -> 40 | R17: kg | S17: =0.25*Q17 -> 10 | T17: MJ
B18: Total mass | C18: 100 | D18: kg
B19: Muscles | C19: 50 | D19: % | F19: =C19/100*$C$18 -> 50 | G19: kg | M19: Actual | Q19: =sum(Q12:Q17) -> 200 | R19: kg
B20: CPU | C20: 10 | D20: % | F20: =C20/100*$C$18 -> 10 | G20: kg
B21: Bones | C21: 15 | D21: % | F21: =C21/100*$C$18 -> 15 | G21: kg | M21: Target mass | N21: 100 | O21: kg | S21: energy | U21: a | W21: carrying cap
B22: Organs | C22: 15 | D22: % | F22: =C22/100*$C$18 -> 15 | G22: kg | L22: 4 | M22: Muscles | N22: 50 | O22: % | Q22: =N22/100*$N$21 -> 50 | R22: kg | S22: =Q22*0.02 -> 1 | T22: MW | U22: =$C$38/3*Q22/Q28 /10 -> 33.333333 | V22: g | W22: =Q22*4-Q28 -> 50 | X22: kg
B23: Battery | C23: 20 | D23: % | F23: =C23/100*$C$18 -> 20 | G23: kg | L23: 5 | M23: CPU | N23: 50 | O23: % | Q23: =N23/100*$N$21 -> 50 | R23: kg | S23: =Q23/50 -> 1 | T23: MW
M24: Bones | N24: 15 | O24: % | Q24: =N24/100*$N$21 -> 15 | R24: kg
B25: Muscle mass | C25: =C19/100*C18 -> 50 | D25: kg | E25: athlete | M25: Organs | N25: 15 | O25: % | Q25: =N25/100*$N$21 -> 15 | R25: kg
B26: Muscles (aggro) | C26: 50 | D26: kW/kg | E26: peak | F26: 0.1 | G26: kW/kg | H26: =$C$25*C26/1000 -> 2.5 | I26: MW | M26: Battery | N26: 20 | O26: % | Q26: =N26/100*$N$21 -> 20 | R26: kg | S26: =0.25*Q26 -> 5 | T26: MJ
B27: Muscles (high) | C27: 10 | D27: kW/kg | E27: sust | F27: 0.02 | G27: kW/kg | H27: =$C$25*C27/1000 -> 0.5 | I27: MW
B28: Muscles (low) | C28: 1 | D28: kW/kg | M28: Actual | Q28: =sum(Q22:Q26) -> 150 | R28: kg
B30: CPU mass | C30: =C20/100*C18 -> 10 | D30: kg | H30: =C30*C31/1000 -> 1 | I30: MW
B31: CPU (high) | C31: 100 | D31: kW/kg | M31: Target mass | N31: 200 | O31: kg | S31: energy | U31: a | W31: carrying cap
B32: CPU (low) | C32: 1 | D32: kW/kg | L32: 5 | M32: Muscles | N32: 50 | O32: % | Q32: =N32/100*$N$31 -> 100 | R32: kg | S32: =Q32*0.02 -> 2 | T32: MW | U32: =$C$38/3*Q32/Q38 /10 -> 33.333333 | V32: g | W32: =Q32*4-Q38 -> 100 | X32: kg
L33: 6 | M33: CPU | N33: 50 | O33: % | Q33: =N33/100*$N$31 -> 100 | R33: kg | S33: =Q33/50 -> 2 | T33: MW
B34: Max discharge | C34: 1000 | D34: kW/kg | H34: =C34*C15/1000 -> 14 | I34: MW | M34: Bones | N34: 15 | O34: % | Q34: =N34/100*$N$31 -> 30 | R34: kg
M35: Organs | N35: 15 | O35: % | Q35: =N35/100*$N$31 -> 30 | R35: kg
B36: Average | C36: 1500 | D36: N/kg | M36: Battery | N36: 20 | O36: % | Q36: =N36/100*$N$31 -> 40 | R36: kg | S36: =0.25*Q36 -> 10 | T36: MJ
B37: Athletic | C37: 2000 | D37: N/kg | G37: legs | H37: =C37*C19/1000*0.3 -> 30 | I37: kN
B38: Force | C38: 3000 | D38: N/kg | G38: hold | H38: =C38*C19/9.80665/1000 -> 15.295743 | I38: t | J38: =C27*1000/C38 -> 3.3333333 | K38: m/s | M38: Actual | Q38: =sum(Q32:Q36) -> 300 | R38: kg
B39: Structure | G39: limit | H39: =H38/3 -> 5.0985811 | I39: t | J39: ARBITRARY
B41: P | C41: =F19*C27*1000 -> 500000 | D41: W | G41: Speed | H41: =(2*C41*C42 / (C43*C44))^(1/3) -> 142.87698 | I41: m/s | J41: v=​(2Pη / (ρCd​A))^1/3 | M41: Target mass | N41: 400 | O41: kg | S41: energy | U41: a | W41: carrying cap
B42: η | C42: 0.7 | D42: (efficiency) | H42: =H41*3.6 -> 514.35713 | I42: km/h | L42: 7 | M42: Muscles | N42: 50 | O42: % | Q42: =N42/100*$N$41 -> 200 | R42: kg | S42: =Q42*0.02 -> 4 | T42: MW | U42: =$C$38/3*Q42/Q48 /10 -> 50 | V42: g | W42: =Q42*4-Q48 -> 400 | X42: kg
B43: ρ | C43: 1.2 | D43: kg/m3 (air density) | L43: 5 | M43: CPU | N43: 10 | O43: % | Q43: =N43/100*$N$41 -> 40 | R43: kg | S43: =Q43/50 -> 0.8 | T43: MW
B44: CdA | C44: 0.2 | D44: m² (aerodynamism) | M44: Bones | N44: 10 | O44: % | Q44: =N44/100*$N$41 -> 40 | R44: kg
M45: Organs | N45: 10 | O45: % | Q45: =N45/100*$N$41 -> 40 | R45: kg
B46: F (legs) | C46: =C38*F19/2 -> 75000 | D46: N | G46: a | H46: =C46/C47 -> 750 | I46: m/s² | J46: a = F/m | M46: Battery | N46: 20 | O46: % | Q46: =N46/100*$N$41 -> 80 | R46: kg | S46: =0.25*Q46 -> 20 | T46: MJ
B47: m | C47: =C18 -> 100 | D47: kg | H47: =H46/10 -> 75 | I47: g
M48: Actual | Q48: =sum(Q42:Q46) -> 400 | R48: kg
B49: Total mass | C49: 100 | D49: kg
B50: strength | C50: 5000 | D50: N/kg | G50: Fmax | H50: =C51*C50 -> 150000 | I50: N
B51: legs muscles | C51: =C49* 0.3 -> 30 | D51: kg | G51: Pmax | H51: =C52*C51 -> 3000 | I51: W | M51: Target mass | N51: 100 | O51: kg | S51: energy | U51: a | W51: carrying cap
B52: power | C52: 100 | D52: W/kg | G52: Vmax | H52: =H51/(C54*H50) -> 0.066666667 | I52: m/s | L52: 3 | M52: Muscles | N52: 50 | O52: % | Q52: =N52/100*$N$51 -> 50 | R52: kg | S52: =Q52*0.02 -> 1 | T52: MW | U52: =$C$38/3*Q52/Q58 /10 -> 25 | V52: g | W52: =Q52*4-Q58 -> 0 | X52: kg
G53: peak | H53: =H50/C49 -> 1500 | I53: m/s² | L53: 6 | M53: CPU | N53: 100 | O53: % | Q53: =N53/100*$N$51 -> 100 | R53: kg | S53: =Q53/50 -> 2 | T53: MW
B54: α | C54: 0.3 | H54: =H53/10 -> 150 | I54: g | M54: Bones | N54: 10 | O54: % | Q54: =N54/100*$N$51 -> 10 | R54: kg
A55: elite | B55: sprint | C55: 10 | D55: m/s | E55: human leg | G55: sprint force | H55: =H50/30 -> 5000 | I55: N | M55: Organs | N55: 10 | O55: % | Q55: =N55/100*$N$51 -> 10 | R55: kg
B56: accel | C56: 10 | D56: m/s² | G56: accel | H56: =H55/C49 -> 50 | I56: m/s² | M56: Battery | N56: 30 | O56: % | Q56: =N56/100*$N$51 -> 30 | R56: kg | S56: =0.25*Q56 -> 7.5 | T56: MJ
B57: arm speed | C57: 40 | D57: m/s | G57: jump force | H57: =H55*3 -> 15000 | I57: N
E58: cyber leg | G58: sprint force | H58: =H50/15 -> 10000 | I58: N | M58: Actual | Q58: =sum(Q52:Q56) -> 200 | R58: kg
G59: accel | H59: =H58/C49 -> 100 | I59: m/s²
B60: Skeletal muscle | C60: =C61*1000 -> 300000 | D60: N/m² | G60: jump force | H60: =H58*3 -> 30000 | I60: N
C61: 300 | D61: N/kg | M61: Target mass | N61: 80 | O61: kg | S61: energy | U61: a | W61: carrying cap
B62: drone | C62: 10000 | D62: N/kg | G62: k | H62: 0.1 | L62: 4 | M62: Muscles | N62: 40 | O62: % | Q62: =N62/100*$N$61 -> 32 | R62: kg | S62: =Q62*0.02 -> 0.64 | T62: MW | U62: =$C$38/3*Q62/Q68 /10 -> 40 | V62: g | W62: =Q62*4-Q68 -> 48 | X62: kg
G63: scaled F/W | H63: =C60*C65/C64/10*1/H62 -> 90 | L63: 4 | M63: CPU | N63: 10 | O63: % | Q63: =N63/100*$N$61 -> 8 | R63: kg | S63: =Q63/50 -> 0.16 | T63: MW
B64: density | C64: 1000 | D64: kg/m3 | M64: Bones | N64: 15 | O64: % | Q64: =N64/100*$N$61 -> 12 | R64: kg
B65: f | C65: 0.3 | E65: V | G65: by mass | H65: F/W (lift) nature | J65: real | K65: eq | M65: Organs | N65: 15 | O65: % | Q65: =N65/100*$N$61 -> 12 | R65: kg
A66: 100 | B66: L (human) | C66: 1.7 | D66: m | E66: =2*1*1 -> 2 | F66: m3 | G66: =(A66/1000)^(1/3) -> 0.46415888 | H66: =sqrt(K66) -> 2.300895 | I66: x body weight | J66: 3 | K66: =C60*C65/C64/10*1/C66 -> 5.2941176 | M66: Battery | N66: 20 | O66: % | Q66: =N66/100*$N$61 -> 16 | R66: kg | S66: =0.25*Q66 -> 4 | T66: MJ
A67: 1 | B67: L (mouse) | C67: 0.1 | D67: m | E67: =C67^3 -> 0.001 | F67: m3 | G67: =(A67/1000)^(1/3) -> 0.1 | H67: =sqrt(K67) -> 9.486833 | I67: x body weight | J67: 10 | K67: =C60*C65/C64/10*1/C67 -> 90
A68: 0.1 | B68: L (ant) | C68: 0.003 | D68: m | E68: =C68^3 -> 2.7e-08 | F68: m3 | G68: =(A68/1000)^(1/3) -> 0.046415888 | H68: =sqrt(K68) -> 54.772256 | I68: x body weight | J68: 50 | K68: =C60*C65/C64/10*1/C68 -> 3000 | M68: Actual | Q68: =sum(Q62:Q66) -> 80 | R68: kg
A69: 1000 | B69: L (elephant) | C69: 3 | D69: m | E69: =3*3*2 -> 18 | F69: m3 | G69: =(A69/1000)^(1/3) -> 1 | H69: =sqrt(K69) -> 1.7320508 | I69: x body weight | J69: 2 | K69: =C60*C65/C64/10*1/C69 -> 3
A70: 1000 | B70: L (power) | C70: 3 | D70: m | E70: =2.5*2*1 -> 5 | F70: m3 | G70: =(A70/1000)^(1/3) -> 1 | H70: =sqrt(K70) -> 1.7320508 | I70: x body weight | K70: =C$60*C65/C64/10*1/C70 -> 3
A71: 10000 | B71: L (tank) | C71: 5 | D71: m | E71: =5*2*2 -> 20 | F71: m3 | G71: =(A71/1000)^(1/3) -> 2.1544347 | H71: =sqrt(K71) -> 1.3416408 | I71: x body weight | K71: =C$60*C65/C64/10*1/C71 -> 1.8 | M71: Target mass | N71: 200 | O71: kg | P71: Others | R71: kg | S71: energy | U71: a | W71: carrying cap
A72: 10 | B72: L (dog) | C72: 0.5 | D72: m | G72: =(A72/1000)^(1/3) -> 0.21544347 | M72: Muscles | N72: 65 | O72: % | Q72: =N72/100*$N$71 -> 130 | R72: kg | S72: =Q72*0.02 -> 2.6 | T72: MW | U72: =$C$38/3*Q72/Q78 /10 -> 65 | V72: g | W72: =Q72*4-Q78 -> 320 | X72: kg
M73: CPU | N73: 5 | O73: % | Q73: =N73/100*$N$71 -> 10 | R73: kg | S73: =Q73/50 -> 0.2 | T73: MW
M74: Structure | N74: 10 | O74: % | Q74: =N74/100*$N$71 -> 20 | R74: kg | W74: =Q74*10 -> 200 | X74: kg
B75: Total mass | C75: 1000 | D75: kg | M75: Organs | N75: 5 | O75: % | Q75: =N75/100*$N$71 -> 10 | R75: kg
B76: strength | C76: 6000 | D76: N/kg | G76: Fmax | H76: =C77*C76 -> 1200000 | I76: N | M76: Battery | N76: 15 | O76: % | Q76: =N76/100*$N$71 -> 30 | R76: kg | S76: =0.25*Q76 -> 7.5 | T76: MJ
B77: legs muscles | C77: =C75/5 -> 200 | D77: kg | G77: Pmax | H77: =C78*C77 -> 2000000 | I77: W
B78: power | C78: 10000 | D78: W/kg | G78: Vmax | H78: =H77/(C80*H76) -> 5.5555556 | I78: m/s | M78: Actual | N78: =N72+N73+N74+N75+N76 -> 100 | O78: % | Q78: =sum(Q71:Q76) -> 200 | R78: kg
G79: peak | H79: =H76/C75 -> 1200 | I79: m/s² | J79: =H79/10 -> 120 | K79: m
B80: α | C80: 0.3 | H80: =H79/10 -> 120 | I80: g
A81: elite | B81: sprint | C81: 10 | D81: m/s | E81: human leg | G81: sprint force | H81: =H76/30 -> 40000 | I81: N
B82: accel | C82: 10 | D82: m/s² | G82: accel | H82: =H81/C75 -> 40 | I82: m/s² | J82: =H82/10 -> 4 | K82: m
B83: arm speed | C83: 40 | D83: m/s | E83: cyber leg | G83: sprint force | H83: =H76/15 -> 80000 | I83: N
G84: accel | H84: =H83/C75 -> 80 | I84: m/s² | J84: =H84/10 -> 8 | K84: m
B85: Skeletal muscle | C85: =C86*1000 -> 5000000 | D85: N/m² | E85: jump
C86: 5000 | D86: N/kg
B87: drone | C87: 10000 | D87: N/kg | G87: k | H87: 0.1
G88: scaled F/W | H88: =C85*C90/C89/10*1/H87 -> 750
B89: density | C89: 2000 | D89: kg/m3
B90: f | C90: 0.3 | E90: V | G90: by mass | H90: F/W (lift) nature | J90: real | K90: eq
A92: 1 | B92: L (mouse) | C92: 0.1 | D92: m | E92: =C92^3 -> 0.001 | F92: m3 | G92: =(A92/1000)^(1/3) -> 0.1 | H92: =sqrt(K92) -> 27.386128 | I92: x body weight | J92: 10 | K92: =C85*C90/C89/10*1/C92 -> 750
A93: 0.1 | B93: L (ant) | C93: 0.003 | D93: m | E93: =C93^3 -> 2.7e-08 | F93: m3 | G93: =(A93/1000)^(1/3) -> 0.046415888 | H93: =sqrt(K93) -> 158.11388 | I93: x body weight | J93: 50 | K93: =C85*C90/C89/10*1/C93 -> 25000
A94: 1000 | B94: L (elephant) | C94: 3 | D94: m | E94: =3*3*2 -> 18 | F94: m3 | G94: =(A94/1000)^(1/3) -> 1 | H94: =sqrt(K94) -> 5 | I94: x body weight | J94: 2 | K94: =C85*C90/C89/10*1/C94 -> 25
A96: 10000 | B96: L (tank) | C96: 5 | D96: m | E96: =5*2*2 -> 20 | F96: m3 | G96: =(A96/1000)^(1/3) -> 2.1544347 | H96: =sqrt(K96) -> 3.8729833 | I96: x body weight | K96: =C$85*C$90/C$89/10*1/C96 -> 15
A97: 10 | B97: L (dog) | C97: 0.5 | D97: m | G97: =(A97/1000)^(1/3) -> 0.21544347 | H97: =sqrt(K97) -> 12.247449 | I97: x body weight | K97: =C$85*C$90/C$89/10*1/C97 -> 150
A99: 0.0001 | B99: taille -4 | C99: =G99 -> 0.0046415888 | D99: m | G99: =(A99/1000)^(1/3) -> 0.0046415888 | H99: =sqrt(K99) -> 127.11515 | I99: x body weight | K99: =C$85*C$90/C$89/10*1/C99 -> 16158.26
A100: 0.01 | B100: taille -3 | C100: =G100 -> 0.021544347 | D100: m | G100: =(A100/1000)^(1/3) -> 0.021544347 | H100: =sqrt(K100) -> 59.001624 | I100: x body weight | K100: =C$85*C$90/C$89/10*1/C100 -> 3481.1916
A101: 1 | B101: taille -2 | C101: =G101 -> 0.1 | D101: m | G101: =(A101/1000)^(1/3) -> 0.1 | H101: =sqrt(K101) -> 27.386128 | I101: x body weight | K101: =C$85*C$90/C$89/10*1/C101 -> 750
A102: 10 | B102: taille -1 | C102: 0.5 | D102: m | G102: =(A102/1000)^(1/3) -> 0.21544347 | H102: =sqrt(K102) -> 12.247449 | I102: x body weight | K102: =C$85*C$90/C$89/10*1/C102 -> 150
A103: 100 | B103: taille 0 | C103: 1.5 | D103: m | E103: =2*1*1 -> 2 | F103: m3 | G103: =(A103/1000)^(1/3) -> 0.46415888 | H103: =sqrt(K103) -> 7.0710678 | I103: x body weight | J103: 3 | K103: =C85*C90/C89/10*1/C103 -> 50
A104: 1000 | B104: taille 1 | C104: 3 | D104: m | E104: =2.5*2*1 -> 5 | F104: m3 | G104: =(A104/1000)^(1/3) -> 1 | H104: =sqrt(K104) -> 5 | I104: x body weight | K104: =C85*C90/C89/10*1/C104 -> 25
A105: 10000 | B105: taille 2 | C105: 5 | D105: m | G105: =(A105/1000)^(1/3) -> 2.1544347 | H105: =sqrt(K105) -> 3.8729833 | I105: x body weight | K105: =C$85*C$90/C$89/10*1/C105 -> 15
A106: 100000 | B106: taille 3 | C106: 5 | D106: m | G106: =(A106/1000)^(1/3) -> 4.6415888 | H106: =sqrt(K106) -> 3.8729833 | I106: x body weight | K106: =C$85*C$90/C$89/10*1/C106 -> 15
A107: 1000000 | B107: taille 4 | C107: 10 | D107: m | G107: =(A107/1000)^(1/3) -> 10 | H107: =sqrt(K107) -> 2.7386128 | I107: x body weight | K107: =C$85*C$90/C$89/10*1/C107 -> 7.5

Sheet Augments
F2: m/s | G2: g | H2: degats | I2: % / sec | J2: Lift : body weight x | P2: kN/kg | Q2: kW/kg | R2: % corps | S2: m/s | T2: kJ
D3: Prix | E3: Indice | F3: Sprint | G3: Jump | H3: Melee | I3: Power | J3: Taille -3 | K3: Taille -2 | L3: Taille -1 | M3: Taille 0 | N3: Taille 1 | O3: Taille 2 | P3: Strength | Q3: Power | R3: Mass | S3: Swing | T3: Punch
B4: Corps | C4: Standard | D4: 0 | E4: 3 | F4: 5 | G4: 2 | H4: 0+ | I4: 0 | J4: x10 | K4: x5 | L4: x2 | M4: x1 | N4: x1 | O4: x0 | P4: 1 | Q4: 0.1 | R4: 30 | S4: 10 | T4: 0.2
C5: Athlétique | D5: 2 | E5: 4 | F5: 10 | G5: 4 | H5: 0+ | I5: 0 | J5: x20 | K5: x10 | L5: x5 | M5: x3 | N5: x2 | O5: x1 | P5: 1.5 | Q5: 0.2 | R5: 40 | S5: 20 | T5: 1
C6: Surhumain | D6: 5 | E6: 5 | F6: 20 | G6: 6 | H6: 1+ | I6: 1 | J6: x50 | K6: x20 | L6: x10 | M6: x5 | N6: x3 | O6: x2 | P6: 3 | Q6: 1 | R6: 50 | S6: 40 | T6: 5
C7: Metahumain | D7: 10 | E7: 6 | F7: 40 | G7: 10 | H7: 2+ | I7: 2 | J7: x80 | K7: x30 | L7: x15 | M7: x8 | N7: x4 | O7: x2 | P7: 6 | Q7: 2 | R7: 50 | S7: 80 | T7: 50
C8: Prototype | D8: ? | E8: 7 | F8: 50 | G8: 12 | H8: 2+ | I8: 5 | J8: x100 | K8: x40 | L8: x20 | M8: x10 | N8: x5 | O8: x3 | P8: 9 | Q8: 5 | R8: 50 | S8: 100 | T8: 100
B9: Membres | C9: Cyberlegs | D9: 3 | E9: 6 | F9: 80 | G9: 20 | H9: 2+ | I9: 1 | P9: 6 | Q9: 2 | R9: 20 | S9: 80 | T9: 64
C10: Bras Mantis | D10: 3 | E10: 6 | H10: 3+ | I10: 0.5 | J10: x10 | K10: x5 | L10: x2 | M10: x1 | N10: x1 | O10: x0 | P10: 6 | Q10: 2 | R10: 5 | S10: 200 | T10: 500
C11: Membre blindé | D11: 1 | E11: 6 | F11: 4 | G11: 1 | H11: 1+ | I11: 0.2 | J11: x0 | K11: x0 | L11: x0 | M11: x0 | N11: x0 | O11: x0 | P11: 6 | Q11: 2 | R11: 60 | S11: 10 | T11: 6
C12: Booster 'DDE' | D12: 5 | F12: +100 | G12: +10 | I12: 0 | R12: 25
B13: Externe | C13: Cyberdeck | D13: 5 | I13: 0 | R13: 20
C14: Batterie | D14: 1 | I14: x0.5 | R14: 20
B17: Standard | C17: Masse | D17: 70 | E17: kg | F17: =sum(D18:D25) -> 100 | G17: % | J17: Athlétique | K17: Masse | L17: 80 | M17: kg | N17: =sum(L18:L25) -> 100 | O17: %
B18: 3 | C18: Muscles | D18: 30 | E18: % | F18: =D18/100*D$17 -> 21 | G18: kg | J18: 4 | K18: Muscles | L18: 40 | M18: % | N18: =L18/100*L$2 -> 0 | O18: kg
C19: Cerveau | D19: 4 | E19: % | F19: =D19/100*D$17 -> 2.8 | G19: kg | K19: Cerveau | L19: 4 | M19: % | N19: =L19/100*L$2 -> 0 | O19: kg
C20: Ossature | D20: 15 | E20: % | F20: =D20/100*D$17 -> 10.5 | G20: kg | K20: Ossature | L20: 15 | M20: % | N20: =L20/100*L$2 -> 0 | O20: kg
C21: Organes | D21: 15 | E21: % | F21: =D21/100*D$17 -> 10.5 | G21: kg | K21: Organes | L21: 15 | M21: % | N21: =L21/100*L$2 -> 0 | O21: kg
B22: Batterie | C22: Hardware | D22: 0.3 | E22: % | F22: =D22/100*D$17 -> 0.21 | G22: kg | J22: Batterie | K22: Hardware | L22: 1 | M22: % | N22: =L22/100*L$2 -> 0 | O22: kg
C23: Graisse | D23: 15 | E23: % | F23: =D23/100*D$17 -> 10.5 | G23: kg | K23: Graisse | L23: 8 | M23: % | N23: =L23/100*L$2 -> 0 | O23: kg
C24: Eau | D24: 20 | E24: % | F24: =D24/100*D$17 -> 14 | G24: kg | K24: Eau | L24: 15 | M24: % | N24: =L24/100*L$2 -> 0 | O24: kg
C25: Carbs | D25: 0.7 | E25: % | F25: =D25/100*D$17 -> 0.49 | G25: kg | K25: Carbs | L25: 2 | M25: % | N25: =L25/100*L$2 -> 0 | O25: kg
B26: Transhumain | C26: Masse | D26: 90 | E26: kg | F26: =sum(D27:D34) -> 100 | G26: % | J26: Metahumain | K26: Masse | L26: 100 | M26: kg | N26: =sum(L27:L34) -> 100 | O26: %
B27: 5 | C27: Muscles | D27: 50 | E27: % | F27: =D27/100*D$11 -> 0.5 | G27: kg | J27: 6 | K27: Muscles | L27: 50 | M27: % | N27: =L27/100*L$26 -> 50 | O27: kg
C28: Cerveau | D28: 4 | E28: % | F28: =D28/100*D$11 -> 0.04 | G28: kg | K28: Cerveau | L28: 4 | M28: % | N28: =L28/100*L$26 -> 4 | O28: kg
C29: Ossature | D29: 15 | E29: % | F29: =D29/100*D$11 -> 0.15 | G29: kg | K29: Ossature | L29: 15 | M29: % | N29: =L29/100*L$26 -> 15 | O29: kg
C30: Organes | D30: 15 | E30: % | F30: =D30/100*D$11 -> 0.15 | G30: kg | K30: Organes | L30: 5 | M30: % | N30: =L30/100*L$26 -> 5 | O30: kg
B31: Batterie | C31: Hardware | D31: 1 | E31: % | F31: =D31/100*D$11 -> 0.01 | G31: kg | J31: Batterie | K31: Hardware | L31: 5 | M31: % | N31: =L31/100*L$26 -> 5 | O31: kg
C32: Graisse + | D32: 1 | E32: % | F32: =D32/100*D$11 -> 0.01 | G32: kg | K32: Graisse + | L32: 0 | M32: % | N32: =L32/100*L$26 -> 0 | O32: kg
C33: Eau | D33: 10 | E33: % | F33: =D33/100*D$11 -> 0.1 | G33: kg | K33: Eau + | L33: 13 | M33: % | N33: =L33/100*L$26 -> 13 | O33: kg
C34: Carbs + | D34: 4 | E34: % | F34: =D34/100*D$11 -> 0.04 | G34: kg | K34: Carbs + | L34: 8 | M34: % | N34: =L34/100*L$26 -> 8 | O34: kg

Sheet gravity
B3: mass | C3: 2 | D3: earth
B4: volume | C4: =F4 -> 1.2058078 | D4: earth | E4: rocky : | F4: =C3^0.27 -> 1.2058078 | G4: earth
B7: gravity | C7: =C3/(C4^2) -> 1.3755418 | D7: g

Sheet Explosives
K2: PeakOverpressure_psi | L2: PeakOverpressure_kPa | M2: Human_effects | N2: Window_glass_3mm | O2: Car_passenger | P2: Light_wood_frame_house | Q2: Brick_masonry_house | R2: Reinforced_concrete_30cm | S2: Steel_plate_5cm
B3: Energy | C3: 200000000 | D3: J | K3: 0.2 | L3: 1.4 | M3: No significant injury if sheltered; minimal structural effect | N3: Very unlikely to break | O3: No structural damage | P3: No damage | Q3: No damage | R3: No damage | S3: No damage
B4: TNT equivalent | C4: =C3/4184000 -> 47.801147 | D4: kg | K4: 0.5 | L4: 3.4 | M4: Possible eardrum rupture for some; minor debris risk | N4: Small windows may crack or pop out | O4: No structural damage; falling debris possible | P4: No damage | Q4: No damage | R4: No damage | S4: No damage
B5: W1/3TNT | C5: =C4^(1/3) -> 3.6292156 | K5: 1 | L5: 6.9 | M5: High chance of eardrum rupture; glass injuries likely | N5: Most residential windows break | O5: Localized denting or cracking | P5: Minor structural damage (doors or windows) | Q5: Minor to moderate non-structural damage | R5: Negligible | S5: No damage
G6: Z(P) | I6: distance | K6: 2 | L6: 13.8 | M6: Increased lung trauma risk; many injured from debris | N6: All standard windows shatter | O6: Possible broken windows; glass and trim ripped off | P6: Significant damage to trim and roof elements | Q6: Partial collapse of unreinforced walls possible | R6: Possible chipping or spalling | S6: No perforation
B7: light damage | C7: =I7*$C$5 -> 72.584313 | D7: m | E7: 1 psi | G7: 7 | H7: kPa | I7: 20 | J7: m | K7: 3 | L7: 20.7 | M7: High probability of serious lung injury; fatalities outdoors | N7: Commercial glazing fails | O7: Doors blown off; body intrusion possible | P7: Partial collapse of light structures | Q7: Severe structural damage to masonry | R7: Localized spalling; generally intact | S7: No perforation
B8: heavy damage | C8: =I8*$C$5 -> 29.033725 | D8: m | E8: 5 psi | G8: 35 | H8: kPa | I8: 8 | J8: m | K8: 5 | L8: 34.5 | M8: Severe injuries common; many fatalities outdoors | N8: All glazing and curtain walls fail | O8: Heavy deformation; possible rolling of vehicles | P8: Severe damage to wood-frame structures | Q8: Heavy damage; collapse of many masonry buildings | R8: Heavy spalling; thin-section breach possible | S8: No perforation
B9: severe damage | C9: =I9*$C$5 -> 18.146078 | D9: m | E9: 10 psi | G9: 70 | H9: kPa | I9: 5 | J9: m | K9: 10 | L9: 68.9 | M9: Very high lethality in the open; massive destruction | N9: Almost all glazing destroyed | O9: Vehicles overturned or crushed by debris | P9: Most wood houses destroyed | Q9: Severe structural collapse | R9: Serious RC damage; through-breaches possible | S9: No perforation; mounts may fail
K10: 20 | L10: 137.9 | M10: Essentially unsurvivable in the open; complete destruction locally | N10: Catastrophic building failure | O10: Vehicles destroyed | P10: Complete destruction of light buildings | Q10: Wide collapse of masonry | R10: Large-scale shattering or spalling | S10: No clean perforation; mounts fail
K11: 50 | L11: 344.7 | M11: Near-certain fatality; near-total obliteration | N11: Few intact structures remain | O11: Vehicles vaporized by fragments | P11: Nothing left of light buildings | Q11: Serious crushing of heavy masonry | R11: Major breach or failure of concrete | S11: Possible large plastic deformation; still unlikely to perforate
K12: 100 | L12: 689.5 | M12: Complete annihilation locally | N12: Absolute annihilation of exposed objects | O12: All vehicles destroyed | P12: All building types destroyed | Q12: Heavy damage to reinforced structures | R12: Full plastic failure of concrete | S12: Perforation depends on impulse/duration; near steel yield
K13: 1000 | L13: 6894.8 | M13: Catastrophic; extreme environment | N13: Absolute annihilation | O13: Steel and heavy structures shredded | P13: No light buildings remain | Q13: Crushing and destruction of masonry | R13: Concrete obliterated | S13: Fragment-driven penetration dominates

Sheet Stratios mass
D2: dry mass
C3: =sum(C5:C16) -> 95 | D3: 400
B5: Engine | C5: 15 | D5: =$D$3*C5/100 -> 60 | E5: 4 TW MICFAM engine
B6: Cooling | C6: 25 | D6: =$D$3*C6/100 -> 100 | E6: 3 50x20m retractable L-ETHER wings (10 GW), coolant pumps
B7: Heat sink | C7: 25 | D7: =$D$3*C7/100 -> 100 | E7: 2 TJ (Lithium hydride + L-ETHER hab wheel)
B8: Structure | C8: 10 | D8: =$D$3*C8/100 -> 40 | E8: Carbon steel hull with ceramic plating, lightweight CNT polymer internal structure
B9: Power | C9: 3 | D9: =$D$3*C9/100 -> 12 | E9: Backup fusion core, graphene capacitors and power buses
B10: Life support | C10: 3 | D10: =$D$3*C10/100 -> 12 | E10: Facilities for a military crew of 10, food and water, recycling
B11: Armor | C11: 1 | D11: =$D$3*C11/100 -> 4 | E11: Multi-layered whipple shield, front only
B12: Weapons | C12: 5 | D12: =$D$3*C12/100 -> 20 | E12: Laser turret, keel-mounted coilgun
B13: Auxiliary | C13: 3 | D13: =$D$3*C13/100 -> 12 | E13: Side thrusters, gyroscope (mounted in the hab wheel), wings and landing struts
B14: CPU | C14: 3 | D14: =$D$3*C14/100 -> 12 | E14: Bio-computer with DNA storage, autonomous AI
B15: Sensors | C15: 1 | D15: =$D$3*C15/100 -> 4 | E15: Sensors suite (radar, lidar, optical, EM sensors, internal monitoring) + Comms array
B16: Miscellaneous | C16: 1 | D16: =$D$3*C16/100 -> 4 | E16: Laser sail, land rover, repair drones and other equipment

Sheet gyro
B2: B | C2: 8 | D2: T
B3: r | C3: 1 | D3: m | E3: shaft radius
B4: A | C4: 2 | D4: m² | E4: magnetic bearing area
B6: τ max | C6: =C3 * C4*C2^2 / (8 * PI() *10^-7) * 10^-6 -> 50.929582 | D6: MN·m | E6: ring torque | G6: τmax = r⋅ B² A / 2μ0​​
B7: max Ωt​​ | C7: =C6*10^6/C10 -> 0.084882636 | D7: rad | G7: τ=L⋅Ωt​
C8: =C7*57.2958 -> 4.8634186 | D8: deg
J9: L = mrv
B10: L | C10: =C11*C12*C13 -> 600000000 | D10: kg·m²/s
B11: m | C11: 10000 | D11: kg | E11: ring mass
B12: r | C12: 30 | D12: m
B13: v | C13: 2000 | D13: m/s
B15: I | C15: =2.88*10^7 -> 28800000 | D15: kg·m² | E15: Ship moment of inertia 2.88×10^7 kg·m²
B16: Ωt​​ | C16: 0.087 | D16: rad
C17: =C16*57.2958 -> 4.9847346 | D17: deg/s
B18: ωship​ | C18: =C10*C16/C15 -> 1.8125 | D18: rad/s
C19: =C18*57.2958 -> 103.84864 | D19: deg/s
B21: P | C21: =C10*C16^2 * 10^-6 -> 4.5414 | D21: MW | E21: energy cost for torque | G21: P=LΩt²
B22: E | C22: =0.5*C11*C13^2 *10^-9 -> 20 | D22: GJ | E22: rotational energy stored | G22: E = 1/2 mv²
J23: Torque | K23: 45 | L23: MN·m
J24: F | K24: =K23* 10^6 / C3 -> 45000000 | L24: N | M24: F = Pm​*A = A * B² / 2μ0​​

Sheet Sail
K1: 1 | L1: g
K2: 63 | L2: d
E3: c= | F3: =3*10^8 -> 300000000 | G3: m/s | K3: 0.181 | L3: c
K4: 990 | L4: AU
B5: Heat res | C5: 1 | D5: TW | H5: F=(1+R)⋅P​ / c | M5: =1361*(1/0.05)^2 -> 544400 | N5: W/m² | O5: solar power at 0.05 AU
B6: Reflectivity | C6: 99.9 | D6: % | F6: =C6*10^-2 -> 0.999 | K6: 2 | L6: g | M6: =M5*10^-6 -> 0.5444 | N6: MW/m²
B7: Max laser power | C7: =1/((100-C6) * 10^-2) -> 1000 | D7: TW | H7: Where: | K7: 45 | L7: d
K8: 0.259 | L8: c | M8: =C22*10^15 / M5 -> 1836884644 | N8: m² | O8: area for 1 PW
H9: F = thrust (Newtons) | K9: 1000 | L9: AU | M9: =M8*10^-6 -> 1836.8846 | N9: km²
B10: Laser power | C10: 1 | D10: PW | F10: =C10*10^15 -> 1e+15 | G10: W | M10: =sqrt(M9) -> 42.858892 | N10: km
B11: Thrust | C11: =F11*10^-6 -> 6.6633333 | D11: MN | F11: =(1+F6)*F10 / F3 -> 6663333.3 | G11: N | H11: P = laser power (Watts) | K11: 3 | L11: g
K12: 37 | L12: d | M12: 1064 | N12: nm | O12: w = L * 1.22 * λ / D​
B13: ship mass | C13: 500 | D13: t | F13: =C13*10^3 -> 500000 | G13: kg | H13: R = reflectivity (unitless, e.g. 0.98 for 98%) | K13: 0.32 | L13: c | M13: =M12*10^-9 -> 1.064e-06 | N13: m | O13: L = w * D / ( 1.22 * λ )
B14: accel | C14: =F11/F13 -> 13.326667 | D14: m/s² | F14: =C14/9.8 -> 1.3598639 | G14: g | K14: 1000 | L14: AU | M14: =M12*10^-12 -> 1.064e-09 | N14: km | O14: w = spot size
H15: c = speed of light ≈ 3×10^8 m/s | O15: L = distance
B16: time | C16: 400 | D16: d | O16: λ = wavelength
B17: speed | C17: =C14*C16*86400/F3 -> 1.535232 | D17: c | H17: F≈1.98⋅P​ / c | O17: D = lens diameter
B18: distance | C18: =E18/(1.496*10^11) -> 53199.483 | D18: AU | E18: =1/2 *C14 * (C16*86400)^2 -> 7.95864e+15 | F18: m | G18: =C18*1.58125*10^-5 -> 0.84121683 | H18: ly
B19: aτ | C19: =C16*C14*86400 -> 460569600 | D19: m/s | E19: =C18*1.5813*10^-5 -> 0.84124343 | F19: ly
B20: v | C20: =E20/F3 -> 0.8379197 | D20: c | E20: =C19 / sqrt(1+(C19/F3)^2) -> 2.5137591e+08 | F20: m/s | J20: proper time
K21: =300*0.7 -> 210
A22: ARRAY | B22: Power | C22: 1 | D22: PW | E22: =C22*10^15 -> 1e+15 | F22: W | H22: =E22/20000 -> 50000000000 | I22: kg
B23: Radius | C23: 20 | D23: km | H23: =H22*10^-9 -> 50 | I23: Mt | L23: =60000000/20000 -> 3000 | N23: =1000000000000 / 100000000 -> 10000
B25: Spot size | C25: 1 | D25: km radius | E25: =C25*10^3 -> 1000 | F25: m
B26: Efficiency | C26: 0.5
B28: Distance | C28: =C25 * C23*2 / (1.22 * M14) / (1.496 * 10^8) -> 205.98089 | D28: AU
B29: Collector area | C29: =M9*C22 /C26 -> 3673.7693 | D29: km² | E29: =C29 * 1000000 -> 3673769287 | F29: m² | M29: full array | N29: 63500 | O29: AU
C30: =sqrt(C29) -> 60.611627 | D30: km square | N30: 60 | O30: Mt
B31: at 1g/m² | C31: =E29*10^-6 -> 3673.7693 | D31: t | G31: spacing | N31: =1.25*0.9 -> 1.125 | O31: PW
B32: Laser area | C32: =(C23*PI())^2 -> 3947.8418 | D32: km²
M33: 10% array | N33: 20000 | O33: AU
N34: 6 | O34: Mt
B35: Focus distance | C35: 65000 | D35: AU | E35: =C35 * 1.496* 10^11 -> 9.724e+15 | F35: m | G35: =C35*1.58125*10^-5 -> 1.0278125 | H35: ly | K35: =sqrt(2*E35 / C14) / 86400 -> 442.14321 | L35: days of accel | N35: 0.1 | O35: PW
B36: > lens diameter | C36: =E36*10^-3 -> 12622.53 | D36: km | E36: =1.22 * M13 * E35 / E25 -> 12622530 | F36: m | I36: D = 1.22 λ L / w | K36: =C14*K35*86400/F3 -> 1.696981 | L36: c | N36: 800 | O36: days
B37: > lens area | C37: =PI() * (C36/2)^2 -> 125136124 | D37: km² | E37: =PI() * (E36/2)^2 -> 125136124023258 | F37: m² | I37: Alens = PI * (D/2)² | N37: 0.29 | O37: c
B39: fill factor (sparse) | C39: 0.1 | K39: 20 | L39: kW/kg
B40: module area | C40: 10 | D40: m² | J40: Module power | K40: 1 | L40: kW
B41: > module count | C41: =E41 -> 1251361240233 | E41: =C39*E37 / C40 -> 1251361240233 | H41: N = Alens / (fill * Amodule) | J41: Module mass | K41: =K40/K39 -> 0.05 | L41: kg
B42: > module power | C42: =C22/E41 * 10^9 -> 0.00079912975 | D42: MW | E42: =C42*10^6 -> 799.12975 | F42: W | G42: 10% loss
C43: =C41*K41*10^-9 -> 62.568062 | D43: Mt
E44: =C41*1000 -> 1.25136e+15 | F44: W
B45: > mirror area | C45: =M9*C22 /C26 -> 3673.7693 | D45: km²
C46: =sqrt(C45) -> 60.611627 | D46: km square | J46: =C41 -> 1251361240233
B47: > mirror mass | C47: =C45 -> 3673.7693 | D47: t | E47: at 1g/m² | K47: =J46*K41 -> 62568062012 | L47: kg
B48: > solar panel mass | C48: =C47 -> 3673.7693 | D48: t | E48: at 100g/m² but 100x smaller | K48: =K47*10^-9 -> 62.568062 | L48: Mt
H49: d <= λ * L / R | K49: =J46*100 -> 125136124023258 | L49: W
B50: fill factor | C50: 0.01
B51: module area | C51: 100 | D51: m²
B52: > module count | C52: =E52*10^-6 -> 12513.612 | D52: x10^6 | E52: =C50*E37 / C51 -> 12513612402 | H52: 99.9% loss
B53: > module power | C53: =C22/E52 * 10^6 * 10 -> 0.00079912975 | D53: MW | E53: 90% loss
C54: =20*C53*E52 * 10^-6 -> 200 | D54: Mt
B55: > collector area | C55: =M9*C22 /C26 * 10 -> 36737.693 | D55: km² | F55: m²
C56: =sqrt(C55) -> 191.67079 | D56: km square
B57: at 1g/m² | C57: =C55 -> 36737.693 | D57: t
B59: > min spacing d | C59: =M13 * E35 / ( E36 ) -> 819.67213 | D59: m
B60: > min fill | C60: =C40/(C59^2) -> 1.4884e-05
B61: > module count | C61: =E61*10^-3 -> 186252.61 | D61: x10^3 | E61: =C60*E37 / C40 -> 186252607
B62: > module power | C62: =C22/E61 * 10^6 * 20 -> 0.10738105 | D62: MW

Sheet Heat 
P1: vapo
A2: HEAT SINK | C2: Metastable Lithium Hybrid | H2: LiH sensible heat | I2: 1.8 | J2: MJ/kg | M2: Li | N2: 6.94 | O2: g/mol | P2: 21 | Q2: MJ/kg | S2: LiD sensible heat | T2: 1.1 | U2: MJ/kg | X2: Li | Y2: 6.94 | Z2: g/mol | AA2: 21 | AB2: MJ/kg
H3: LiH heat of fusion | I3: 2.9 | J3: MJ/kg | M3: H | N3: 1 | O3: g/mol | S3: LiD heat of fusion | T3: 2.9 | U3: MJ/kg | X3: D | Y3: 2.014 | Z3: g/mol
B4: Decomposition | C4: 20 | D4: MJ/kg | E4: LiH > Li + 1/2 H2 decomposition is endothermic | H4: chemical decomposition | I4: =N6*N7*10^-3 -> 16.100629 | J4: MJ/kg | K4: =sum(I2:I4) -> 20.800629 | M4: H2 | N4: =N3*2 -> 2 | O4: g/mol | S4: chemical decomposition | T4: =Y6*Y7*10^-3 -> 14.518651 | U4: MJ/kg | X4: D2 | Y4: =Y3*2 -> 4.028 | Z4: g/mol
E5: Engineered for higher temp | H5: sensible heat 2000K | I5: 2.2 | J5: MJ/kg | K5: =sum(I2:I5) -> 23.000629 | M5: LiH | N5: 7.95 | O5: g/mol | S5: sensible heat 2000K | T5: 2 | U5: MJ/kg | X5: LiD | Y5: =Y2+Y3 -> 8.954 | Z5: g/mol
H6: Lithium vaporization | I6: =P2*N9 -> 18.332075 | J6: MJ/kg | K6: Latent heat of vaporization: 21 MJ/kg | M6: LiH | N6: =1000/N5 -> 125.78616 | O6: mol/kg | S6: D2 vaporization | T6: =7.8*Y10 -> 1.7544338 | U6: MJ/kg | X6: LiD | Y6: =1000/Y5 -> 111.68193 | Z6: mol/kg
B7: Vaporization | C7: 20 | D7: MJ/kg | E7: also using some dissociation/ionization energy | H7: H2 vaporization | I7: =P10*N10 -> 3.672956 | J7: MJ/kg | K7: Latent + sensible heat to 2000 K: ~445 MJ/kg | M7: ΔH | N7: 128 | O7: kJ/mol | S7: total | T7: =sum(T2:T6) -> 22.273085 | U7: MJ/kg | V7: =T11*10^6 -> 100000000 | W7: g | X7: ΔH | Y7: 130 | Z7: kJ/mol
H8: total | I8: =sum(I2:I6) -> 41.332704 | J8: MJ/kg | S8: Lithium vaporization | T8: =AA2*Y9 -> 16.276524 | U8: MJ/kg | V8: 7.95 | W8: g/mol
B9: Vapor is recaptured and ran through the Ether dust radiators to recondense | M9: Li | N9: =N2/N5 -> 0.87295597 | O9: mass ratio | S9: total | T9: =T7+T8 -> 38.549609 | U9: MJ/kg | V9: 0.5 | W9: g/mol | X9: Li | Y9: =Y2/Y5 -> 0.77507259 | Z9: mass ratio
H10: LiH mass | I10: 0.01 | J10: t | K10: =I10*10^6 -> 10000 | L10: g | M10: H2 | N10: =N3/N5 -> 0.12578616 | O10: mass ratio | P10: 29.2 | Q10: MJ/kg (vapo at 2000K) | X10: D2 | Y10: =Y3/Y5 -> 0.22492741 | Z10: mass ratio | AA10: 93 | AB10: kJ/mol
B11: Operation temp | C11: 2000 | D11: K | H11: LiH mol | I11: =K10/K11 -> 1257.8616 | J11: mol | K11: 7.95 | L11: g/mol | S11: LiH mass | T11: 100 | U11: t
H12: H2 released | I12: =I11/2 -> 628.93082 | J12: mol | K12: 0.5 | L12: g/mol | S12: LiH mol | T12: =V7/V8 -> 12578616 | U12: mol
B13: tonnage | C13: 150 | D13: t | S13: H2 released | T13: =T12/2 -> 6289308.2 | U13: mol
B14: sink | C14: =(C4)*C13*10^-3 -> 3 | D14: TJ | H14: Temp | I14: 2000 | J14: K | X14: Latent heat of vaporization: 21 MJ/kg
B15: venting | C15: =(C7)*C13*10^-3 -> 3 | D15: TJ | H15: Pressure | I15: 500 | J15: atm | S15: Temp | T15: 2000 | U15: K | X15: Latent + sensible heat to 2000 K: ~445 MJ/kg
H16: R = | I16: 0.082057 | J16: L·atm/(mol·K) | S16: Pressure | T16: 500 | U16: atm
H17: V = nRT / P | I17: =I12*0.0821*I14 / I15 -> 206.54088 | J17: L | O17: Q=m⋅[cp​⋅(Tmelt​−Tstart​)+Lf​] | S17: R = | T17: 0.082057 | U17: L·atm/(mol·K)
B18: Lithium vapor at | I18: =I17/1000 -> 0.20654088 | J18: m3 | S18: V = nRT / P | T18: =T13*0.0821*T15 / T16 -> 2065408.8 | U18: L
I19: =I18/100 -> 0.0020654088 | J19: x10x10m | O19: Q is energy stored | T19: =T18/1000 -> 2065.4088 | U19: m3
O20: m is mass | T20: =T19/100 -> 20.654088 | U20: x10x10m
O21: cp​ is specific heat (J/kg·K)
A22: COOLING | O22: Tmelt​ is melting point
B23: Ether dust tech | C23: 200 | D23: kW/m² | E23: baseline | O23: Tstart​ is starting temperature
B24: at 2000K | C24: 1 | D24: MW/m² | O24: Lf​ is latent heat of fusion (J/kg)
A26: base | B26: Structure | C26: 20 | D26: kg/m²
B27: Hardware | C27: 5 | D27: kg/m²
B28: Coolant | C28: 15 | D28: kg/m² | M28: wing
M29: 60 | N29: m
A30: high tech | B30: Wing | C30: 0.1 | D30: kg/m² | E30: CNT polymer + graphene | M30: 30 | N30: m
B31: Support structure | C31: 5 | D31: kg/m² | E31: Folding trusses/ribs, actuators & mechanisms, control surfaces | J31: =I72*M37*10^-6 -> 0.0125047 | K31: GW | L31: cloud distance | M31: 2 | N31: m | O31: =M36*10*10^-3 -> 54 | P31: t
B32: Cooling hardware | C32: 5 | D32: kg/m² | E32: Pressurized pipes, magnetic pumps, sensors | L32: top / bottom | M32: =M29*M30 -> 1800 | N32: m²
B33: Coolant | E33: > already accounted for in heat sink | I33: ROUNDED | J33: 1500 | K33: kW/m² | L33: long edge | M33: =M29*M31*2 -> 240 | N33: m²
I34: wings | J34: =J31 -> 0.0125047 | K34: GW | L34: short edge | M34: =M30*M31*2 -> 120 | N34: m²
B35: Radiator | C35: 10 | D35: kg/m² | I35: wheel | J35: =1200*J33*10^-6 -> 1.8 | K35: GW | L35: cloud surface area | M35: =M32*2+M33*2+M34 -> 4200 | N35: m²
B36: RadHull | C36: 5 | D36: kg/m² | G36: =10*10*10 -> 1000 | J36: =1200*5*10^-3 -> 6 | K36: t | L36: total wing area (3 wings) | M36: =M29*M30*3 -> 5400 | N36: m²
L37: total cloud surface (3 wings) | M37: =M35*3 -> 12600 | N37: m² | O37: =M37/M36 -> 2.3333333
I38: lithium nanodroplets (~10 nm radius):
H39: Particle mass m | I39: 1.16×10−26kg | O39: =I72*O37 -> 2.3156853
H40: Thermal velocity vth​ | I40: ~2,200 m/s (at 2000 K)
H41: Particle charge q | I41: 5.5×10−18C | O41: =2.83*664 -> 1879.12
C43: LITHIUM VAPOR VOLUME
C45: V | D45: =D47*D48*D49/D50 -> 299.304 | E45: m3 | G45: V=nRT​ / P | H45: n=1.44×10^7 mol | I45: 100t
C46: m | D46: 1 | E46: t | H46: R=8.314 J/mol K | I46: ideal gas constant
C47: n | D47: =1.44*10^5*D46 -> 144000 | E47: mol | H47: T=2500 K | M47: =65*40*10 -> 26000
C48: R | D48: 8.314 | H48: P=60,800 Pa | I48: 0.6 atm
C49: T | D49: 2500 | E49: K
C50: P | D50: 10000000 | E50: Pa | I50: V= | J50: 5000000
D51: =D50/100000 -> 100 | E51: atm
C53: container | D53: =D45^(1/3) -> 6.6891485 | E53: m d'arete | F53: 19250 | G53: kg/m3 | K53: m3
D54: =6*D53^2 -> 268.46825 | E54: m²
D55: 0.03 | E55: m thickness
D56: =D54*D55 -> 8.0540475 | E56: m3 tungsten volume
D57: =D56*19250 *10^-3 -> 155.04041 | E57: t
B60: DUSTY PLASMA
B61: tungsten / lithium | C61: 200 | D61: kW/kg
C62: 60 | D62: t
C63: =C62*1000*C61*10^-6 -> 12 | D63: GW
A65: GRAPHITE | B65: major radius R | C65: 16 | D65: m | H65: P = ϵσT^4 | I65: graphite dusty plasma
B66: minor radius r | C66: =C65/4 -> 4 | D66: m | H66: ϵ = emissivity | I66: 0.9
B67: torus outer area A | C67: =2*pi()^2*C65*C66 -> 1263.3094 | D67: m² | H67: σ = constant | I67: =5.67*10^-8 -> 5.67e-08 | J67: W/m²K^4
B68: Heat rad | C68: =C67*I72*10^-3 -> 1.2537544 | D68: GW | E68: =10/C68 -> 7.9760439 | H68: T = operating temp | I68: 2100 | J68: K
B70: torus volume V | C70: =2*PI()^2*C65*C66^2 -> 5053.2375 | D70: m3
B71: dust mass density | C71: 0.1 | D71: kg/m3 | E71: > to 0.01 | H71: P= | I71: =I66*I67*I68^4 -> 992436.54 | J71: W/m²
B72: argon density | C72: 0.02 | D72: kg/m3 | E72: > at 0.1 atm | I72: =I71*10^-6 -> 0.99243654 | J72: MW/m²
B73: total density | C73: =C71+C72 -> 0.12 | D73: kg/m3
B74: total mass | C74: =C70*C73*10^-3 -> 0.60638849 | D74: t | O74: Target dust surface area per m³:
O75: Adust​≈10^5−10^6 m2/m3
A76: -- | B76: Rcoil | C76: =C65 -> 16 | D76: m
B77: Rtorus | C77: =C65 -> 16 | D77: m
B78: Bcoil | C78: 0.5 | D78: T | H78: B = μ0​ NI / (2 R) | I78: Field at center of torus
B79: B(Rtorus) | C79: =C78*(C76/C77)^3 -> 0.5 | D79: T | E79: field strength at torus | H79: μ0​=4π×10−7 H/m | I79: =4*pi()*10^-7 -> 1.2566371e-06 | L79: Plasma beta (β) ≤ 0.01–0.1 | M79: this means magnetic pressure dominates, and the plasma stays tightly confined.
L80: at 0.1 atm > magnetic field strength B = 1.58 T
B81: NI | C81: =2 * C76 *C78 /I79 -> 12732395 | D81: A-turns | L81: ideally > 2T for long-term confinement
B82: turns | C82: 100
B83: I | C83: =C81/C82 -> 127323.95 | E83: > 100 turns
B84: A | C84: =C83/I84 -> 0.00012732395 | D84: m² | G84: A = I / J | H84: J (graphene) | I84: =10^9 -> 1000000000 | J84: A/m²
B85: L | C85: =C82*(2*pi()*C76) -> 10053.096 | D85: m | E85: > total length
B86: V | C86: =C84*C85 -> 1.28 | D86: m3 | E86: > conductor volume | H86: p (graphene) | I86: 2200 | J86: kg/m3
B87: coil mass | C87: =C86*I86*10^-3 -> 2.816 | D87: t
B88: structure ratio | C88: 1 | D88: <3
B89: cryo ratio | C89: 0.2 | D89: <0.4
B90: shielding ratio | C90: 0.2 | D90: <0.2
B91: power ratio | C91: 0.1
B92: safety ratio | C92: =0.2*(C91+C90+C89+C88) -> 0.3
B93: total mass | C93: =C87*(1+(C88+C89+C90+C91+C92)) -> 7.8848 | D93: t | E93: =C93*round(E68,0) -> 63.0784 | F93: t
B94: total mass 2 | C94: =C87*2.2 -> 6.1952 | D94: t | E94: =C94*round(E68,0)/1 -> 49.5616 | F94: t for 10 GW | G94: ITER : 3.3x | H94: But ITER operates at higher fields and far larger scale
C95: =C68/C93 -> 0.15900903 | D95: GW/t | E95: =1/(E94/10)*1000 -> 201.76911 | F95: kW/kg
C96: =C68/C94 -> 0.20237513 | D96: GW/t
B98: safe distance d | C98: =sqrt(I72*1000*C67/( 4*PI()*500)) -> 14.125906 | D98: m | E98: from the ship
C99: 10 | D99: m | E99: from other coils if co-planar, less if perpendicular

Sheet Stratios laser
B2: Power density | C2: 20 | D2: kW/kg | I2: =2000*H5 -> 6000000
G3: For 10s charge + pulse
B4: Lens radius | C4: 500 | D4: m | L4: 10 sec charge
B5: Mass | C5: 10000 | D5: t | G5: Waste heat | H5: =C6*0.015 -> 3000 | I5: GJ | K5: Input power | L5: =C6*10 -> 2000000 | M5: MJ
B6: Power | C6: =C5*C2 -> 200000 | D6: MW | H6: =H5/(H9*10^3)*100 -> 62.5 | I6: % heat sink | K6: Laser heat | L6: =L5*0.3 -> 600000 | M6: MJ
B7: Efficiency | C7: 70 | D7: % | G7: Heat sink | H7: 160 | I7: t | K7: Power gen heat | L7: =L5 -> 2000000 | M7: MJ
B8: Wavelength | C8: 1064 | D8: nm | G8: Lithium+ | H8: 30 | I8: MJ / kg
H9: =(H7*10^3)*H8*10^-6 -> 4.8 | I9: TJ
C10: Lab | E10: Effective | K10: ARMOR | L10: Hull density | M10: 10 | N10: g/cm3 | O10: Ablation loss | P10: 90 | Q10: %
B11: Extreme range | C11: =(C4) / (0.0000000305 * C8) * SQRT( (0.000000002 *C6 * C7) / (0.01*C17 * PI()) ) -> 14545633 | D11: km | E11: =round((C11+C12)/200,0)*100 -> 9572700 | G11: Mostly harmless | I11: May heat up sensors or interfere with optics | L11: carbon vaporization | M11: 30 | N11: kJ/g | O11: Number of layers | P11: 2
B12: Long range | C12: =(C4) / (0.0000000305 * C8) * SQRT( (0.000000002 *C6 * C7) / (0.1*C17 * PI()) ) -> 4599732.9 | D12: km | E12: =round((C12+C13)/20,0)*10 -> 3027150 | G12: Sub-threshold burn | I12: Can damage exposed systems, weak armor | L12: CNT / graphite | M12: 100 | N12: kJ/g | O12: Energy remaining | P12: =(1-P10*0.01)^P11 *100 -> 1 | Q12: %
B13: Med range | C13: =(C4) / (0.0000000305 * C8) * SQRT( (0.000000002 *C6 * C7) / (1*C17 * PI()) ) -> 1454563.3 | D13: km | E13: =round((C13+C14)/20,0)*10 -> 957270 | G13: Matches hull resistance | I13: Burns through hull, damages one subsystem | L13: Hull heat res | M13: =M12*M10*10^-3 -> 1 | N13: MJ/cm3
B14: Short range | C14: =(C4) / (0.0000000305 * C8) * SQRT( (0.000000002 *C6 * C7) / (10*C17 * PI()) ) -> 459973.29 | D14: km | E14: =round((C14+C15)/20,0)*10 -> 302710 | G14: 10× damage threshold | I14: Punches through multiple compartments | L14: 5 cm thick | M14: =M13*5 -> 5 | N14: MJ/cm²
B15: Overkill range | C15: =(C4) / (0.0000000305 * C8) * SQRT( (0.000000002 *C6 * C7) / (100*C17 * PI()) ) -> 145456.33 | D15: km | E15: =round((C15+C16)/20,0)*10 -> 72730 | I15: Full compartment meltdown | L15: Slope, rotation, etc | M15: dice roll
B17: Hull heat res | C17: 1 | D17: MW/cm²
K19: C6 | L19: 1 | M19: 2 | N19: 3 | O19: 4 | P19: 5 | Q19: 6 | R19: 7 | S19: 8 | T19: 9 | U19: 10 | V19: 11 | W19: 12
K20: 20 | L20: =(L$19) / (0.0000000305 * $C$8) * SQRT( (0.000000002 *$K20 * $C$7) / (PI()) ) -> 29.091265 | M20: =(M$19) / (0.0000000305 * $C$8) * SQRT( (0.000000002 *$K20 * $C$7) / (PI()) ) -> 58.182531 | N20: =(N$19) / (0.0000000305 * $C$8) * SQRT( (0.000000002 *$K20 * $C$7) / (PI()) ) -> 87.273796 | O20: =(O$19) / (0.0000000305 * $C$8) * SQRT( (0.000000002 *$K20 * $C$7) / (PI()) ) -> 116.36506 | P20: =(P$19) / (0.0000000305 * $C$8) * SQRT( (0.000000002 *$K20 * $C$7) / (PI()) ) -> 145.45633 | Q20: =(Q$19) / (0.0000000305 * $C$8) * SQRT( (0.000000002 *$K20 * $C$7) / (PI()) ) -> 174.54759 | R20: =(R$19) / (0.0000000305 * $C$8) * SQRT( (0.000000002 *$K20 * $C$7) / (PI()) ) -> 203.63886 | S20: =(S$19) / (0.0000000305 * $C$8) * SQRT( (0.000000002 *$K20 * $C$7) / (PI()) ) -> 232.73012 | ... U20: =(U$19) / (0.0000000305 * $C$8) * SQRT( (0.000000002 *$K20 * $C$7) / (PI()) ) -> 290.91265
K21: 40 | L21: =(L$19) / (0.0000000305 * $C$8) * SQRT( (0.000000002 *$K21 * $C$7) / (PI()) ) -> 41.141262 | M21: =(M$19) / (0.0000000305 * $C$8) * SQRT( (0.000000002 *$K21 * $C$7) / (PI()) ) -> 82.282524 | N21: =(N$19) / (0.0000000305 * $C$8) * SQRT( (0.000000002 *$K21 * $C$7) / (PI()) ) -> 123.42379 | O21: =(O$19) / (0.0000000305 * $C$8) * SQRT( (0.000000002 *$K21 * $C$7) / (PI()) ) -> 164.56505 | P21: =(P$19) / (0.0000000305 * $C$8) * SQRT( (0.000000002 *$K21 * $C$7) / (PI()) ) -> 205.70631 | Q21: =(Q$19) / (0.0000000305 * $C$8) * SQRT( (0.000000002 *$K21 * $C$7) / (PI()) ) -> 246.84757 | R21: =(R$19) / (0.0000000305 * $C$8) * SQRT( (0.000000002 *$K21 * $C$7) / (PI()) ) -> 287.98883 | S21: =(S$19) / (0.0000000305 * $C$8) * SQRT( (0.000000002 *$K21 * $C$7) / (PI()) ) -> 329.1301 | ... U21: =(U$19) / (0.0000000305 * $C$8) * SQRT( (0.000000002 *$K21 * $C$7) / (PI()) ) -> 411.41262
H22: =H9*10^3/H5/6/60 -> 0.0044444444 | I22: h of continuous fire | K22: 60 | L22: =(L$19) / (0.0000000305 * $C$8) * SQRT( (0.000000002 *$K22 * $C$7) / (PI()) ) -> 50.38755 | M22: =(M$19) / (0.0000000305 * $C$8) * SQRT( (0.000000002 *$K22 * $C$7) / (PI()) ) -> 100.7751 | N22: =(N$19) / (0.0000000305 * $C$8) * SQRT( (0.000000002 *$K22 * $C$7) / (PI()) ) -> 151.16265 | O22: =(O$19) / (0.0000000305 * $C$8) * SQRT( (0.000000002 *$K22 * $C$7) / (PI()) ) -> 201.5502 | P22: =(P$19) / (0.0000000305 * $C$8) * SQRT( (0.000000002 *$K22 * $C$7) / (PI()) ) -> 251.93775 | Q22: =(Q$19) / (0.0000000305 * $C$8) * SQRT( (0.000000002 *$K22 * $C$7) / (PI()) ) -> 302.3253 | R22: =(R$19) / (0.0000000305 * $C$8) * SQRT( (0.000000002 *$K22 * $C$7) / (PI()) ) -> 352.71285 | S22: =(S$19) / (0.0000000305 * $C$8) * SQRT( (0.000000002 *$K22 * $C$7) / (PI()) ) -> 403.1004 | ... U22: =(U$19) / (0.0000000305 * $C$8) * SQRT( (0.000000002 *$K22 * $C$7) / (PI()) ) -> 503.8755
K23: 80 | L23: =(L$19) / (0.0000000305 * $C$8) * SQRT( (0.000000002 *$K23 * $C$7) / (PI()) ) -> 58.182531 | M23: =(M$19) / (0.0000000305 * $C$8) * SQRT( (0.000000002 *$K23 * $C$7) / (PI()) ) -> 116.36506 | N23: =(N$19) / (0.0000000305 * $C$8) * SQRT( (0.000000002 *$K23 * $C$7) / (PI()) ) -> 174.54759 | O23: =(O$19) / (0.0000000305 * $C$8) * SQRT( (0.000000002 *$K23 * $C$7) / (PI()) ) -> 232.73012 | P23: =(P$19) / (0.0000000305 * $C$8) * SQRT( (0.000000002 *$K23 * $C$7) / (PI()) ) -> 290.91265 | Q23: =(Q$19) / (0.0000000305 * $C$8) * SQRT( (0.000000002 *$K23 * $C$7) / (PI()) ) -> 349.09518 | R23: =(R$19) / (0.0000000305 * $C$8) * SQRT( (0.000000002 *$K23 * $C$7) / (PI()) ) -> 407.27772 | S23: =(S$19) / (0.0000000305 * $C$8) * SQRT( (0.000000002 *$K23 * $C$7) / (PI()) ) -> 465.46025 | ... U23: =(U$19) / (0.0000000305 * $C$8) * SQRT( (0.000000002 *$K23 * $C$7) / (PI()) ) -> 581.82531
K24: 100 | L24: =(L$19) / (0.0000000305 * $C$8) * SQRT( (0.000000002 *$K24 * $C$7) / (PI()) ) -> 65.050047 | M24: =(M$19) / (0.0000000305 * $C$8) * SQRT( (0.000000002 *$K24 * $C$7) / (PI()) ) -> 130.10009 | N24: =(N$19) / (0.0000000305 * $C$8) * SQRT( (0.000000002 *$K24 * $C$7) / (PI()) ) -> 195.15014 | O24: =(O$19) / (0.0000000305 * $C$8) * SQRT( (0.000000002 *$K24 * $C$7) / (PI()) ) -> 260.20019 | P24: =(P$19) / (0.0000000305 * $C$8) * SQRT( (0.000000002 *$K24 * $C$7) / (PI()) ) -> 325.25023 | Q24: =(Q$19) / (0.0000000305 * $C$8) * SQRT( (0.000000002 *$K24 * $C$7) / (PI()) ) -> 390.30028 | R24: =(R$19) / (0.0000000305 * $C$8) * SQRT( (0.000000002 *$K24 * $C$7) / (PI()) ) -> 455.35033 | S24: =(S$19) / (0.0000000305 * $C$8) * SQRT( (0.000000002 *$K24 * $C$7) / (PI()) ) -> 520.40038 | ... U24: =(U$19) / (0.0000000305 * $C$8) * SQRT( (0.000000002 *$K24 * $C$7) / (PI()) ) -> 650.50047
K25: 120 | L25: =(L$19) / (0.0000000305 * $C$8) * SQRT( (0.000000002 *$K25 * $C$7) / (PI()) ) -> 71.258756 | M25: =(M$19) / (0.0000000305 * $C$8) * SQRT( (0.000000002 *$K25 * $C$7) / (PI()) ) -> 142.51751 | N25: =(N$19) / (0.0000000305 * $C$8) * SQRT( (0.000000002 *$K25 * $C$7) / (PI()) ) -> 213.77627 | O25: =(O$19) / (0.0000000305 * $C$8) * SQRT( (0.000000002 *$K25 * $C$7) / (PI()) ) -> 285.03502 | P25: =(P$19) / (0.0000000305 * $C$8) * SQRT( (0.000000002 *$K25 * $C$7) / (PI()) ) -> 356.29378 | Q25: =(Q$19) / (0.0000000305 * $C$8) * SQRT( (0.000000002 *$K25 * $C$7) / (PI()) ) -> 427.55254 | R25: =(R$19) / (0.0000000305 * $C$8) * SQRT( (0.000000002 *$K25 * $C$7) / (PI()) ) -> 498.81129 | S25: =(S$19) / (0.0000000305 * $C$8) * SQRT( (0.000000002 *$K25 * $C$7) / (PI()) ) -> 570.07005 | ... U25: =(U$19) / (0.0000000305 * $C$8) * SQRT( (0.000000002 *$K25 * $C$7) / (PI()) ) -> 712.58756
K26: 140 | L26: =(L$19) / (0.0000000305 * $C$8) * SQRT( (0.000000002 *$K26 * $C$7) / (PI()) ) -> 76.968254 | M26: =(M$19) / (0.0000000305 * $C$8) * SQRT( (0.000000002 *$K26 * $C$7) / (PI()) ) -> 153.93651 | N26: =(N$19) / (0.0000000305 * $C$8) * SQRT( (0.000000002 *$K26 * $C$7) / (PI()) ) -> 230.90476 | O26: =(O$19) / (0.0000000305 * $C$8) * SQRT( (0.000000002 *$K26 * $C$7) / (PI()) ) -> 307.87301 | P26: =(P$19) / (0.0000000305 * $C$8) * SQRT( (0.000000002 *$K26 * $C$7) / (PI()) ) -> 384.84127 | Q26: =(Q$19) / (0.0000000305 * $C$8) * SQRT( (0.000000002 *$K26 * $C$7) / (PI()) ) -> 461.80952 | R26: =(R$19) / (0.0000000305 * $C$8) * SQRT( (0.000000002 *$K26 * $C$7) / (PI()) ) -> 538.77777 | S26: =(S$19) / (0.0000000305 * $C$8) * SQRT( (0.000000002 *$K26 * $C$7) / (PI()) ) -> 615.74603 | ... U26: =(U$19) / (0.0000000305 * $C$8) * SQRT( (0.000000002 *$K26 * $C$7) / (PI()) ) -> 769.68254
K27: 160 | L27: =(L$19) / (0.0000000305 * $C$8) * SQRT( (0.000000002 *$K27 * $C$7) / (PI()) ) -> 82.282524 | M27: =(M$19) / (0.0000000305 * $C$8) * SQRT( (0.000000002 *$K27 * $C$7) / (PI()) ) -> 164.56505 | N27: =(N$19) / (0.0000000305 * $C$8) * SQRT( (0.000000002 *$K27 * $C$7) / (PI()) ) -> 246.84757 | O27: =(O$19) / (0.0000000305 * $C$8) * SQRT( (0.000000002 *$K27 * $C$7) / (PI()) ) -> 329.1301 | P27: =(P$19) / (0.0000000305 * $C$8) * SQRT( (0.000000002 *$K27 * $C$7) / (PI()) ) -> 411.41262 | Q27: =(Q$19) / (0.0000000305 * $C$8) * SQRT( (0.000000002 *$K27 * $C$7) / (PI()) ) -> 493.69514 | R27: =(R$19) / (0.0000000305 * $C$8) * SQRT( (0.000000002 *$K27 * $C$7) / (PI()) ) -> 575.97767 | S27: =(S$19) / (0.0000000305 * $C$8) * SQRT( (0.000000002 *$K27 * $C$7) / (PI()) ) -> 658.26019 | ... U27: =(U$19) / (0.0000000305 * $C$8) * SQRT( (0.000000002 *$K27 * $C$7) / (PI()) ) -> 822.82524
K28: 180 | L28: =(L$19) / (0.0000000305 * $C$8) * SQRT( (0.000000002 *$K28 * $C$7) / (PI()) ) -> 87.273796 | M28: =(M$19) / (0.0000000305 * $C$8) * SQRT( (0.000000002 *$K28 * $C$7) / (PI()) ) -> 174.54759 | N28: =(N$19) / (0.0000000305 * $C$8) * SQRT( (0.000000002 *$K28 * $C$7) / (PI()) ) -> 261.82139 | O28: =(O$19) / (0.0000000305 * $C$8) * SQRT( (0.000000002 *$K28 * $C$7) / (PI()) ) -> 349.09518 | P28: =(P$19) / (0.0000000305 * $C$8) * SQRT( (0.000000002 *$K28 * $C$7) / (PI()) ) -> 436.36898 | Q28: =(Q$19) / (0.0000000305 * $C$8) * SQRT( (0.000000002 *$K28 * $C$7) / (PI()) ) -> 523.64278 | R28: =(R$19) / (0.0000000305 * $C$8) * SQRT( (0.000000002 *$K28 * $C$7) / (PI()) ) -> 610.91657 | S28: =(S$19) / (0.0000000305 * $C$8) * SQRT( (0.000000002 *$K28 * $C$7) / (PI()) ) -> 698.19037 | ... U28: =(U$19) / (0.0000000305 * $C$8) * SQRT( (0.000000002 *$K28 * $C$7) / (PI()) ) -> 872.73796
K29: 200 | L29: =(L$19) / (0.0000000305 * $C$8) * SQRT( (0.000000002 *$K29 * $C$7) / (PI()) ) -> 91.994659 | M29: =(M$19) / (0.0000000305 * $C$8) * SQRT( (0.000000002 *$K29 * $C$7) / (PI()) ) -> 183.98932 | N29: =(N$19) / (0.0000000305 * $C$8) * SQRT( (0.000000002 *$K29 * $C$7) / (PI()) ) -> 275.98398 | O29: =(O$19) / (0.0000000305 * $C$8) * SQRT( (0.000000002 *$K29 * $C$7) / (PI()) ) -> 367.97863 | P29: =(P$19) / (0.0000000305 * $C$8) * SQRT( (0.000000002 *$K29 * $C$7) / (PI()) ) -> 459.97329 | Q29: =(Q$19) / (0.0000000305 * $C$8) * SQRT( (0.000000002 *$K29 * $C$7) / (PI()) ) -> 551.96795 | R29: =(R$19) / (0.0000000305 * $C$8) * SQRT( (0.000000002 *$K29 * $C$7) / (PI()) ) -> 643.96261 | S29: =(S$19) / (0.0000000305 * $C$8) * SQRT( (0.000000002 *$K29 * $C$7) / (PI()) ) -> 735.95727 | ... U29: =(U$19) / (0.0000000305 * $C$8) * SQRT( (0.000000002 *$K29 * $C$7) / (PI()) ) -> 919.94659
K30: 220 | L30: =(L$19) / (0.0000000305 * $C$8) * SQRT( (0.000000002 *$K30 * $C$7) / (PI()) ) -> 96.484812 | M30: =(M$19) / (0.0000000305 * $C$8) * SQRT( (0.000000002 *$K30 * $C$7) / (PI()) ) -> 192.96962 | N30: =(N$19) / (0.0000000305 * $C$8) * SQRT( (0.000000002 *$K30 * $C$7) / (PI()) ) -> 289.45444 | O30: =(O$19) / (0.0000000305 * $C$8) * SQRT( (0.000000002 *$K30 * $C$7) / (PI()) ) -> 385.93925 | P30: =(P$19) / (0.0000000305 * $C$8) * SQRT( (0.000000002 *$K30 * $C$7) / (PI()) ) -> 482.42406 | Q30: =(Q$19) / (0.0000000305 * $C$8) * SQRT( (0.000000002 *$K30 * $C$7) / (PI()) ) -> 578.90887 | R30: =(R$19) / (0.0000000305 * $C$8) * SQRT( (0.000000002 *$K30 * $C$7) / (PI()) ) -> 675.39368 | S30: =(S$19) / (0.0000000305 * $C$8) * SQRT( (0.000000002 *$K30 * $C$7) / (PI()) ) -> 771.8785 | ... U30: =(U$19) / (0.0000000305 * $C$8) * SQRT( (0.000000002 *$K30 * $C$7) / (PI()) ) -> 964.84812
K31: 240 | L31: =(L$19) / (0.0000000305 * $C$8) * SQRT( (0.000000002 *$K31 * $C$7) / (PI()) ) -> 100.7751 | M31: =(M$19) / (0.0000000305 * $C$8) * SQRT( (0.000000002 *$K31 * $C$7) / (PI()) ) -> 201.5502 | N31: =(N$19) / (0.0000000305 * $C$8) * SQRT( (0.000000002 *$K31 * $C$7) / (PI()) ) -> 302.3253 | O31: =(O$19) / (0.0000000305 * $C$8) * SQRT( (0.000000002 *$K31 * $C$7) / (PI()) ) -> 403.1004 | P31: =(P$19) / (0.0000000305 * $C$8) * SQRT( (0.000000002 *$K31 * $C$7) / (PI()) ) -> 503.8755 | Q31: =(Q$19) / (0.0000000305 * $C$8) * SQRT( (0.000000002 *$K31 * $C$7) / (PI()) ) -> 604.6506 | R31: =(R$19) / (0.0000000305 * $C$8) * SQRT( (0.000000002 *$K31 * $C$7) / (PI()) ) -> 705.4257 | S31: =(S$19) / (0.0000000305 * $C$8) * SQRT( (0.000000002 *$K31 * $C$7) / (PI()) ) -> 806.20079 | ... U31: =(U$19) / (0.0000000305 * $C$8) * SQRT( (0.000000002 *$K31 * $C$7) / (PI()) ) -> 1007.751
K32: 260 | L32: =(L$19) / (0.0000000305 * $C$8) * SQRT( (0.000000002 *$K32 * $C$7) / (PI()) ) -> 104.89005 | M32: =(M$19) / (0.0000000305 * $C$8) * SQRT( (0.000000002 *$K32 * $C$7) / (PI()) ) -> 209.7801 | N32: =(N$19) / (0.0000000305 * $C$8) * SQRT( (0.000000002 *$K32 * $C$7) / (PI()) ) -> 314.67015 | O32: =(O$19) / (0.0000000305 * $C$8) * SQRT( (0.000000002 *$K32 * $C$7) / (PI()) ) -> 419.5602 | P32: =(P$19) / (0.0000000305 * $C$8) * SQRT( (0.000000002 *$K32 * $C$7) / (PI()) ) -> 524.45024 | Q32: =(Q$19) / (0.0000000305 * $C$8) * SQRT( (0.000000002 *$K32 * $C$7) / (PI()) ) -> 629.34029 | R32: =(R$19) / (0.0000000305 * $C$8) * SQRT( (0.000000002 *$K32 * $C$7) / (PI()) ) -> 734.23034 | S32: =(S$19) / (0.0000000305 * $C$8) * SQRT( (0.000000002 *$K32 * $C$7) / (PI()) ) -> 839.12039 | ... U32: =(U$19) / (0.0000000305 * $C$8) * SQRT( (0.000000002 *$K32 * $C$7) / (PI()) ) -> 1048.9005
K33: 280 | L33: =(L$19) / (0.0000000305 * $C$8) * SQRT( (0.000000002 *$K33 * $C$7) / (PI()) ) -> 108.84955 | M33: =(M$19) / (0.0000000305 * $C$8) * SQRT( (0.000000002 *$K33 * $C$7) / (PI()) ) -> 217.6991 | N33: =(N$19) / (0.0000000305 * $C$8) * SQRT( (0.000000002 *$K33 * $C$7) / (PI()) ) -> 326.54864 | O33: =(O$19) / (0.0000000305 * $C$8) * SQRT( (0.000000002 *$K33 * $C$7) / (PI()) ) -> 435.39819 | P33: =(P$19) / (0.0000000305 * $C$8) * SQRT( (0.000000002 *$K33 * $C$7) / (PI()) ) -> 544.24774 | Q33: =(Q$19) / (0.0000000305 * $C$8) * SQRT( (0.000000002 *$K33 * $C$7) / (PI()) ) -> 653.09729 | R33: =(R$19) / (0.0000000305 * $C$8) * SQRT( (0.000000002 *$K33 * $C$7) / (PI()) ) -> 761.94684 | S33: =(S$19) / (0.0000000305 * $C$8) * SQRT( (0.000000002 *$K33 * $C$7) / (PI()) ) -> 870.79638 | ... U33: =(U$19) / (0.0000000305 * $C$8) * SQRT( (0.000000002 *$K33 * $C$7) / (PI()) ) -> 1088.4955
K34: 300 | L34: =(L$19) / (0.0000000305 * $C$8) * SQRT( (0.000000002 *$K34 * $C$7) / (PI()) ) -> 112.66999 | M34: =(M$19) / (0.0000000305 * $C$8) * SQRT( (0.000000002 *$K34 * $C$7) / (PI()) ) -> 225.33997 | N34: =(N$19) / (0.0000000305 * $C$8) * SQRT( (0.000000002 *$K34 * $C$7) / (PI()) ) -> 338.00996 | O34: =(O$19) / (0.0000000305 * $C$8) * SQRT( (0.000000002 *$K34 * $C$7) / (PI()) ) -> 450.67995 | P34: =(P$19) / (0.0000000305 * $C$8) * SQRT( (0.000000002 *$K34 * $C$7) / (PI()) ) -> 563.34993 | Q34: =(Q$19) / (0.0000000305 * $C$8) * SQRT( (0.000000002 *$K34 * $C$7) / (PI()) ) -> 676.01992 | R34: =(R$19) / (0.0000000305 * $C$8) * SQRT( (0.000000002 *$K34 * $C$7) / (PI()) ) -> 788.6899 | S34: =(S$19) / (0.0000000305 * $C$8) * SQRT( (0.000000002 *$K34 * $C$7) / (PI()) ) -> 901.35989 | ... U34: =(U$19) / (0.0000000305 * $C$8) * SQRT( (0.000000002 *$K34 * $C$7) / (PI()) ) -> 1126.6999
... K69: 1000 | L69: =(L$19) / (0.0000000305 * $C$8) * SQRT( (0.000000002 *$K69 * $C$7) / (PI()) ) -> 205.70631 | M69: =(M$19) / (0.0000000305 * $C$8) * SQRT( (0.000000002 *$K69 * $C$7) / (PI()) ) -> 411.41262 | N69: =(N$19) / (0.0000000305 * $C$8) * SQRT( (0.000000002 *$K69 * $C$7) / (PI()) ) -> 617.11893 | O69: =(O$19) / (0.0000000305 * $C$8) * SQRT( (0.000000002 *$K69 * $C$7) / (PI()) ) -> 822.82524 | P69: =(P$19) / (0.0000000305 * $C$8) * SQRT( (0.000000002 *$K69 * $C$7) / (PI()) ) -> 1028.5316 | Q69: =(Q$19) / (0.0000000305 * $C$8) * SQRT( (0.000000002 *$K69 * $C$7) / (PI()) ) -> 1234.2379 | R69: =(R$19) / (0.0000000305 * $C$8) * SQRT( (0.000000002 *$K69 * $C$7) / (PI()) ) -> 1439.9442 | S69: =(S$19) / (0.0000000305 * $C$8) * SQRT( (0.000000002 *$K69 * $C$7) / (PI()) ) -> 1645.6505 | ... U69: =(U$19) / (0.0000000305 * $C$8) * SQRT( (0.000000002 *$K69 * $C$7) / (PI()) ) -> 2057.0631

Sheet Localisations
B2: 🔵 FRONT Arc
B3: Roll | C3: Protection | D3: System | E3: Subsystem | F3: Light | G3: Heavy | H3: Critical | Q3: TOP / BOTTOM ARC (Polar attack vectors)
B4: 2 | C4: 🛡️ | D4: ⚡ | E4: Reactor Core | F4: Output reduced; auxiliary grid compensates | G4: Partial shutdown; reroute power | H4: Reactor fails; risk of meltdown or explosion | Q4: 2 | R4: Reactor Core | S4: Deepest, central. Only reachable if top armor is breached.
B5: 3 | C5: 🛡️ | D5: 🧠 | E5: Bridge / Command Core | F5: Brief command delay | G5: AI loop errors; command loss for 1 round | H5: Total CPU loss; ship control reverts to emergency backup | Q5: 3 | R5: Bridge / Command Core | S5: May be dorsal; some risk depending on design.
B6: 4 | C6: 🛡️ | E6: Habitat Section | F6: Minor crew injuries or decompression | G6: Significant hull breach; life support stress | H6: Habitat destroyed; crew casualties and full decompression | Q6: 4 | R6: Habitat Section | S6: Accessible mid-ship hit.
B7: 5 | C7: ⚠️ | D7: 🌡️ | E7: Cooling Systems | F7: Minor coolant leak; reduced heat capacity | G7: Overheating; reactor throttled | H7: Coolant loop ruptured; core shutdown imminent | Q7: 5 | R7: Sensors / Comms | S7: Often mounted top and bottom for full-sky coverage.
B8: 6 | C8: 🎯 | D8: 📡 | E8: Sensors / Comms Array | F8: Signal jitter; targeting penalties | G8: Sensor lock lost; comms blackout | H8: Sensor suite destroyed; blind and deaf in front arc | Q8: 6 | R8: Radiators | S8: Extended vertically in many designs; big and weak.
B9: 7 | C9: 🛡️ | E9: Front Armor / Hull | F9: Minor scorch or spalling | G9: Armor plate cracked; weak point created | H9: Armor breached; front internal systems exposed | Q9: 7 | R9: Dorsal/Ventral Armor | S9: Most common surface hit.
B10: 8 | C10: 🎯 | E10: Weapons (Forward) | F10: 1 forward weapon disabled | G10: Multiple barrels offline; weapon misfires | H10: Full battery destroyed or explodes | Q10: 8 | R10: Weapons (Turrets) | S10: Top-mounted guns, flak, or CIWS systems.
B11: 9 | C11: 🛡️ | D11: 🚀 | E11: Fuel Tanks | F11: Small leak; slight thrust penalty | G11: Fuel dump; ship slows | H11: Fuel fire or loss; burn duration reduced significantly | Q11: 9 | R11: Fuel Tanks | S11: May wrap around midsection.
B12: 10 | C12: 🛡️ | D12: ⚡ | E12: Power Vein | F12: Local arc; minor output drop | G12: Grid instability; reroute needed | H12: Short circuit disables major subsystems | Q12: 10 | R12: Power Trunking | S12: Central lines passing vertically.
B13: 11 | C13: 🛡️ | E13: Secondary Systems | F13: Alarms or lights fail; minor utility loss | G13: Internal bulkheads jam; doors or support fail | H13: Full subsystem loss; e.g., medbay, backups, or support AI | Q13: 11 | R13: Secondary Systems | S13: Life support, storage modules, soft targets.
B14: 12 | C14: 🎯 | D14: 🚀 | E14: Propulsion Ancillaries | F14: Gimbal failure; steering penalty | G14: Burn precision degraded; drift introduced | H14: Full steering failure; major maneuvering impossible | Q14: 12 | R14: Docking Bays / Hangars | S14: Often dorsal/ventral for cargo or landers.
B16: 🟡 SIDE Arc
B17: Roll | E17: Subsystem | F17: Light | G17: Heavy | H17: Critical
B18: 2 | D18: ⚡ | E18: Reactor Core | F18: Minor control spike; temporary throttling | G18: Output irregularity; forced safety constraints | H18: Core instability; emergency SCRAM or meltdown risk
B19: 3 | D19: ⚡ | E19: Power Vein | F19: Local rerouting; brief flicker | G19: Surging; secondary nodes cut off | H19: Wide power outage across one or more systems
B20: 4 | D20: 🧠 | E20: Bridge / Command Core | F20: Momentary system desync | G20: Coordination loss; action delay | H20: Bridge offline; command rerouted or disrupted entirely
B21: 5 | D21: 📡 | E21: Sensors / Comms Array | F21: Targeting penalty; degraded resolution | G21: Full quadrant blind; sensor blackout | H21: Sensor array destroyed; no external awareness on this side
B22: 6 | D22: 🌡️ | E22: Cooling Systems | F22: Efficiency drop; local overheating | G22: Coolant throughput halved; reactor throttled | H22: Heat rejection failure; thermal buildup threatening system stability
B23: 7 | E23: Side Hull / Armor | F23: Surface scarring; no penetration | G23: Cracked plating; risk of breach under pressure | H23: Hull breach; interior compartments exposed to space | M23: 2 | N23: Reactor Core | P23: 2 | Q23: Bridge / Command Core
B24: 8 | E24: Habitat Section | F24: Shaken crew; minor compartment disruption | G24: Habitat compromised; crew injured | H24: Major breach; crew casualties and life support failure | M24: 3 | N24: Power Trunking | P24: 3 | Q24: Habitat Section
B25: 9 | E25: Weapons (Side) | F25: Jammed weapon; RoF reduced | G25: Weapon mount damaged; full arc offline | H25: Weapons destroyed or blown off; explosion risk nearby | M25: 4 | N25: Bridge / Command Core | P25: 4 | Q25: Cooling systems
B26: 10 | D26: 🚀 | E26: Fuel Tanks | F26: Pressurization loss; transfer pump failure | G26: Fuel leak; throttling required | H26: Tank rupture; risk of fire/explosion and mass loss | M26: 5 | N26: Sensors / Comms Array | P26: 5 | Q26: Sensors / Comms
B27: 11 | E27: Secondary Systems | F27: Utility outage; minimal operational impact | G27: Redundant function lost; increased system load elsewhere | H27: Secondary systems destroyed; damage control, life support etc. fail | M27: 6 | N27: Radiators | P27: 6 | Q27: Power Trunking
B28: 12 | D28: 🚀 | E28: Propulsion Ancillaries | F28: Minor thrust fluctuation; attitude hold degraded | G28: Stabilizers or guidance fail; erratic maneuvering | H28: Full control loss on one axis; spin or tumble risk | M28: 7 | N28: Side Hull / Armor | P28: 7 | Q28: Rear Hull / Armor
M29: 8 | N29: Habitat Section | P29: 8 | Q29: Propulsion Nozzles
B30: 🔴 REAR Arc | M30: 9 | N30: Weapons (Side) | P30: 9 | Q30: Engine Mounts
B31: Roll | E31: Subsystem | F31: Light | G31: Heavy | H31: Critical
B32: 2 | D32: 🧠 | E32: Bridge / Command Core | F32: Minor control delays; backup systems online | G32: Severe latency; partial loss of ship control | H32: Core AI offline; command rerouted or lost | M32: 10 | N32: Fuel Tanks | P32: 10 | Q32: Fuel Tanks
B33: 3 | E33: Habitat Section | F33: Local injuries or decompression | G33: Major breach; life support failing | H33: Section destroyed; survivors at risk | M33: 11 | N33: Secondary Systems | P33: 11 | Q33: Reactor Shielding
B34: 4 | D34: 🌡️ | E34: Cooling Systems | F34: Reduced thermal capacity; reactor throttled | G34: Major sink ruptured; overheating begins | H34: Cooling collapse; system-wide overheating risk | M34: 12 | N34: Propulsion Ancillaries | P34: 12 | Q34: Reactor Core
B35: 5 | D35: 📡 | E35: Comms/Sensor Suite | F35: Signal interference; degraded targeting | G35: Array damage; blind spots in coverage | H35: Total blackout; sensor blackout in rear hemisphere
B36: 6 | D36: ⚡ | E36: Power Vein | F36: Power fluctuations; minor load-shedding | G36: Partial power loss; rerouting required | H36: Power grid failure; system-wide blackouts
B37: 7 | E37: Rear Hull / Armor | F37: Armor blistered; cosmetic burns | G37: Armor section holed; exposed internals | H37: Hull breach; internal compartments compromised
B38: 8 | D38: 🚀 | E38: Main Nozzle | F38: Thrust instability; vectoring loss | G38: Nozzle damage; maneuvering hampered | H38: Nozzle destroyed; main thrust offline
B39: 9 | D39: 🚀 | E39: Engine Mounts | F39: Structural vibration; minor stress fractures | G39: Mount damage; reduced acceleration efficiency | H39: Engine detachment imminent; drive unsafe
B40: 10 | D40: 🚀 | E40: Fuel Tanks | F40: Minor leak; containment holding | G40: Major leak; fire risk present | H40: Explosion risk; rapid depressurization
B41: 11 | D41: 🚀 | E41: Reactor Shielding | F41: Containment stress; monitoring required | G41: Radiation leakage; crew exposure risk | H41: Shield breached; core exposed
B42: 12 | D42: 🚀 | E42: Reactor Core | F42: Flux spike; auto-dampeners engaged | G42: Core damage; efficiency drop | H42: Core breach; meltdown imminent

Sheet Avaries
B2: PROPULSION DAMAGE
B3: Roll | C3: Light Damage | D3: Critical Damage
B4: 1 | C4: A main engine sputters, reducing max thrust briefly. | D4: Engine bell torn or fused—full thrust unavailable.
B5: 2 | C5: Minor leak, efficiency drops until patched. | D5: Rapid fuel loss forces shutdown or explosion risk.
B6: 3 | C6: Gimbal range reduced, maneuverability impaired. | D6: Nozzle shatters—course control lost.
B7: 4 | C7: Overheat warning—limited burns only. | D7: Propulsion system seizes—total engine lockout.
B8: 5 | C8: Delayed response to navigation commands. | D8: Thruster fires erratically—risk of spin.
B9: 6 | C9: Misalignment causes vibration at high thrust. | D9: Mount ruptures—engine detaches or self-destructs.
B12: POWER DAMAGE
B13: Roll | C13: Light Damage | D13: Critical Damage
B14: 1 | C14: Temporary power drop, subsystems reboot. | D14: Arcs disable connected systems—power rerouted.
B15: 2 | C15: Reactor throttled—reduced energy output. | D15: Reactor scrams—ship on emergency reserves.
B16: 3 | C16: Energy bottleneck—auxiliary systems flicker. | D16: Conduits rupture—fires or electrical arcs spread.
B17: 4 | C17: Emergency battery drains faster than expected. | D17: Batteries explode—localized EMP hits nearby gear.
B18: 5 | C18: Radiators run hot—power output throttled. | D18: Radiators offline—reactor forced to idle or shut down.
B19: 6 | C19: Voltage drops—some equipment underpowered. | D19: Power grid collapse—entire ship blacks out.
B22: SENSORS DAMAGE
B23: Roll | C23: Light Damage | D23: Critical Damage
B24: 1 | C24: Range or resolution reduced. | D24: Sensor blind in one arc.
B25: 2 | C25: Delayed or inconsistent telemetry. | D25: Feedback loop disables tracking.
B26: 3 | C26: Target lock degrades, increased jitter. | D26: Tracking lost—targeting systems disabled.
B27: 4 | C27: False signals or ghost contacts. | D27: Data flood—sensor net overloads and reboots.
B28: 5 | C28: Some readings unavailable or delayed. | D28: Total sensor blackout—targeting and nav blind.
B29: 6 | C29: Sensors forced to low-power mode. | D29: Optics fry—system burns out.
B32: CPU DAMAGE
B33: Roll | C33: Light Damage | D33: Critical Damage
B34: 1 | C34: Delays or glitches in tactical responses. | D34: Combat AI crashes—manual control needed.
B35: 2 | C35: Navigation and fire control slow. | D35: Predictive systems offline—misses and misfires.
B36: 3 | C36: Optimization algorithms fail—lower performance. | D36: Ship coordination fails—automated systems disabled.
B37: 4 | C37: Delayed input processing. | D37: Commands lost or reversed—risk of collision or friendly fire.
B38: 5 | C38: Minor brownouts disrupt task allocation. | D38: CPU resets—ship acts on outdated data or panics.
B39: 6 | C39: Minor damage, self-diagnostics in progress. | D39: Core CPU melted or torn—control lost.

Sheet Calculs
B1: https://upload.wikimedia.org/wikipedia/commons/8/89/236084main_MilkyWay-full-annotated.jpg
Z2: g | AB2: km/s
B3: 150 M km = 1 AU = 12 lm | P3: 1g | R3: 10 | S3: m/s² | T3: =R3*60*60/1000 -> 36 | U3: km/min² | Z3: 1.5 | AB3: 1
B4: https://upload.wikimedia.org/wikipedia/commons/e/ee/Orbit_Alpha_Centauri_AB_arcsec.png | P4: 1g | R4: =R3/(1000) -> 0.01 | S4: km/s² | Z4: 5 | AB4: 3
B5: Depuis B | C5: AU | D5: Mkm | E5: vm | F5: c | I5: ip | J5: is | P5: 1m | R5: =R4*60 -> 0.6 | S5: km/s/m | T5: 36 | U5: km | Y5: 1 min | Z5: 10 | AB5: 6
C6: 0.12 | D6: 15 | F6: 1 | H6: m | P6: 1h | R6: =R4*60*60 -> 36 | S6: km/s/h | T6: =W6/(1000) -> 129.6 | U6: kkm/h² | W6: =T3*60*60 -> 129600 | X6: km/h² | Z6: 20 | AB6: 12
B7: Abiwan | C7: 1 | D7: 150 | F7: =C7/$R$43 -> 8.3333333 | I7: =F7/#REF! -> #REF! | P7: 1j | R7: =R6*24 -> 864 | S7: km/s/j | T7: =W7/150000000 -> 0.497664 | U7: AU/j² | W7: =W6*24*24 -> 74649600 | X7: km/j² | Z7: 50 | AB7: 30
B8: Metal | C8: 10 | D8: =C8*D$7 -> 1500 | F8: =C8/$R$44 -> 1.3888889 | H8: h | I8: =F8/#REF! -> #REF! | J8: =F8*1/$R$19 -> 2.3148148 | L8: jours | M8: Propre (0.2c) | Z8: 100 | AB8: 60
B9: A | C9: 20 | D9: =C9*D$7 -> 3000 | F9: =C9/$R$44 -> 2.7777778 | I9: =F9*1/#REF! -> #REF! | J9: =F9*1/$R$19 -> 4.6296296 | M9: Maintenu (100)
B10: Ceinture | C10: 23 | D10: =C10*D$7 -> 3450 | F10: =C10/$R$44 -> 3.1944444 | I10: =F10*1/#REF! -> #REF! | J10: =F10*1/$R$19 -> 5.3240741 | U10: 1000
B11: Routes | C11: 25 | D11: =C11*D$7 -> 3750 | F11: =C11/$R$44 -> 3.4722222 | I11: =F11*1/#REF! -> #REF! | J11: =F11*1/$R$19 -> 5.787037 | O11: temps propre | P11: P | Z11: g | AA11: acc | AC11: dj | AD11: da
C12: AU | D12: ly | E12: c | F12: is | G12: isp | H12: is1 | I12: is1p | J12: is2 | K12: is2p | Z12: 1 | AB12: m
B13: Proxima | C13: 15 k | D13: 0.24 | E13: =D13*12 -> 2.88 | F13: =E13*1/$R$19 -> 4.8 | G13: =F13*S$20 -> 3.84 | H13: =E13*1/$R$21 -> 4.1142857 | I13: =H13*S$21 -> 2.88 | J13: =E13*1/$R$22 -> 3.6 | K13: =H13*$S$22 -> 2.4685714 | L13: mois | R13: temps standard * dilatation | X13: 1 | Y13: km/s | Z13: 10 | AB13: m
D14: 3 | E14: =D14 -> 3 | F14: =E14*1/$R$19 -> 5 | G14: =F14*S$20 -> 4 | H14: =E14*1/$R$21 -> 4.2857143 | I14: =H14*S$21 -> 3 | J14: =E14*1/$R$22 -> 3.75 | K14: =H14*$S$22 -> 2.5714286 | L14: années | O14: Vitesse | Z14: 20 | AB14: m
B15: Sol | D15: 4 | E15: =D15 -> 4 | F15: =E15*1/$R$19 -> 6.6666667 | G15: =F15*S$20 -> 5.3333333 | H15: =E15*1/$R$21 -> 5.7142857 | I15: =H15*S$21 -> 4 | J15: =E15*1/$R$22 -> 5 | K15: =H15*$S$22 -> 3.4285714 | Z15: 20 | AB15: m
B16: Wolf | D16: 5 | E16: =D16 -> 5 | F16: =E16*1/$R$19 -> 8.3333333 | G16: =F16*S$20 -> 6.6666667 | H16: =E16*1/$R$21 -> 7.1428571 | I16: =H16*S$21 -> 5 | J16: =E16*1/$R$22 -> 6.25 | K16: =H16*$S$22 -> 4.2857143 | O16: manoeuvre | P16: vm | R16: 1 | S16: km/s
O17: pointe | P17: vp | R17: 1000 | S17: km/s | Z17: g | AA17: acc | AC17: dj | AD17: da
B18: https://en.wikipedia.org/wiki/List_of_nearest_stars_and_brown_dwarfs | O18: (dilatation d) | R18: c | S18: d | Z18: 1 | AA18: 20 | AB18: m | AC18: =AD18/2 -> 0
B19: Sol | C19: ly | D19: sec | F19: isy | I19: isP | J19: is2y | K19: is2P | L19: long(equat) | M19: lat | O19: jump interplanétaire | P19: ip | R19: 0.6 | S19: 1 | X19: 10 | Y19: km/s | Z19: 10 | AA19: 2 | AB19: m | AC19: =AD19/2 -> 0
B20: Centre galactique | C20: 20k | D20: C | J20: =20000/$R$22 -> 25000 | K20: =J20*$S$22 -> 15000 | L20: 17h45 | M20: -30 | O20: jump interstellaire | P20: is | S20: 0.8 | Z20: 20 | AA20: 1 | AB20: m | AC20: =AD20/2 -> 180 | AD20: 360 | AE20: km
B21: Alpha Centauri | C21: 4 | D21: CES | E21: -30° | F21: =C21/$R$19 -> 6.6666667 | I21: =F21*$S$20 -> 5.3333333 | J21: =C21/$R$22 -> 5 | K21: =J21*$S$22 -> 3 | L21: 14h30 | M21: -62 | O21: jumper +1 | P21: is1 | R21: 0.7 | S21: 0.7
B22: Barnard | C22: 6 | D22: CN | E22: 30° | F22: =C22/$R$19 -> 10 | I22: =F22*$S$20 -> 8 | J22: =C22/$R$22 -> 7.5 | K22: =J22*$S$22 -> 4.5 | L22: 18h | M22: 4 | O22: jumper +2 | P22: is2 | R22: 0.8 | S22: 0.6 | Z22: g | AA22: acc | AC22: dj | AD22: da
B23: Luhman | C23: 7 | D23: ES | E23: -90° | F23: =C23/$R$19 -> 11.666667 | I23: =F23*$S$20 -> 9.3333333 | J23: =C23/$R$22 -> 8.75 | K23: =J23*$S$22 -> 5.25 | L23: 11h | M23: -60 | U23: =20000/60 -> 333.33333 | X23: =1000 -> 1000 | Y23: km/s | Z23: 1 | AA23: 1 | AB23: j | AC23: =AD23/2 -> 0.15 | AD23: 0.3 | AE23: AU
B24: Wolf | C24: 8 | D24: E | E24: 0° | F24: =C24/$R$19 -> 13.333333 | I24: =F24*$S$20 -> 10.666667 | J24: =C24/$R$22 -> 10 | K24: =J24*$S$22 -> 6 | L24: 11h | M24: =7 -> 7 | X24: =X23*24*3600/150000000 -> 0.576 | Y24: AU/j | Z24: 25 | AA24: 1 | AB24: h | AC24: =AD24/2 -> 0.5 | AD24: 1 | AE24: Mkm
B25: Lalande | C25: 8 | D25: AS | F25: =C25/$R$19 -> 13.333333 | I25: =F25*$S$20 -> 10.666667 | J25: =C25/$R$22 -> 10 | K25: =J25*$S$22 -> 6 | L25: 6h45 | M25: -16 | O25: Secteurs | X25: =X24*7 -> 4.032 | Y25: AU/sm | Z25: 50 | AA25: 30 | AB25: m | AC25: =AD25/2 -> 300 | AD25: 600 | AE25: kkm
B26: Sirius | C26: 8 | D26: A | F26: =C26/$R$19 -> 13.333333 | I26: =F26*$S$20 -> 10.666667 | J26: =C26/$R$22 -> 10 | K26: =J26*$S$22 -> 6 | O26: Centre | P26: C | R26: 18 | S26: -30
B27: Luyten | C27: 9 | D27: EN | E27: 30° | F27: =C27/$R$19 -> 15 | I27: =F27*$S$20 -> 12 | J27: =C27/$R$22 -> 11.25 | K27: =J27*$S$22 -> 6.75 | L27: 11h | M27: 35 | O27: Anticentre | P27: A | R27: 6 | S27: 30
B28: Sagiross | C28: 10 | D28: C | E28: 0° | F28: =C28/$R$19 -> 16.666667 | I28: =F28*$S$20 -> 13.333333 | J28: =C28/$R$22 -> 12.5 | K28: =J28*$S$22 -> 7.5 | L28: 19h | M28: -24 | O28: Est | P28: E | R28: 12 | S28: 0
B29: Androross | C29: 10 | D29: W | F29: =C29/$R$19 -> 16.666667 | I29: =F29*$S$20 -> 13.333333 | J29: =C29/$R$22 -> 12.5 | K29: =J29*$S$22 -> 7.5 | L29: 23h40 | M29: 44 | O29: West | P29: W | R29: 0 | S29: 0 | Y29: 21h | Z29: CW | AB29: 0h | AD29: AW | AE29: 3h
B30: Eridani | C30: 10 | D30: AWS | F30: =C30/$R$19 -> 16.666667 | I30: =F30*$S$20 -> 13.333333 | J30: =C30/$R$22 -> 12.5 | K30: =J30*$S$22 -> 7.5 | L30: 3h30 | M30: -10 | O30: Nord polaire | P30: N | AA30: -15° | AB30: W | AC30: 15°
B31: Lacaille | C31: 10 | D31: WS | F31: =C31/$R$19 -> 16.666667 | I31: =F31*$S$20 -> 13.333333 | J31: =C31/$R$22 -> 12.5 | K31: =J31*$S$22 -> 7.5 | L31: 23h | M31: -35 | O31: Sud polaire | P31: S | Y31: 18h | Z31: C | AA31: -30° | AC31: 30° | AD31: A | AE31: 6h
B32: Virgiross | C32: 11 | D32: E | E32: 0° | F32: =C32/$R$19 -> 18.333333 | I32: =F32*$S$20 -> 14.666667 | J32: =C32/$R$22 -> 13.75 | K32: =J32*$S$22 -> 8.25 | L32: 12h | M32: 0 | AB32: E
B33: Aquarii | C33: 11 | D33: W | F33: =C33/$R$19 -> 18.333333 | I33: =F33*$S$20 -> 14.666667 | J33: =C33/$R$22 -> 13.75 | K33: =J33*$S$22 -> 8.25 | L33: 23h | M33: -15 | O33: Unité stellaire | P33: AU | R33: 150 | S33: Mkm | Y33: 15h | Z33: CE | AB33: 12h | AD33: AE | AE33: 9h
B34: Procyon | C34: 11 | D34: AS | F34: =C34/$R$19 -> 18.333333 | I34: =F34*$S$20 -> 14.666667 | J34: =C34/$R$22 -> 13.75 | K34: =J34*$S$22 -> 8.25 | L34: 8h | M34: 5 | P34: lm | R34: 0.1 | S34: AU | X34: =sum(Sheet27!C5:C19) -> 360
B35: Cygni | C35: 11 | D35: CWN | F35: =C35/$R$19 -> 18.333333 | I35: =F35*$S$20 -> 14.666667 | J35: =C35/$R$22 -> 13.75 | K35: =J35*$S$22 -> 8.25 | L35: 21h | M35: 40 | O35: jour lumière | P35: ld | R35: =R39*3600*24/R33 -> 172.8 | S35: AU
B36: Struve | C36: 11 | D36: CN | F36: =C36/$R$19 -> 18.333333 | I36: =F36*$S$20 -> 14.666667 | J36: =C36/$R$22 -> 13.75 | K36: =J36*$S$22 -> 8.25 | L36: 19h | M36: 60 | O36: année lumière | P36: ly | R36: =R35*365/1000 -> 63.072 | S36: kAU
B38: Groombridge | C38: 11 | D38: WN | F38: =C38/$R$19 -> 18.333333 | I38: =F38*$S$20 -> 14.666667 | J38: =C38/$R$22 -> 13.75 | K38: =J38*$S$22 -> 8.25 | L38: 24h | M38: 44
B39: Indi | C39: 12 | D39: CWS | F39: =C39/$R$19 -> 20 | I39: =F39*$S$20 -> 16 | J39: =C39/$R$22 -> 15 | K39: =J39*$S$22 -> 9 | L39: 22h | M39: -56 | O39: vitesse lumière | P39: c | R39: =300000 / 1000000 -> 0.3 | S39: Mkm/s | Z39: g | AA39: acc | AC39: dj | AD39: da
B40: Tau Ceti | C40: 12 | D40: AWS | F40: =C40/$R$19 -> 20 | I40: =F40*$S$20 -> 16 | J40: =C40/$R$22 -> 15 | K40: =J40*$S$22 -> 9 | L40: 2h | M40: -15 | X40: =1800 -> 1800 | Y40: km/s | Z40: 1 | AA40: 2 | AB40: j | AC40: =AD40/2 -> 0.15 | AD40: 0.3 | AE40: AU
B41: Cancri | C41: 12 | D41: CWN | F41: =C41/$R$19 -> 20 | I41: =F41*$S$20 -> 16 | J41: =C41/$R$22 -> 15 | K41: =J41*$S$22 -> 9 | L41: 20h | M41: 9 | R41: c | X41: =X40*3600/150000000 -> 0.0432 | Y41: AU/h | Z41: 20 | AB41: j | AC41: =AD41/2 -> 0 | AE41: AU
B42: Neuten | C42: 12 | D42: AE | F42: =C42/$R$19 -> 20 | I42: =F42*$S$20 -> 16 | J42: =C42/$R$22 -> 15 | K42: =J42*$S$22 -> 9 | L42: 7h30 | M42: 5 | P42: ls | R42: =R39/R33 -> 0.002 | S42: AU | X42: =X41*24 -> 1.0368 | Y42: AU/j | Z42: 30 | AB42: h | AC42: =AD42/2 -> 0 | AE42: Mkm
B43: Teegarden | C43: 12 | D43: AW | F43: =C43/$R$19 -> 20 | I43: =F43*$S$20 -> 16 | J43: =C43/$R$22 -> 15 | K43: =J43*$S$22 -> 9 | L43: 3h | M43: 16 | P43: lm | R43: =R39*60/R33 -> 0.12 | S43: AU | X43: =X42*7 -> 7.2576 | Y43: AU/sm | Z43: 50 | AA43: 1 | AB43: h | AC43: =AD43/2 -> 0 | AE43: kkm
B44: Kapteyn | C44: 13 | D44: AS2 | F44: =C44/$R$19 -> 21.666667 | I44: =F44*$S$20 -> 17.333333 | J44: =C44/$R$22 -> 16.25 | K44: =J44*$S$22 -> 9.75 | L44: 5h | M44: -45 | P44: lh | R44: =R39*3600/R33 -> 7.2 | S44: AU
B45: Van Maanen | C45: 14 | D45: AS | F45: =C45/$R$19 -> 23.333333 | I45: =F45*$S$20 -> 18.666667 | J45: =C45/$R$22 -> 17.5 | K45: =J45*$S$22 -> 10.5 | L45: 5h | M45: 5 | P45: ld | R45: =R39*3600*24/R33 -> 172.8 | S45: AU
B46: Altair | C46: 16 | D46: CWN | F46: =C46/$R$19 -> 26.666667 | I46: =F46*$S$20 -> 21.333333 | J46: =C46/$R$22 -> 20 | K46: =J46*$S$22 -> 12 | L46: 20h | M46: 9 | P46: lmois | R46: 5k | S46: AU
B47: Escier | C47: 13 | D47: CS | E47: -30° | G47: SCR | L47: 19h | M47: -63 | P47: ly | R47: 63k | S47: AU | X47: 0.014 | Y47: c | Z47: g | AA47: acc | AC47: dj | AD47: da
B48: Rex | C48: 14 | D48: CE | E48: 0° | G48: Wolf 1061 | L48: 16h30 | M48: -12 | X48: 0.1 | Y48: AU/h | Z48: 20 | AA48: 6 | AB48: h | AC48: =AD48/2 -> 50 | AD48: 100 | AE48: kkm
C49: 14 | D49: CES2 | E49: -30° | G49: MASS | L49: 16h | M49: -50 | X49: =X48*24 -> 2.4 | Y49: AU/j | Z49: 30 | AA49: 4 | AB49: h | AC49: =AD49/2 -> 0.1 | AD49: 0.2 | AE49: AU
V50: Parcouru | X50: =X49*7 -> 16.8 | Y50: AU/sm | Z50: 50 | AA50: 2 | AB50: h | AC50: =AD50/2 -> 0.1 | AD50: 0.2 | AE50: AU
O51: 1 | P51: g | R51: =O51*10 -> 10 | S51: m/s² | T51: =R51*60/1000 -> 0.6 | U51: km/min²
B52: km/s | C52: speed = g x time x A | H52: km/s² | I52: days | K52: A | L52: =60*60*24 -> 86400 | R52: =R51/(1000) -> 0.01 | S52: km/s²
B53: AU | C53: distance = speed x time x B x A | H53: km/s | I53: days | K53: B | L53: =1/149597870.691*60*60*24 -> 0.00057754833 | P53: 1m | R53: =R52*60 -> 0.6 | S53: km/s | T53: =R53*60 -> 36 | U53: km/min | V53: =R53/2*60 -> 18 | W53: =T51 -> 0.6 | Z53: g | AA53: acc | AC53: dj | AD53: da
C54: distance = g x time ² x A² x B | P54: 2 | R54: =$R$53*P54 -> 1.2 | S54: km/s | T54: =T$53*P54^2 -> 144 | U54: km/xm² | V54: =R54/2*P54*60 -> 72 | X54: 0.03c | Z54: 20
B55: days | C55: time = square ( distance/g ) | H55: AU | I55: km/s² | P55: 3 | R55: =$R$53*P55 -> 1.8 | S55: km/s | T55: =T$53*P55^2 -> 324 | U55: km/xm² | V55: =R55/2*P55*60 -> 162 | X55: AU/h
B56: days | C56: time = square ( distance / (g x A² x B) ) | J56: AU | K56: AU/j | P56: 4 | R56: =$R$53*P56 -> 2.4 | S56: km/s | T56: =T$53*P56^2 -> 576 | U56: km/xm² | V56: =R56/2*P56*60 -> 288 | X56: AU/h
P57: 5 | R57: =$R$53*P57 -> 3 | S57: km/s | T57: =T$53*P57^2 -> 900 | U57: km/xm² | V57: =R57/2*P57*60 -> 450 | X57: AU/h
O58: c | P58: 6 | R58: =$R$53*P58 -> 3.6 | S58: km/s | T58: =T$53*P58^2 -> 1296 | U58: km/xm² | V58: =R58/2*P58*60 -> 648 | X58: AU/h
O59: =R59/300000 -> 0.00012 | P59: 1h | R59: =R52*60*60 -> 36 | S59: km/s | T59: =R59/149597870.691*60*60*24 -> 0.02079174 | U59: AU/j | V59: =R59/2*P59*60 -> #VALUE! | X59: AU/h | AB59: =200/30000 -> 0.0066666667
E60: Distance parcourue | K60: =1/2*3 -> 1.5 | O60: =R60/300000 -> 0.00024 | P60: 2 | R60: =R59*2 -> 72 | S60: km/s | T60: =R60/149597870.691*60*60*24 -> 0.04158348 | U60: AU/j | V60: =R60/2*P60*60 -> 4320 | X60: AU/h
B61: 1g | C61: Vitesse | E61: max | F61: stop | O61: =R61/300000 -> 0.00036 | P61: 3 | R61: =R$59*P61 -> 108 | S61: km/s | T61: =R61/149597870.691*60*60*24 -> 0.062375219 | U61: AU/j | V61: =R61/2*P61*60 -> 9720 | X61: AU/h | Y61: g | Z61: km/m | AA61: su
B62: Accel, 1m | C62: =R5 -> 0.6 | D62: km/s | E62: =C62/2*60 -> 18 | F62: =E62/2 -> 9 | H62: km | O62: =R62/300000 -> 0.00048 | P62: 4 | R62: =R$59*P62 -> 144 | S62: km/s | T62: =R62/149597870.691*60*60*24 -> 0.083166959 | U62: AU/j | V62: =R62/2*P62*60 -> 17280 | X62: AU/h | Y62: 1 | Z62: =Y62*36 -> 36 | AA62: =Z62/36 -> 1
B63: 10 min | C63: =R5*10 -> 6 | D63: km/s | E63: =C63/2*60*10 -> 1800 | F63: =E63/2 -> 900 | H63: km | O63: =R63/300000 -> 0.0006 | P63: 5 | R63: =R$59*P63 -> 180 | S63: km/s | T63: =R63/149597870.691*60*60*24 -> 0.1039587 | U63: AU/j | V63: =R63/2*P63*60 -> 27000 | X63: AU/h | Y63: 8 | Z63: =Y63*60 -> 480 | AA63: =Z63/20 -> 24
B64: 1 heure | C64: =R6 -> 36 | D64: km/s | E64: =C64/2*3600/1000 -> 64.8 | F64: =E64/2 -> 32.4 | H64: kkm | O64: =R64/300000 -> 0.00072 | P64: 6 | R64: =R$59*P64 -> 216 | S64: km/s | T64: =R64/149597870.691*60*60*24 -> 0.12475044 | U64: AU/j | V64: =R64/2*P64*60 -> 38880 | X64: AU/h | Y64: km/s | Z64: km/m | AA64: cu
B65: 1 jour | C65: =R7 -> 864 | D65: km/s | E65: =C65/2*3600*24/1000000 -> 37.3248 | F65: =E65/2 -> 18.6624 | H65: Mkm | O65: =R65/300000 -> 0.00084 | P65: 7 | R65: =R$59*P65 -> 252 | S65: km/s | T65: =R65/149597870.691*60*60*24 -> 0.14554218 | U65: AU/j | V65: =R65/2*P65*60 -> 52920 | X65: AU/h | AA65: =Y63*1.5 -> 12
B66: Pointe, 1 sem | C66: =1000 -> 1000 | D66: km/s | E66: =(E65*2 + C66*3600*24*5) /150000000 -> 2.8800005 | F66: =(E65*4 +C66*3600*24*3) /150000000 -> 1.728001 | H66: AU | O66: =R66/300000 -> 0.00096 | P66: 8 | R66: =R$59*P66 -> 288 | S66: km/s | T66: =R66/149597870.691*60*60*24 -> 0.16633392 | U66: AU/j | V66: =R66/2*P66*60 -> 69120 | X66: AU/h
H67: Distance parcourue | O67: =R67/300000 -> 0.00108 | P67: 9 | R67: =R$59*P67 -> 324 | S67: km/s | T67: =R67/149597870.691*60*60*24 -> 0.18712566 | U67: AU/j | V67: =R67/2*P67*60 -> 87480 | X67: AU/h
B68: =O51 -> 1 | C68: g | D68: Vitesse | H68: max | I68: stop | O68: =R68/300000 -> 0.0012 | P68: 10 | R68: =R$59*P68 -> 360 | S68: km/s | T68: =R68/149597870.691*60*60*24 -> 0.2079174 | U68: AU/j | V68: =R68/2*P68*60 -> 108000 | X68: AU/h | Z68: RCF = 11.2 x Radius x (RPM/1,000)2
B69: Accel, 1 s | C69: =R52 -> 0.01 | D69: km/s | H69: =C69/2*60 -> 0.3 | I69: =H69/2 -> 0.15 | J69: km | M69: AU/j | O69: =R69/300000 -> 0.00132 | P69: 11 | R69: =R$59*P69 -> 396 | S69: km/s | T69: =R69/149597870.691*60*60*24 -> 0.22870914 | U69: AU/j | V69: =R69/2*P69*60 -> 130680 | X69: AU/h
B70: 1 m | C70: =R53 -> 0.6 | D70: km/s | H70: =C70/2*60 -> 18 | I70: =H70/2 -> 9 | J70: km | M70: AU/j | O70: =R70/300000 -> 0.00144 | P70: 12 | R70: =R$59*P70 -> 432 | S70: km/s | T70: =R70/149597870.691*60*60*24 -> 0.24950088 | U70: AU/j | V70: =R70/2*P70*60 -> 155520 | X70: AU/h | Z70: radius (m) | AA70: 30
B71: 1 h | C71: =R59 -> 36 | D71: km/s | E71: =#REF! -> #REF! | F71: AU/h | H71: =C71*60*60 /1000000 /2 -> 0.0648 | I71: =H71/2 -> 0.0324 | J71: Mkm | L71: =E71*24 -> #REF! | M71: AU/j | O71: =R71/300000 -> 0.00156 | P71: 13 | R71: =R$59*P71 -> 468 | S71: km/s | T71: =R71/149597870.691*60*60*24 -> 0.27029262 | U71: AU/j | V71: =R71/2*P71*60 -> 182520 | X71: AU/h | Z71: RPM | AA71: 5
B72: 2 h | C72: =O60 -> 0.00024 | D72: c | E72: =W60 | F72: AU/h | H72: =#REF!/2 -> #REF! | I72: =H72/2 -> #REF! | J72: AU | L72: =E72*24 -> 0 | M72: AU/j | O72: =R72/300000 -> 0.00168 | P72: 14 | R72: =R$59*P72 -> 504 | S72: km/s | T72: =R72/149597870.691*60*60*24 -> 0.29108436 | U72: AU/j | V72: =R72/2*P72*60 -> 211680 | X72: AU/h | Z72: g | AA72: =1120*AA70*(AA71/1000)^2 -> 0.84
B73: 3 h | C73: =O61 -> 0.00036 | D73: c | E73: =W61 | F73: AU/h | H73: =#REF!/2 -> #REF! | I73: =H73/2 -> #REF! | J73: AU | L73: =E73*24 -> 0 | M73: AU/j | O73: =R73/300000 -> 0.0018 | P73: 15 | R73: =R$59*P73 -> 540 | S73: km/s | T73: =R73/149597870.691*60*60*24 -> 0.3118761 | U73: AU/j | X73: AU/h
B74: 6 h | C74: =O64 -> 0.00072 | D74: c | E74: =W64 | F74: AU/h | H74: =#REF!/2 -> #REF! | I74: =H74/2 -> #REF! | J74: AU | L74: =E74*24 -> 0 | M74: AU/j | O74: =R74/300000 -> 0.00192 | P74: 16 | R74: =R$59*P74 -> 576 | S74: km/s | T74: =R74/149597870.691*60*60*24 -> 0.33266784 | U74: AU/j | X74: AU/h
B75: 8 h | C75: =O66 -> 0.00096 | D75: c | E75: =W66 | F75: AU/h | H75: =#REF!/2 -> #REF! | I75: =H75/2 -> #REF! | J75: AU | L75: =E75*24 -> 0 | M75: AU/j | O75: =R75/300000 -> 0.00204 | P75: 17 | R75: =R$59*P75 -> 612 | S75: km/s | T75: =R75/149597870.691*60*60*24 -> 0.35345958 | U75: AU/j | X75: AU/h
B76: 12 h | C76: =O70 -> 0.00144 | D76: c | E76: =W70 | F76: AU/h | H76: =#REF!/2 -> #REF! | I76: =H76/2 -> #REF! | J76: AU | L76: =E76*24 -> 0 | M76: AU/j | O76: =R76/300000 -> 0.00216 | P76: 18 | R76: =R$59*P76 -> 648 | S76: km/s | T76: =R76/149597870.691*60*60*24 -> 0.37425132 | U76: AU/j | X76: AU/h | AB76: =6*7 -> 42
B77: 24 h | C77: =O82 -> 0.00288 | D77: c | E77: =W82 | F77: AU/h | H77: =#REF!/2 -> #REF! | I77: =H77/2 -> #REF! | J77: AU | L77: =E77*24 -> 0 | M77: AU/j | O77: =R77/300000 -> 0.00228 | P77: 19 | R77: =R$59*P77 -> 684 | S77: km/s | T77: =R77/149597870.691*60*60*24 -> 0.39504306 | U77: AU/j | X77: AU/h
B78: 48 h | C78: =O83 -> 0.00576 | D78: c | E78: =W83 | F78: AU/h | H78: =#REF!/2 -> #REF! | I78: =H78/2 -> #REF! | J78: AU | L78: =E78*24 -> 0 | M78: AU/j | O78: =R78/300000 -> 0.0024 | P78: 20 | R78: =R$59*P78 -> 720 | S78: km/s | T78: =R78/149597870.691*60*60*24 -> 0.4158348 | U78: AU/j | X78: AU/h
O79: =R79/300000 -> 0.00252 | P79: 21 | R79: =R$59*P79 -> 756 | S79: km/s | T79: =R79/149597870.691*60*60*24 -> 0.43662654 | U79: AU/j | X79: AU/h
O80: =R80/300000 -> 0.00264 | P80: 22 | R80: =R$59*P80 -> 792 | S80: km/s | T80: =R80/149597870.691*60*60*24 -> 0.45741828 | U80: AU/j | X80: AU/h
O81: =R81/300000 -> 0.00276 | P81: 23 | R81: =R$59*P81 -> 828 | S81: km/s | T81: =R81/149597870.691*60*60*24 -> 0.47821002 | U81: AU/j | X81: AU/h
I82: Distance (AU) | O82: =R82/300000 -> 0.00288 | P82: 24 | Q82: h | R82: =R$59*P82 -> 864 | S82: km/s | T82: =R82/149597870.691*60*60*24 -> 0.49900175 | U82: AU/j | X82: AU/h
H83: Poin | I83: Acc | J83: Jum | O83: =R83/300000 -> 0.00576 | P83: 48 | Q83: h | R83: =R$59*P83 -> 1728 | S83: km/s | T83: =R83/149597870.691*60*60*24 -> 0.99800351 | U83: AU/j | X83: AU/h
B84: 1j | C84: =1000 -> 1000 | D84: km/s | E84: =C84*3600/150000000 -> 0.024 | F84: AU/h | H84: =E84*24 -> 0.576 | I84: =H84/2 -> 0.288 | J84: =I84/2 -> 0.144 | P84: 3 | R84: =R$59*P84*24 -> 2592 | S84: km/s | T84: =R84/149597870.691*60*60*24 -> 1.4970053 | U84: AU/j | X84: AU/h
P85: 4 | R85: =R$59*P85*24 -> 3456 | S85: km/s | T85: =R85/149597870.691*60*60*24 -> 1.996007 | U85: AU/j | X85: AU/h
P86: 5 | R86: =R$59*P86*24 -> 4320 | S86: km/s | T86: =R86/149597870.691*60*60*24 -> 2.4950088 | U86: AU/j | X86: AU/h | AA86: m/s | AB86: km/h
P87: =P86*2 -> 10 | R87: =R$59*P87*24 -> 8640 | S87: km/s | T87: =R87/149597870.691*60*60*24 -> 4.9900175 | U87: AU/j | X87: AU/h | AA87: 70 | AB87: =AA87/1000*60*60 -> 252
P88: =P87*2 -> 20 | R88: =R$59*P88*24 -> 17280 | S88: km/s | T88: =R88/149597870.691*60*60*24 -> 9.9800351 | U88: AU/j | X88: AU/h
B89: Depuis B | C89: AU | D89: Mkm | F89: c | J89: ip | K89: is | P89: =P88*2 -> 40 | R89: =R$59*P89*24 -> 34560 | S89: km/s | T89: =R89/149597870.691*60*60*24 -> 19.96007 | U89: AU/j | X89: AU/h
C90: 0.12 | D90: 15 | F90: 1 | I90: min | P90: =P89*2 -> 80 | R90: =R$59*P90*24 -> 69120 | S90: km/s | T90: =R90/149597870.691*60*60*24 -> 39.92014 | U90: AU/j | X90: AU/h
B91: Terra | C91: 1 | D91: 150 | F91: =C91/$R$43 -> 8.3333333 | I91: min | P91: =P90*2 -> 160 | R91: =R$59*P91*24 -> 138240 | S91: km/s | T91: =R91/149597870.691*60*60*24 -> 79.840281 | U91: AU/j | X91: AU/h
B92: * Luna | M92: jours | O92: c
B93: Mars | C93: 1.5 | D93: =C93*D$7 -> 225 | F93: =C93/$R$44 -> 0.20833333 | I93: min | J93: =F93*1/#REF! -> #REF! | K93: =F93*1/$R$19 -> 0.34722222 | O93: =R93/300000 -> 0.0864 | P93: 1mois | R93: =R82*30 -> 25920 | S93: km/s
B94: Saturn | D94: =C94*D$7 -> 0 | F94: =C94/$R$44 -> 0 | J94: =F94*1/#REF! -> #REF! | K94: =F94*1/$R$19 -> 0 | O94: =R94/300000 -> 0.1728 | P94: 2mois | R94: =R93*2 -> 51840 | S94: km/s
B95: Jupiter | D95: =C95*D$7 -> 0 | F95: =C95/$R$44 -> 0 | J95: =F95*1/#REF! -> #REF! | K95: =F95*1/$R$19 -> 0 | O95: =R95/300000 -> 0.2592 | P95: 3 | R95: =R$93*P95 -> 77760 | S95: km/s
B96: Kuiper | C96: 30 | D96: =C96*D$7 -> 4500 | F96: =C96/$R$44 -> 4.1666667 | I96: j | J96: =F96*1/#REF! -> #REF! | K96: =F96*1/$R$19 -> 6.9444444 | O96: =R96/300000 -> 0.3456 | P96: 4 | R96: =R$93*P96 -> 103680 | S96: km/s
O97: =R97/300000 -> 0.432 | P97: 5 | R97: =R$93*P97 -> 129600 | S97: km/s | Y97: 300000 | Z97: km/s
O98: =R98/300000 -> 0.5184 | P98: 6mois | R98: =R93*6 -> 155520 | S98: km/s
O99: =R99/300000 -> 1.0368 | P99: 1an | R99: =R98*2 -> 311040 | S99: km/s
X101: =((1/sqrt(1-0.14*Y97^2/Y97^2))-1)*300 -> 23.49832
L105: =155324540.283528/150000000 -> 1.0354969 | O105: 150000000

Sheet Laser
C1: http://panoptesv.com/SciFi/LaserDeathRay/DamageFromLaser.php
C2: https://www.projectrho.com/public_html/rocket/spacegunconvent2.php#id--Laser_Cannon--Attack_Vector:_Tactical_Lasers | Q2: =P9*1000 -> 140000000 | R2: J/s | S2: =Q2/1000 -> 140000 | T2: J/ms
C3: https://en.wikipedia.org/wiki/Beer%E2%80%93Lambert_law | AA3: Vaporization | AF3: 29.6 | AG3: 45.3 | AH3: 60 | AI3: kj/cm3 | AL3: 30
C4: https://doaj.org/article/d7eb7ea5e26e4e5abc7a32a8425ad07f | Q4: Heat sink = 10 GW/t | AA4: Heat resistance | AE4: 0.5 | AF4: MW/cm² | AQ4: =AQ11*10^9 -> 825078876915095
B5: Mirror radius | C5: 5 | D5: m | E5: =C5*10^-3 -> 0.005 | F5: km | H5: 20Mm−1 | L5: =C5*100 -> 500 | M5: cm | Q5: 10 | R5: kW/kg | AR5: =1.55*10^9 -> 1550000000
B6: Distance | C6: 30 | D6: km | E6: =C6/(1.5*10^8) -> 2e-07 | F6: AU | H6: =C6*1000 -> 30000 | I6: m | L6: =C6*10^3 -> 30000 | M6: m | T6: =T14/100/1000 -> 3.89424e-06 | U6: km | V6: Diffraction | X6: RT = L * 1.22 * λ / D​ | AA6: L = distance | AC6: λ = wavelength | AE6: D = lens diameter
B7: Input power | C7: 20 | D7: kW/kg | L7: Reference | M7: 2.4 | N7: kW/kg | O7: ?? | V7: Intensity | X7: BPT = BP/(π * RT²)
U8: cm | V8: Intensity 2 | X8: BPT = BP/RT²
A9: 10ms | B9: =Y11*100 -> 206269.72 | C9: kJ/cm² | J9: =J14*1000 -> 10000 | K9: kg | L9: =L14*1000 -> 200000 | M9: kW | P9: =P14*1000 -> 140000 | Q9: kW | R9: =R14*1000 -> 60000 | S9: kW
A10: absorb, air | B10: absorb, water | F10: freq | J10: Mass | L10: Input power | N10: Efficiency | P10: Aperture power | R10: Waste heat | T10: Spot radius | V10: Intensity | Y10: in 100 millisec | AA10: 10 ms | AC10: Energy | AF10: Spot area | AI10: power | AL10: radius | AO10: Beam radius | AQ10: Intensity | AS10: Intensity 2 | AV10: Beam diameter | AZ10: frequency
C11: nIR 1 | F11: 2400 | G11: nm | J11: 5 | K11: t | L11: =J11*$C$7 -> 100 | M11: MW | N11: 50 | O11: % | P11: =L11*N11/100 -> 50 | Q11: MW | R11: =L11-P11 -> 50 | S11: MW | T11: =100*1.22*AZ11*$L$6 / ($C$5*2) -> 0.8784 | U11: cm | V11: =P11/(PI()*T11^2) -> 20.626972 | W11: GW/cm² | Y11: =V11/10*1000 -> 2062.6972 | Z11: kJ/cm² | AA11: =V11/5*1000 -> 4125.3944 | AO11: =0.305*$L$6*AZ11/($C$5) -> 0.004392 | AP11: m | AQ11: =P11/(PI()*AO11^2) -> 825078.88 | AR11: GW/m² | AS11: =P11/(AO11^2) -> 2592061.7 | AT11: GW/m² | AV11: =1.22*AZ11*L6 / (C5*2) -> 0.008784 | AW11: m | AX11: =P11/(PI()*AV11^2) -> 206269.72 | AZ11: =F11*10^-9 -> 2.4e-06 | BA11: =V11*1000*1000*100 -> 2062697192
A12: 45568 | B12: 0.2 | C12: nIR 2 | F12: 1600 | G12: nm | J12: 1 | K12: t | L12: =J12*$C$7 -> 20 | M12: MW | N12: 30 | O12: % | P12: =L12*N12/100 -> 6 | Q12: GW | R12: =L12-P12 -> 14 | T12: =100*1.22*AZ12*$L$6 / ($C$5*2) -> 0.5856 | U12: cm | V12: =P12/(PI()*T12^2) -> 5.5692824 | W12: GW/cm² | Y12: =V12/10*1000 -> 556.92824 | Z12: kJ/cm² | AA12: =V12/5*1000 -> 1113.8565 | AO12: =0.305*$L$6*AZ12/($C$5) -> 0.002928 | AP12: m | AQ12: =P12/(PI()*AO12^2) -> 222771.3 | AR12: GW/m² | AS12: =P12/(AO12^2) -> 699856.67 | AT12: GW/m² | AZ12: =F12*10^-9 -> 1.6e-06 | BA12: =V12*1000*1000*100 -> 5.5692824e+08
C13: nIR 3 | F13: 1200 | G13: nm | J13: 1 | K13: t | L13: =J13*$C$7 -> 20 | M13: MW | N13: 20 | O13: % | P13: =L13*N13/100 -> 4 | Q13: GW | R13: =L13-P13 -> 16 | T13: =100*1.22*AZ13*$L$6 / ($C$5*2) -> 0.4392 | U13: cm | V13: =P13/(PI()*T13^2) -> 6.600631 | W13: GW/cm² | Y13: =V13/10*1000 -> 660.0631 | Z13: kJ/cm² | AA13: =V13/5*1000 -> 1320.1262 | AO13: =0.305*$L$6*AZ13/($C$5) -> 0.002196 | AP13: m | AQ13: =P13/(PI()*AO13^2) -> 264025.24 | AR13: GW/m² | AS13: =P13/(AO13^2) -> 829459.76 | AT13: GW/m² | AZ13: =F13*10^-9 -> 1.2e-06 | BA13: =V13*1000*1000 -> 6600631 | BB13: W/cm²
A14: =1/20000000 -> 5e-08 | B14: 0.1 | C14: nIR 4 | F14: 1064 | G14: nm | J14: 10 | K14: t | L14: =J14*$C$7 -> 200 | M14: MW | N14: 70 | O14: % | P14: =L14*N14/100 -> 140 | Q14: MW | R14: =L14-P14 -> 60 | S14: MW | T14: =100*1.22*AZ14*$L$6 / ($C$5*2) -> 0.389424 | U14: cm | V14: =P14/(PI()*T14^2)*10^3 -> 293854.76 | W14: kW/cm² | Y14: =V14/10 -> 29385.476 | Z14: kJ/cm² | AA14: =V14/100 -> 2938.5476 | AB14: kJ/cm² | AC14: =P14*10^3 -> 140000 | AD14: kJ | AE14: =70/AF14 -> 146.92738 | AF14: =PI()*T14^2 -> 0.47642583 | AG14: cm² | AI14: =P14*10^6 -> 140000000 | AJ14: W | AZ14: =F14*10^-9 -> 1.064e-06
C15: nIR 5 | F15: 800 | G15: nm | J15: 1 | K15: t | L15: =J15*$C$7 -> 20 | M15: MW | N15: 10 | O15: % | P15: =L15*N15/100 -> 2 | Q15: GW | R15: =L15-P15 -> 18 | T15: =0.5*100*1.22*AZ15*$L$6 / ($C$5*2) -> 0.1464 | U15: cm | V15: =P15/(PI()*T15^2) -> 29.70284 | W15: GW/cm² | Y15: =V15/10*1000 -> 2970.284 | Z15: kJ/cm² | AA15: =V15/5*1000 -> 5940.5679 | AZ15: =F15*10^-9 -> 8e-07
C16: orange | F16: 600 | G16: nm | J16: 1 | K16: t | L16: =J16*$C$7 -> 20 | M16: MW | N16: 7 | O16: % | P16: =L16*N16/100 -> 1.4 | Q16: GW | R16: =L16-P16 -> 18.6 | T16: =0.5*100*1.22*AZ16*$L$6 / ($C$5*2) -> 0.1098 | U16: cm | V16: =P16/(PI()*T16^2) -> 36.963534 | W16: GW/cm² | Y16: =V16/10*1000 -> 3696.3534 | Z16: kJ/cm² | AA16: =V16/5*1000 -> 7392.7067 | AZ16: =F16*10^-9 -> 6e-07
A17: 0.01 | B17: 0.02 | C17: green | F17: 532 | G17: nm | N17: 20 | T17: =100*1.22*AZ17*$L$6 / ($C$5*2) -> 0.194712 | AZ17: =F17*10^-9 -> 5.32e-07
C18: indigo | F18: 400 | G18: nm | J18: 1 | K18: t | L18: =J18*$C$7 -> 20 | M18: MW | N18: 3 | O18: % | P18: =L18*N18/100 -> 0.6 | Q18: GW | R18: =L18-P18 -> 19.4 | T18: =0.5*100*1.22*AZ18*$L$6 / ($C$5*2) -> 0.0732 | U18: cm | V18: =P18/(PI()*T18^2) -> 35.643407 | W18: GW/cm² | Y18: =V18/10*1000 -> 3564.3407 | Z18: kJ/cm² | AA18: =V18/5*1000 -> 7128.6815 | AZ18: =F18*10^-9 -> 4e-07
C19: UV | F19: 200 | G19: nm | J19: 1 | K19: t | L19: =J19*$C$7 -> 20 | M19: MW | N19: 10 | O19: % | P19: =L19*N19/100 -> 2 | Q19: GW | R19: =L19-P19 -> 18 | S19: MW | T19: =0.5*100*1.22*AZ19*$L$6 / ($C$5*2) -> 0.0366 | U19: cm | V19: =P19/(PI()*T19^2) -> 475.24543 | W19: GW/cm² | Y19: =V19/10*1000 -> 47524.543 | Z19: MJ/cm² | AA19: =V19/5*1000 -> 95049.087 | AE19: =Y19*1000 -> 47524543 | AF19: kJ/cm² | AZ19: =F19*10^-9 -> 2e-07
C21: m | D21: 0.1 | E21: 0.3 | F21: 1 | G21: 3 | I21: 9 | J21: 27 | K21: 100 | L21: 300 | M21: 1000 | N21: 2000 | O21: 10000 | P21: 20000 | Q21: 40000 | R21: 60000
B22: IR 1ms | C22: Vacuum | D22: =0.01*$L$14*$N$14 / (PI()*(0.61*10^-7*$F$14*D$21 / ($C$5*2))^2) -> 105787715124848 | E22: =0.01*$L$14*$N$14 / (PI()*(0.61*10^-7*$F$14*E$21 / ($C$5*2))^2) -> 11754190569428 | F22: =0.01*$L$14*$N$14 / (PI()*(0.61*10^-7*$F$14*F$21 / ($C$5*2))^2) -> 1057877151248 | G22: =0.01*$L$14*$N$14 / (PI()*(0.61*10^-7*$F$14*G$21 / ($C$5*2))^2) -> 117541905694 | I22: =0.01*$L$14*$N$14 / (PI()*(0.61*10^-7*$F$14*I$21 / ($C$5*2))^2) -> 13060211744 | J22: =0.01*$L$14*$N$14 / (PI()*(0.61*10^-7*$F$14*J$21 / ($C$5*2))^2) -> 1451134638 | K22: =0.01*$L$14*$N$14 / (PI()*(0.61*10^-7*$F$14*K$21 / ($C$5*2))^2) -> 1.0578772e+08 | L22: =0.01*$L$14*$N$14 / (PI()*(0.61*10^-7*$F$14*L$21 / ($C$5*2))^2) -> 11754191 | M22: =0.01*$L$14*$N$14 / (PI()*(0.61*10^-7*$F$14*M$21 / ($C$5*2))^2) -> 1057877.2 | N22: =0.01*$L$14*$N$14 / (PI()*(0.61*10^-7*$F$14*N$21 / ($C$5*2))^2) -> 264469.29 | O22: =0.01*$L$14*$N$14 / (PI()*(0.61*10^-7*$F$14*O$21 / ($C$5*2))^2) -> 10578.772 | P22: =0.01*$L$14*$N$14 / (PI()*(0.61*10^-7*$F$14*P$21 / ($C$5*2))^2) -> 2644.6929 | ... R22: =0.01*$L$14*$N$14 / (PI()*(0.61*10^-7*$F$14*R$21 / ($C$5*2))^2) -> 293.85476 | U22: intensity = AB / ( pi ( 0.305*10^-6 * CD / E )² )
B23: kJ/cm² | C23: atmo | D23: =D22*10^-($A$14*E$26*10^2) -> 105763359407424 | E23: =E22*10^-($A$14*F$26*10^2) -> 11748778810830 | F23: =F22*10^-($A$14*G$26*10^2) -> 1057146647937 | G23: =G22*10^-($A$14*H$26*10^2) -> 117433695439 | I23: =I22*10^-($A$14*J$26*10^2) -> 13030174090 | J23: =J22*10^-($A$14*K$26*10^2) -> 1446131242 | K23: =K22*10^-($A$14*L$26*10^2) -> 1.0530166e+08 | L23: =L22*10^-($A$14*M$26*10^2) -> 11686722 | M23: =M22*10^-($A$14*N$26*10^2) -> 1045767.7 | N23: =N22*10^-($A$14*O$26*10^2) -> 258449.23 | O23: =O22*10^-($A$14*P$26*10^2) -> 10219.632 | P23: =P22*10^-($A$14*Q$26*10^2) -> 2525.6621 | ... R23: =R22*10^-($A$14*S$26*10^2) -> 261.89833 | V23: A = input power MW | AZ23: =F23*10^-9 -> 1057.1466
C24: water | D24: =D22*10^-($B$17*E$26*10^2) -> 0 | E24: =E22*10^-($B$17*F$26*10^2) -> 0 | F24: =F22*10^-($B$17*G$26*10^2) -> 0 | G24: =G22*10^-($B$17*H$26*10^2) -> 0 | V24: B = efficiency | AB24: =50/100000 -> 0.0005
U25: 45574 | V25: C = wavelength (nm)
C26: km | D26: 1 | E26: 20 | F26: 40 | G26: 60 | H26: 80 | I26: 100 | J26: 200 | K26: 300 | L26: 400 | M26: 500 | N26: 1000 | O26: 2000 | P26: 3000 | Q26: 4000 | R26: 5000 | S26: 10000 | T26: 20000 | V26: D = distance (m)
B27: UV 100ms (MW) | C27: Vacuum | D27: =0.001*$L$19*$N$19 / (PI()*(0.61*10^-4*$F$19*D$26 / ($C$5*2))^2) -> 42772.089 | E27: =0.001*$L$19*$N$19 / (PI()*(0.61*10^-4*$F$19*E$26 / ($C$5*2))^2) -> 106.93022 | F27: =0.001*$L$19*$N$19 / (PI()*(0.61*10^-4*$F$19*F$26 / ($C$5*2))^2) -> 26.732556 | G27: =0.001*$L$19*$N$19 / (PI()*(0.61*10^-4*$F$19*G$26 / ($C$5*2))^2) -> 11.881136 | H27: =0.001*$L$19*$N$19 / (PI()*(0.61*10^-4*$F$19*H$26 / ($C$5*2))^2) -> 6.6831389 | I27: =0.001*$L$19*$N$19 / (PI()*(0.61*10^-4*$F$19*I$26 / ($C$5*2))^2) -> 4.2772089 | J27: =0.001*$L$19*$N$19 / (PI()*(0.61*10^-4*$F$19*J$26 / ($C$5*2))^2) -> 1.0693022 | K27: =0.001*$L$19*$N$19 / (PI()*(0.61*10^-4*$F$19*K$26 / ($C$5*2))^2) -> 0.47524543 | ... T27: =0.001*$L$19*$N$19 / (PI()*(0.61*10^-4*$F$19*T$26 / ($C$5*2))^2) -> 0.00010693022 | V27: E = lens radius
D28: intensity = 10^-7 AB / ( pi ( 0.305*10^-6 * CD / E )² ) | R28: μs | S28: J | T28: pulses | U28: Range | V28: hole | X28: drilled
D29: 10-7 AB = I (pi M)² | F29: sqrt (10-7 AB / I / pi) = M | I29: 0.1 | J29: 1 | K29: 10 | L29: 100 | M29: 1000 | N29: MW
B30: efficiency | D30: D = E sqrt (...) / ( 0.305 10-6 C ) | I30: =$C$5 * sqrt(10^-7*$L$14*$N$14 /I29 / PI()) / (0.305 * 10^-6 * $F$14) -> 1028.5316 | J30: =$C$5 * sqrt(10^-7*$L$14*$N$14 /J29 / PI()) / (0.305 * 10^-6 * $F$14) -> 325.25023 | K30: =$C$5 * sqrt(10^-7*$L$14*$N$14 /K29 / PI()) / (0.305 * 10^-6 * $F$14) -> 102.85316 | L30: =$C$5 * sqrt(10^-7*$L$14*$N$14 /L29 / PI()) / (0.305 * 10^-6 * $F$14) -> 32.525023 | M30: =$C$5 * sqrt(10^-7*$L$14*$N$14 /M29 / PI()) / (0.305 * 10^-6 * $F$14) -> 10.285316 | N30: km | R30: 100 | S30: 1 | T30: 10 | U30: 1 | V30: 0.003 | W30: mm | X30: 1000 | Y30: cm | Z30: CNT
A31: standard | B31: best | C31: theoretical | S31: 1 | T31: 10 | U31: 5 | V31: 0.016 | W31: mm | X31: 30 | Y31: cm | Z31: CNT
A32: 20 | B32: 40 | C32: 60 | M32: intens = (5000*input*lens²) / (distance²) | S32: 1 | T32: 10 | U32: 20 | V32: 0.065 | X32: 2 | Z32: CNT | AA32: =(5000*L19*C5^2)/(C6^2) -> 2777.7778 | AF32: 1 cm of | AG32: MJ/kg | AZ32: =F32*10^-9 -> 0
J33: 3 | K33: =2*J33^2 -> 18 | M33: distance = sqrt( (5000*input*lens²) ) | S33: 1 | T33: 10 | U33: 50 | V33: 0.16 | X33: 0.4 | Z33: CNT | AZ33: =F33*10^-9 -> 0
A34: UV | B34: Mirror radius | C34: 20 | F34: m | M34: =sqrt( 5000*C5^2*L19) -> 1581.1388 | S34: 1 | T34: 10 | U34: 100 | V34: 0.3 | X34: 0.1 | Z34: CNT | AC34: =Y19/AA11 -> 11.52 | AF34: CNT | AG34: =60*1.8 -> 108 | AH34: =AG34/AG$36 -> 7.2 | AZ34: =#REF!*10^-9 -> #REF!
B35: Slope | C35: 2 | F35: (2 to 15) | J35: 10 | K35: =J35^2*0.5 -> 50 | R35: 10 | S35: 0.1 | T35: 100 | U35: 20 | V35: 0.065 | X35: 2 | Y35: cm | Z35: CNT | AF35: Steel | AG35: 50 | AH35: =AG35/AG$36 -> 3.3333333
D36: Turret | AF36: Bone | AG36: 15 | AH36: 1
C37: =MIN(100000*D37*PI()*E37^2,D37)*10 -> 0.3 | D37: =D38/10 -> 0.03 | E37: =E39*10 -> 3 | X37: 0 | AF37: Tungsten | AG37: =1.9*4.4 -> 8.36 | AH37: =AG37/AG$36 -> 0.55733333
B38: 30km | C38: =MIN(100000*D38*PI()*E38^2,D38)*10 -> 3 | D38: =D39/10 -> 0.3 | E38: =E40*10 -> 1 | R38: 10 | S38: 0.1 | T38: 50 | U38: 20 | V38: 0.065 | X38: 1 | Y38: cm | Z38: CNT | AB38: =$X$40/X38 -> 6 | AC38: =AB38/3 -> 2 | AF38: flesh | AG38: 2 | AH38: =AG38/AG$36 -> 0.13333333
B39: 10km | C39: =MIN(100000*D39*PI()*E39^2,D39)*10 -> 30 | D39: =D40/10 -> 3 | E39: =E41*10 -> 0.3 | M39: 30 km/h = 100 m/s = 10 cm/ms | R39: 10 | S39: 0.1 | T39: 50 | U39: 20 | V39: 0.065 | X39: 2 | Y39: cm | Z39: Steel | AB39: =$X$40/X39 -> 3 | AC39: =AB39/3 -> 1 | AF39: cloth
C40: =MIN(100000*D40*PI()*E40^2,D40)*10 -> 300 | D40: =D41/10 -> 30 | E40: 0.1 | R40: 10 | S40: 0.1 | T40: 50 | U40: 20 | V40: 0.065 | X40: 6 | Y40: cm | Z40: Bone | AB40: =$X$40/X40 -> 1 | AC40: 0 | AF40: graphite | AG40: 120 | AH40: =AG40/AG$36 -> 8
C41: =MIN(100000*D41*PI()*E41^2,D41)*10 -> 3000 | D41: =D42/10 -> 300 | E41: 0.03 | F41: Cannon | I41: RIFLE | J41: max | L41: m | M41: hole r | O41: LxR | P41: CNT | Q41: max | S41: PISTOL | X41: 6.5 | Z41: Diamond | AB41: =$X$40/X41 -> 0.92307692
B42: 300m | C42: =MIN(100000*D42*PI()*E42^2,D42)*10 -> 30000 | D42: =P42*1000000 -> 3000 | E42: 0.01 | F42: =MIN(100000000*P42*PI()*H42^2,P42*1000)*10 -> 30 | G42: =H42*20000 -> 480 | H42: 0.024 | I42: =MIN(10000000*P42*PI()*M42^2,P42*100)*10 -> 3 | J42: =M42*20000 -> 1000 | L42: 300 | M42: 0.05 | O42: =MIN(100000*P42*PI()*V42^2,P42) -> 0.003 | P42: 0.003 | Q42: =V42*20000 -> 2000 | U42: 300 | V42: 0.1 | X42: 165 | Z42: flesh | AB42: =$X$40/X42 -> 0.036363636 | AC42: -1
C43: =MIN(100000*D43*PI()*E43^2,D43)*10 -> 333333.33 | D43: =P43*1000000 -> 33333.333 | E43: =E41/10 -> 0.003 | F43: =MIN(100000000*P43*PI()*H43^2,P43*1000)*10 -> 333.33333 | G43: =H43*20000 -> 120 | H43: 0.006 | I43: =MIN(10000000*P43*PI()*M43^2,P43*100)*10 -> 33.333333 | J43: =M43*20000 -> 300 | K43: 2.4 | L43: 100 | M43: 0.015 | O43: =MIN(100000*P43*PI()*V43^2,P43)*10 -> 0.33333333 | P43: =P44/9 -> 0.033333333 | Q43: =V43*20000 -> 600 | U43: 100 | V43: 0.03
C44: =MIN(100000*D44*PI()*E44^2,D44)*10 -> 942477.8 | D44: =P44*1000000 -> 300000 | E44: =E42/10 -> 0.001 | F44: =MIN(100000000*P44*PI()*H44^2,P44*1000)*10 -> 3000 | G44: =H44*20000 -> 40 | H44: 0.002 | I44: =MIN(10000000*P44*PI()*M44^2,P44*100)*10 -> 300 | J44: =M44*20000 -> 100 | L44: 30 | M44: 0.005 | O44: =MIN(100000*P44*PI()*V44^2,P44)*10 -> 3 | P44: =P45/9 -> 0.3 | Q44: =V44*20000 -> 200 | R44: 10 | S44: 0.1 | T44: 100 | U44: 30 | V44: 0.01 | W44: e1 | X44: 1 | Y44: CNT | Z44: 7 | AA44: bone | AB44: 1.7 | AC44: steel | AD44: 1 | AE44: graphite | AF44: 50 | AG44: flesh
C45: =MIN(100000*D45*PI()*E45^2,D45)*10 -> 763407.01 | D45: =P45*1000000 -> 2700000 | E45: =E43/10 -> 0.0003 | F45: =MIN(100000000*P45*PI()*H45^2,P45*1000)*10 -> 3053.6281 | G45: =H45*20000 -> 12 | H45: 0.0006 | I45: =MIN(10000000*P45*PI()*M45^2,P45*100)*10 -> 1908.5175 | J45: =M45*20000 -> 30 | L45: 9 | M45: 0.0015 | O45: =MIN(100000*P45*PI()*V45^2,P45)*10 -> 27 | P45: 2.7 | Q45: =V45*20000 -> 60 | T45: 100 | U45: 9 | V45: 0.003 | X45: 10 | Y45: CNT
C46: =MIN(100000*D46*PI()*E46^2,D46)*10 -> 753982.24 | D46: =P46*1000000 -> 24000000 | E46: =E44/10 -> 0.0001 | F46: =MIN(100000000*P46*PI()*H46^2,P46*1000)*10 -> 3015.9289 | G46: =H46*20000 -> 4 | H46: 0.0002 | I46: =MIN(10000000*P46*PI()*M46^2,P46*100)*10 -> 1884.9556 | J46: =M46*20000 -> 10 | L46: 3 | M46: 0.0005 | O46: =MIN(100000*P46*PI()*V46^2,P46)*10 -> 75.398224 | P46: 24 | Q46: =V46*20000 -> 20 | T46: 100 | U46: 3 | V46: 0.001 | X46: 100 | Y46: CNT
C47: =MIN(100000*D47*PI()*E47^2,D47)*10 -> 610725.61 | D47: =P47*1000000 -> 216000000 | E47: =E45/10 -> 3e-05 | F47: =MIN(100000000*P47*PI()*H47^2,P47*1000)*10 -> 2442.9024 | G47: =H47*20000 -> 1.2 | H47: 6e-05 | I47: =MIN(10000000*P47*PI()*M47^2,P47*100)*10 -> 1526.814 | J47: =M47*20000 -> 3 | L47: 1 | M47: 0.00015 | O47: =MIN(100000*P47*PI()*V47^2,P47)*10 -> 61.072561 | P47: =9*P46 -> 216 | Q47: =V47*20000 -> 6 | R47: 10 | S47: 0.1 | T47: 100 | U47: 1 | V47: 0.0003 | W47: e4 | X47: 1500 | Y47: CNT
O48: =MIN(100000*P48*PI()*V48^2,P48) -> 0.61072561 | P48: =P47*10 -> 2160 | Q48: =V48*20000 -> 0.6 | U48: 0.3 | V48: 3e-05
O49: =MIN(100000*P49*PI()*V49^2,P49) -> 0.67858401 | P49: =P48*10 -> 21600 | Q49: =V49*20000 -> 0.2 | U49: 0.1 | V49: 1e-05 | Z49: graphite
S50: 10 | T50: 50 | U50: 20 | V50: 0.065 | X50: 80 | Y50: cm | Z50: CNT
X51: 260 | Y51: cm
C52: Power | F52: 20 | K52: Pulse power (MW/cm²) | T52: range = 40-100 * lens radius * power | AB52: heat res | AE52: =($AE$4 * $C$35) -> 1 | AQ52: power/radius² = 5.1 | AT52: power at 50km
C53: Radius | F53: 50 | H53: 100 | J53: 200 | K53: 300 | L53: 400 | M53: 500 | N53: 600 | O53: 700 | P53: 800 | Q53: 900 | R53: 1000 | T53: Max | U53: Min | W53: /succes | AB53: power needed to vaporize
C54: 1 | F54: =$F$52*$N$19 / (PI()*(0.61*$F$19*F$53*10^-4 / ($C54*2))^2) -> 684.35342 | H54: =$F$52*$N$19 / (PI()*(0.61*$F$19*H$53*10^-4 / ($C54*2))^2) -> 171.08836 | J54: =$F$52*$N$19 / (PI()*(0.61*$F$19*J$53*10^-4 / ($C54*2))^2) -> 42.772089 | K54: =$F$52*$N$19 / (PI()*(0.61*$F$19*K$53*10^-4 / ($C54*2))^2) -> 19.009817 | L54: =$F$52*$N$19 / (PI()*(0.61*$F$19*L$53*10^-4 / ($C54*2))^2) -> 10.693022 | M54: =$F$52*$N$19 / (PI()*(0.61*$F$19*M$53*10^-4 / ($C54*2))^2) -> 6.8435342 | N54: =$F$52*$N$19 / (PI()*(0.61*$F$19*N$53*10^-4 / ($C54*2))^2) -> 4.7524543 | O54: =$F$52*$N$19 / (PI()*(0.61*$F$19*O$53*10^-4 / ($C54*2))^2) -> 3.4915991 | P54: =$F$52*$N$19 / (PI()*(0.61*$F$19*P$53*10^-4 / ($C54*2))^2) -> 2.6732556 | Q54: =$F$52*$N$19 / (PI()*(0.61*$F$19*Q$53*10^-4 / ($C54*2))^2) -> 2.1122019 | R54: =$F$52*$N$19 / (PI()*(0.61*$F$19*R$53*10^-4 / ($C54*2))^2) -> 1.7108836 | T54: =50*C54*$F$52 -> 1000 | U54: =20*C54*$F$72 -> 2000 | V54: + | W54: =(T54-U54)/12 -> -83.333333 | Y54: =T54*1.5 -> 1500 | AA54: 50 | AB54: 100 | AE54: 200 | AF54: 300 | AG54: 400 | AH54: 500 | AI54: 600 | AJ54: 700 | AK54: 800 | AL54: 900 | AM54: 1000 | AP54: =F54/C54^2 -> 684.35342 | AQ54: =F54/C54^2 -> 684.35342 | AS54: =AQ54*C54^2 -> 684.35342 | AT54: =5*C54^2 -> 5
C55: 2 | F55: =$F$52*$N$19 / (PI()*(0.61*$F$19*F$53*10^-4 / ($C55*2))^2) -> 2737.4137 | H55: =$F$52*$N$19 / (PI()*(0.61*$F$19*H$53*10^-4 / ($C55*2))^2) -> 684.35342 | J55: =$F$52*$N$19 / (PI()*(0.61*$F$19*J$53*10^-4 / ($C55*2))^2) -> 171.08836 | K55: =$F$52*$N$19 / (PI()*(0.61*$F$19*K$53*10^-4 / ($C55*2))^2) -> 76.039269 | L55: =$F$52*$N$19 / (PI()*(0.61*$F$19*L$53*10^-4 / ($C55*2))^2) -> 42.772089 | M55: =$F$52*$N$19 / (PI()*(0.61*$F$19*M$53*10^-4 / ($C55*2))^2) -> 27.374137 | N55: =$F$52*$N$19 / (PI()*(0.61*$F$19*N$53*10^-4 / ($C55*2))^2) -> 19.009817 | O55: =$F$52*$N$19 / (PI()*(0.61*$F$19*O$53*10^-4 / ($C55*2))^2) -> 13.966396 | P55: =$F$52*$N$19 / (PI()*(0.61*$F$19*P$53*10^-4 / ($C55*2))^2) -> 10.693022 | Q55: =$F$52*$N$19 / (PI()*(0.61*$F$19*Q$53*10^-4 / ($C55*2))^2) -> 8.4488077 | R55: =$F$52*$N$19 / (PI()*(0.61*$F$19*R$53*10^-4 / ($C55*2))^2) -> 6.8435342 | T55: =50*C55*$F$52 -> 2000 | U55: =20*C55*$F$72 -> 4000 | V55: + | W55: =(T55-U55)/12 -> -166.66667 | Y55: =T55*1.5 -> 3000 | AA55: =$AE$52/AT54 -> 0.2 | AB55: =$AA55*1/V$39 -> 3.0769231 | AE55: =$AA55*1/X$39 -> 0.1 | AF55: =$AA55*1/Y$39 -> #VALUE! | AG55: =$AA55*1/Z$39 -> #VALUE! | AH55: =$AA55*1/AA$40 -> #DIV/0! | AI55: =$AA55*1/AB$40 -> 0.2 | AJ55: =$AA55*1/AC$39 -> 0.2 | AK55: =$AA55*1/AD$40 -> #DIV/0! | AL55: =$AA55*1/AE$40 -> #DIV/0! | AM55: =$AA55*1/AF$40 -> #VALUE! | AP55: =F55/C55 -> 1368.7068 | AQ55: =F55/C55^2 -> 684.35342 | AS55: =AQ55*C55^2 -> 2737.4137 | AT55: =5*C55^2 -> 20
C56: 3 | F56: =$F$52*$N$19 / (PI()*(0.61*$F$19*F$53*10^-4 / ($C56*2))^2) -> 6159.1808 | H56: =$F$52*$N$19 / (PI()*(0.61*$F$19*H$53*10^-4 / ($C56*2))^2) -> 1539.7952 | J56: =$F$52*$N$19 / (PI()*(0.61*$F$19*J$53*10^-4 / ($C56*2))^2) -> 384.9488 | K56: =$F$52*$N$19 / (PI()*(0.61*$F$19*K$53*10^-4 / ($C56*2))^2) -> 171.08836 | L56: =$F$52*$N$19 / (PI()*(0.61*$F$19*L$53*10^-4 / ($C56*2))^2) -> 96.2372 | M56: =$F$52*$N$19 / (PI()*(0.61*$F$19*M$53*10^-4 / ($C56*2))^2) -> 61.591808 | N56: =$F$52*$N$19 / (PI()*(0.61*$F$19*N$53*10^-4 / ($C56*2))^2) -> 42.772089 | O56: =$F$52*$N$19 / (PI()*(0.61*$F$19*O$53*10^-4 / ($C56*2))^2) -> 31.424392 | P56: =$F$52*$N$19 / (PI()*(0.61*$F$19*P$53*10^-4 / ($C56*2))^2) -> 24.0593 | Q56: =$F$52*$N$19 / (PI()*(0.61*$F$19*Q$53*10^-4 / ($C56*2))^2) -> 19.009817 | R56: =$F$52*$N$19 / (PI()*(0.61*$F$19*R$53*10^-4 / ($C56*2))^2) -> 15.397952 | T56: =50*C56*$F$52 -> 3000 | U56: =20*C56*$F$72 -> 6000 | V56: + | W56: =(T56-U56)/12 -> -250 | Y56: =T56*1.5 -> 4500 | AA56: =$AE$52/AT55 -> 0.05 | AB56: =$AA56*1/V$39 -> 0.76923077 | AE56: =$AA56*1/X$39 -> 0.025 | AF56: =$AA56*1/Y$39 -> #VALUE! | AG56: =$AA56*1/Z$39 -> #VALUE! | AH56: =$AA56*1/AA$40 -> #DIV/0! | AI56: =$AA56*1/AB$40 -> 0.05 | AJ56: =$AA56*1/AC$39 -> 0.05 | AK56: =$AA56*1/AD$40 -> #DIV/0! | AL56: =$AA56*1/AE$40 -> #DIV/0! | AM56: =$AA56*1/AF$40 -> #VALUE! | AP56: =F56/C56 -> 2053.0603 | AQ56: =F56/C56^2 -> 684.35342 | AS56: =AQ56*C56^2 -> 6159.1808 | AT56: =5*C56^2 -> 45
C57: 4 | F57: =$F$52*$N$19 / (PI()*(0.61*$F$19*F$53*10^-4 / ($C57*2))^2) -> 10949.655 | H57: =$F$52*$N$19 / (PI()*(0.61*$F$19*H$53*10^-4 / ($C57*2))^2) -> 2737.4137 | J57: =$F$52*$N$19 / (PI()*(0.61*$F$19*J$53*10^-4 / ($C57*2))^2) -> 684.35342 | K57: =$F$52*$N$19 / (PI()*(0.61*$F$19*K$53*10^-4 / ($C57*2))^2) -> 304.15708 | L57: =$F$52*$N$19 / (PI()*(0.61*$F$19*L$53*10^-4 / ($C57*2))^2) -> 171.08836 | M57: =$F$52*$N$19 / (PI()*(0.61*$F$19*M$53*10^-4 / ($C57*2))^2) -> 109.49655 | N57: =$F$52*$N$19 / (PI()*(0.61*$F$19*N$53*10^-4 / ($C57*2))^2) -> 76.039269 | O57: =$F$52*$N$19 / (PI()*(0.61*$F$19*O$53*10^-4 / ($C57*2))^2) -> 55.865586 | P57: =$F$52*$N$19 / (PI()*(0.61*$F$19*P$53*10^-4 / ($C57*2))^2) -> 42.772089 | Q57: =$F$52*$N$19 / (PI()*(0.61*$F$19*Q$53*10^-4 / ($C57*2))^2) -> 33.795231 | R57: =$F$52*$N$19 / (PI()*(0.61*$F$19*R$53*10^-4 / ($C57*2))^2) -> 27.374137 | T57: =50*C57*$F$52 -> 4000 | U57: =20*C57*$F$72 -> 8000 | V57: + | W57: =(T57-U57)/12 -> -333.33333 | Y57: =T57*1.5 -> 6000 | AA57: =$AE$52/AT56 -> 0.022222222 | AB57: =$AA57*1/V$39 -> 0.34188034 | AE57: =$AA57*1/X$39 -> 0.011111111 | AF57: =$AA57*1/Y$39 -> #VALUE! | AG57: =$AA57*1/Z$39 -> #VALUE! | AH57: =$AA57*1/AA$40 -> #DIV/0! | AI57: =$AA57*1/AB$40 -> 0.022222222 | AJ57: =$AA57*1/AC$39 -> 0.022222222 | AK57: =$AA57*1/AD$40 -> #DIV/0! | AL57: =$AA57*1/AE$40 -> #DIV/0! | AM57: =$AA57*1/AF$40 -> #VALUE! | AP57: =F57/C57 -> 2737.4137 | AQ57: =F57/C57^2 -> 684.35342 | AS57: =AQ57*C57^2 -> 10949.655 | AT57: =5*C57^2 -> 80
C58: 5 | F58: =$F$52*$N$19 / (PI()*(0.61*$F$19*F$53*10^-4 / ($C58*2))^2) -> 17108.836 | H58: =$F$52*$N$19 / (PI()*(0.61*$F$19*H$53*10^-4 / ($C58*2))^2) -> 4277.2089 | J58: =$F$52*$N$19 / (PI()*(0.61*$F$19*J$53*10^-4 / ($C58*2))^2) -> 1069.3022 | K58: =$F$52*$N$19 / (PI()*(0.61*$F$19*K$53*10^-4 / ($C58*2))^2) -> 475.24543 | L58: =$F$52*$N$19 / (PI()*(0.61*$F$19*L$53*10^-4 / ($C58*2))^2) -> 267.32556 | M58: =$F$52*$N$19 / (PI()*(0.61*$F$19*M$53*10^-4 / ($C58*2))^2) -> 171.08836 | N58: =$F$52*$N$19 / (PI()*(0.61*$F$19*N$53*10^-4 / ($C58*2))^2) -> 118.81136 | O58: =$F$52*$N$19 / (PI()*(0.61*$F$19*O$53*10^-4 / ($C58*2))^2) -> 87.289978 | P58: =$F$52*$N$19 / (PI()*(0.61*$F$19*P$53*10^-4 / ($C58*2))^2) -> 66.831389 | Q58: =$F$52*$N$19 / (PI()*(0.61*$F$19*Q$53*10^-4 / ($C58*2))^2) -> 52.805048 | R58: =$F$52*$N$19 / (PI()*(0.61*$F$19*R$53*10^-4 / ($C58*2))^2) -> 42.772089 | T58: =50*C58*$F$52 -> 5000 | U58: =20*C58*$F$72 -> 10000 | V58: + | W58: =(T58-U58)/12 -> -416.66667 | Y58: =T58*1.5 -> 7500 | AA58: =$AE$52/AT57 -> 0.0125 | AB58: =$AA58*1/V$39 -> 0.19230769 | AE58: =$AA58*1/X$39 -> 0.00625 | AF58: =$AA58*1/Y$39 -> #VALUE! | AG58: =$AA58*1/Z$39 -> #VALUE! | AH58: =$AA58*1/AA$40 -> #DIV/0! | AI58: =$AA58*1/AB$40 -> 0.0125 | AJ58: =$AA58*1/AC$39 -> 0.0125 | AK58: =$AA58*1/AD$40 -> #DIV/0! | AL58: =$AA58*1/AE$40 -> #DIV/0! | AM58: =$AA58*1/AF$40 -> #VALUE! | AP58: =F58/C58 -> 3421.7671 | AQ58: =F58/C58^2 -> 684.35342 | AS58: =AQ58*C58^2 -> 17108.836 | AT58: =5*C58^2 -> 125
C59: 10 | F59: =$F$52*$N$19 / (PI()*(0.61*$F$19*F$53*10^-4 / ($C59*2))^2) -> 68435.342 | H59: =$F$52*$N$19 / (PI()*(0.61*$F$19*H$53*10^-4 / ($C59*2))^2) -> 17108.836 | J59: =$F$52*$N$19 / (PI()*(0.61*$F$19*J$53*10^-4 / ($C59*2))^2) -> 4277.2089 | K59: =$F$52*$N$19 / (PI()*(0.61*$F$19*K$53*10^-4 / ($C59*2))^2) -> 1900.9817 | L59: =$F$52*$N$19 / (PI()*(0.61*$F$19*L$53*10^-4 / ($C59*2))^2) -> 1069.3022 | M59: =$F$52*$N$19 / (PI()*(0.61*$F$19*M$53*10^-4 / ($C59*2))^2) -> 684.35342 | N59: =$F$52*$N$19 / (PI()*(0.61*$F$19*N$53*10^-4 / ($C59*2))^2) -> 475.24543 | O59: =$F$52*$N$19 / (PI()*(0.61*$F$19*O$53*10^-4 / ($C59*2))^2) -> 349.15991 | P59: =$F$52*$N$19 / (PI()*(0.61*$F$19*P$53*10^-4 / ($C59*2))^2) -> 267.32556 | Q59: =$F$52*$N$19 / (PI()*(0.61*$F$19*Q$53*10^-4 / ($C59*2))^2) -> 211.22019 | R59: =$F$52*$N$19 / (PI()*(0.61*$F$19*R$53*10^-4 / ($C59*2))^2) -> 171.08836 | T59: =50*C59*$F$52 -> 10000 | U59: =20*C59*$F$72 -> 20000 | V59: + | W59: =(T59-U59)/12 -> -833.33333 | Y59: =T59*1.5 -> 15000 | AA59: =$AE$52/AT58 -> 0.008 | AB59: =$AA59*1/V$39 -> 0.12307692 | AE59: =$AA59*1/X$39 -> 0.004 | AF59: =$AA59*1/Y$39 -> #VALUE! | AG59: =$AA59*1/Z$39 -> #VALUE! | AH59: =$AA59*1/AA$40 -> #DIV/0! | AI59: =$AA59*1/AB$40 -> 0.008 | AJ59: =$AA59*1/AC$39 -> 0.008 | AK59: =$AA59*1/AD$40 -> #DIV/0! | AL59: =$AA59*1/AE$40 -> #DIV/0! | AM59: =$AA59*1/AF$40 -> #VALUE! | AP59: =F59/C59 -> 6843.5342 | AQ59: =F59/C59^2 -> 684.35342 | AS59: =AQ59*C59^2 -> 68435.342 | AT59: =5*C59^2 -> 500
C60: 25 | F60: =$F$52*$N$19 / (PI()*(0.61*$F$19*F$53*10^-4 / ($C60*2))^2) -> 427720.89 | H60: =$F$52*$N$19 / (PI()*(0.61*$F$19*H$53*10^-4 / ($C60*2))^2) -> 106930.22 | J60: =$F$52*$N$19 / (PI()*(0.61*$F$19*J$53*10^-4 / ($C60*2))^2) -> 26732.556 | K60: =$F$52*$N$19 / (PI()*(0.61*$F$19*K$53*10^-4 / ($C60*2))^2) -> 11881.136 | L60: =$F$52*$N$19 / (PI()*(0.61*$F$19*L$53*10^-4 / ($C60*2))^2) -> 6683.1389 | M60: =$F$52*$N$19 / (PI()*(0.61*$F$19*M$53*10^-4 / ($C60*2))^2) -> 4277.2089 | N60: =$F$52*$N$19 / (PI()*(0.61*$F$19*N$53*10^-4 / ($C60*2))^2) -> 2970.284 | O60: =$F$52*$N$19 / (PI()*(0.61*$F$19*O$53*10^-4 / ($C60*2))^2) -> 2182.2494 | P60: =$F$52*$N$19 / (PI()*(0.61*$F$19*P$53*10^-4 / ($C60*2))^2) -> 1670.7847 | Q60: =$F$52*$N$19 / (PI()*(0.61*$F$19*Q$53*10^-4 / ($C60*2))^2) -> 1320.1262 | R60: =$F$52*$N$19 / (PI()*(0.61*$F$19*R$53*10^-4 / ($C60*2))^2) -> 1069.3022 | T60: =50*C60*$F$52 -> 25000 | U60: =20*C60*$F$72 -> 50000 | V60: + | W60: =(T60-U60)/12 -> -2083.3333 | Y60: =T60*1.5 -> 37500 | AA60: =$AE$52/AT59 -> 0.002 | AB60: =$AA60*1/V$39 -> 0.030769231 | AE60: =$AA60*1/X$39 -> 0.001 | AF60: =$AA60*1/Y$39 -> #VALUE! | AG60: =$AA60*1/Z$39 -> #VALUE! | AH60: =$AA60*1/AA$40 -> #DIV/0! | AI60: =$AA60*1/AB$40 -> 0.002 | AJ60: =$AA60*1/AC$39 -> 0.002 | AK60: =$AA60*1/AD$40 -> #DIV/0! | AL60: =$AA60*1/AE$40 -> #DIV/0! | AM60: =$AA60*1/AF$40 -> #VALUE! | AP60: =F60/C60 -> 17108.836 | AQ60: =F60/C60^2 -> 684.35342 | AS60: =AQ60*C60^2 -> 427720.89 | AT60: =5*C60^2 -> 3125
C61: 50 | F61: =$F$52*$N$19 / (PI()*(0.61*$F$19*F$53*10^-4 / ($C61*2))^2) -> 1710883.6 | H61: =$F$52*$N$19 / (PI()*(0.61*$F$19*H$53*10^-4 / ($C61*2))^2) -> 427720.89 | J61: =$F$52*$N$19 / (PI()*(0.61*$F$19*J$53*10^-4 / ($C61*2))^2) -> 106930.22 | K61: =$F$52*$N$19 / (PI()*(0.61*$F$19*K$53*10^-4 / ($C61*2))^2) -> 47524.543 | L61: =$F$52*$N$19 / (PI()*(0.61*$F$19*L$53*10^-4 / ($C61*2))^2) -> 26732.556 | M61: =$F$52*$N$19 / (PI()*(0.61*$F$19*M$53*10^-4 / ($C61*2))^2) -> 17108.836 | N61: =$F$52*$N$19 / (PI()*(0.61*$F$19*N$53*10^-4 / ($C61*2))^2) -> 11881.136 | O61: =$F$52*$N$19 / (PI()*(0.61*$F$19*O$53*10^-4 / ($C61*2))^2) -> 8728.9978 | P61: =$F$52*$N$19 / (PI()*(0.61*$F$19*P$53*10^-4 / ($C61*2))^2) -> 6683.1389 | Q61: =$F$52*$N$19 / (PI()*(0.61*$F$19*Q$53*10^-4 / ($C61*2))^2) -> 5280.5048 | R61: =$F$52*$N$19 / (PI()*(0.61*$F$19*R$53*10^-4 / ($C61*2))^2) -> 4277.2089 | T61: =50*C61*$F$52 -> 50000 | U61: =20*C61*$F$72 -> 100000 | V61: + | W61: =(T61-U61)/12 -> -4166.6667 | Y61: =T61*1.5 -> 75000 | AA61: =$AE$52/AT60 -> 0.00032 | AB61: =$AA61*1/V$39 -> 0.0049230769 | AE61: =$AA61*1/X$39 -> 0.00016 | AF61: =$AA61*1/Y$39 -> #VALUE! | AG61: =$AA61*1/Z$39 -> #VALUE! | AH61: =$AA61*1/AA$40 -> #DIV/0! | AI61: =$AA61*1/AB$40 -> 0.00032 | AJ61: =$AA61*1/AC$39 -> 0.00032 | AK61: =$AA61*1/AD$40 -> #DIV/0! | AL61: =$AA61*1/AE$40 -> #DIV/0! | AM61: =$AA61*1/AF$40 -> #VALUE! | AP61: =F61/C61 -> 34217.671 | AQ61: =F61/C61^2 -> 684.35342 | AS61: =AQ61*C61^2 -> 1710883.6 | AT61: =5*C61^2 -> 12500
C62: 100 | F62: =$F$52*$N$19 / (PI()*(0.61*$F$19*F$53*10^-4 / ($C62*2))^2) -> 6843534.2 | H62: =$F$52*$N$19 / (PI()*(0.61*$F$19*H$53*10^-4 / ($C62*2))^2) -> 1710883.6 | J62: =$F$52*$N$19 / (PI()*(0.61*$F$19*J$53*10^-4 / ($C62*2))^2) -> 427720.89 | K62: =$F$52*$N$19 / (PI()*(0.61*$F$19*K$53*10^-4 / ($C62*2))^2) -> 190098.17 | L62: =$F$52*$N$19 / (PI()*(0.61*$F$19*L$53*10^-4 / ($C62*2))^2) -> 106930.22 | M62: =$F$52*$N$19 / (PI()*(0.61*$F$19*M$53*10^-4 / ($C62*2))^2) -> 68435.342 | N62: =$F$52*$N$19 / (PI()*(0.61*$F$19*N$53*10^-4 / ($C62*2))^2) -> 47524.543 | O62: =$F$52*$N$19 / (PI()*(0.61*$F$19*O$53*10^-4 / ($C62*2))^2) -> 34915.991 | P62: =$F$52*$N$19 / (PI()*(0.61*$F$19*P$53*10^-4 / ($C62*2))^2) -> 26732.556 | Q62: =$F$52*$N$19 / (PI()*(0.61*$F$19*Q$53*10^-4 / ($C62*2))^2) -> 21122.019 | R62: =$F$52*$N$19 / (PI()*(0.61*$F$19*R$53*10^-4 / ($C62*2))^2) -> 17108.836 | T62: =50*C62*$F$52 -> 100000 | U62: =20*C62*$F$72 -> 200000 | V62: + | W62: =(T62-U62)/12 -> -8333.3333 | Y62: =T62*1.5 -> 150000 | AA62: =$AE$52/AT61 -> 8e-05 | AB62: =$AA62*1/V$39 -> 0.0012307692 | AE62: =$AA62*1/X$39 -> 4e-05 | AF62: =$AA62*1/Y$39 -> #VALUE! | AG62: =$AA62*1/Z$39 -> #VALUE! | AH62: =$AA62*1/AA$40 -> #DIV/0! | AI62: =$AA62*1/AB$40 -> 8e-05 | AJ62: =$AA62*1/AC$39 -> 8e-05 | AK62: =$AA62*1/AD$40 -> #DIV/0! | AL62: =$AA62*1/AE$40 -> #DIV/0! | AM62: =$AA62*1/AF$40 -> #VALUE! | AP62: =F62/C62 -> 68435.342 | AQ62: =F62/C62^2 -> 684.35342 | AS62: =AQ62*C62^2 -> 6843534.2 | AT62: =5*C62^2 -> 50000
C63: 500 | F63: =$F$52*$N$19 / (PI()*(0.61*$F$19*F$53*10^-4 / ($C63*2))^2) -> 1.7108836e+08 | H63: =$F$52*$N$19 / (PI()*(0.61*$F$19*H$53*10^-4 / ($C63*2))^2) -> 42772089 | J63: =$F$52*$N$19 / (PI()*(0.61*$F$19*J$53*10^-4 / ($C63*2))^2) -> 10693022 | K63: =$F$52*$N$19 / (PI()*(0.61*$F$19*K$53*10^-4 / ($C63*2))^2) -> 4752454.3 | L63: =$F$52*$N$19 / (PI()*(0.61*$F$19*L$53*10^-4 / ($C63*2))^2) -> 2673255.6 | M63: =$F$52*$N$19 / (PI()*(0.61*$F$19*M$53*10^-4 / ($C63*2))^2) -> 1710883.6 | N63: =$F$52*$N$19 / (PI()*(0.61*$F$19*N$53*10^-4 / ($C63*2))^2) -> 1188113.6 | O63: =$F$52*$N$19 / (PI()*(0.61*$F$19*O$53*10^-4 / ($C63*2))^2) -> 872899.78 | P63: =$F$52*$N$19 / (PI()*(0.61*$F$19*P$53*10^-4 / ($C63*2))^2) -> 668313.89 | Q63: =$F$52*$N$19 / (PI()*(0.61*$F$19*Q$53*10^-4 / ($C63*2))^2) -> 528050.48 | R63: =$F$52*$N$19 / (PI()*(0.61*$F$19*R$53*10^-4 / ($C63*2))^2) -> 427720.89 | T63: =50*C63*$F$52 -> 500000 | U63: =20*C63*$F$72 -> 1000000 | V63: + | W63: =(T63-U63)/12 -> -41666.667 | Y63: =T63*1.5 -> 750000 | AA63: =$AE$52/AT62 -> 2e-05 | AB63: =$AA63*1/V$39 -> 0.00030769231 | AE63: =$AA63*1/X$39 -> 1e-05 | AF63: =$AA63*1/Y$39 -> #VALUE! | AG63: =$AA63*1/Z$39 -> #VALUE! | AH63: =$AA63*1/AA$40 -> #DIV/0! | AI63: =$AA63*1/AB$40 -> 2e-05 | AJ63: =$AA63*1/AC$39 -> 2e-05 | AK63: =$AA63*1/AD$40 -> #DIV/0! | AL63: =$AA63*1/AE$40 -> #DIV/0! | AM63: =$AA63*1/AF$40 -> #VALUE! | AP63: =F63/C63 -> 342176.71 | AQ63: =F63/C63^2 -> 684.35342 | AS63: =AQ63*C63^2 -> 1.7108836e+08 | AT63: =5*C63^2 -> 1250000
C64: 1000 | F64: =$F$52*$N$19 / (PI()*(0.61*$F$19*F$53*10^-4 / ($C64*2))^2) -> 6.8435342e+08 | H64: =$F$52*$N$19 / (PI()*(0.61*$F$19*H$53*10^-4 / ($C64*2))^2) -> 1.7108836e+08 | J64: =$F$52*$N$19 / (PI()*(0.61*$F$19*J$53*10^-4 / ($C64*2))^2) -> 42772089 | K64: =$F$52*$N$19 / (PI()*(0.61*$F$19*K$53*10^-4 / ($C64*2))^2) -> 19009817 | L64: =$F$52*$N$19 / (PI()*(0.61*$F$19*L$53*10^-4 / ($C64*2))^2) -> 10693022 | M64: =$F$52*$N$19 / (PI()*(0.61*$F$19*M$53*10^-4 / ($C64*2))^2) -> 6843534.2 | N64: =$F$52*$N$19 / (PI()*(0.61*$F$19*N$53*10^-4 / ($C64*2))^2) -> 4752454.3 | O64: =$F$52*$N$19 / (PI()*(0.61*$F$19*O$53*10^-4 / ($C64*2))^2) -> 3491599.1 | P64: =$F$52*$N$19 / (PI()*(0.61*$F$19*P$53*10^-4 / ($C64*2))^2) -> 2673255.6 | Q64: =$F$52*$N$19 / (PI()*(0.61*$F$19*Q$53*10^-4 / ($C64*2))^2) -> 2112201.9 | R64: =$F$52*$N$19 / (PI()*(0.61*$F$19*R$53*10^-4 / ($C64*2))^2) -> 1710883.6 | T64: =50*C64*$F$52 -> 1000000 | U64: =20*C64*$F$72 -> 2000000 | V64: + | W64: =(T64-U64)/12 -> -83333.333 | Y64: =T64*1.5 -> 1500000 | AA64: =$AE$52/AT63 -> 8e-07 | AB64: =$AA64*1/V$39 -> 1.2307692e-05 | AE64: =$AA64*1/X$39 -> 4e-07 | AF64: =$AA64*1/Y$39 -> #VALUE! | AG64: =$AA64*1/Z$39 -> #VALUE! | AH64: =$AA64*1/AA$40 -> #DIV/0! | AI64: =$AA64*1/AB$40 -> 8e-07 | AJ64: =$AA64*1/AC$39 -> 8e-07 | AK64: =$AA64*1/AD$40 -> #DIV/0! | AL64: =$AA64*1/AE$40 -> #DIV/0! | AM64: =$AA64*1/AF$40 -> #VALUE! | AP64: =F64/C64 -> 684353.42 | AQ64: =F64/C64^2 -> 684.35342 | AS64: =AQ64*C64^2 -> 6.8435342e+08 | AT64: =5*C64^2 -> 5000000
Y65: =Y64/150000 -> 10 | Z65: AU
A67: IR | C67: IR laser | F67: 80% efficiency | X67: =5000/#REF!^2 -> #REF! | Y67: =5000*$F$72/#REF!^2 -> #REF! | Z67: =5000/#REF!^2 -> #REF! | AA67: =5000/AA74^2 -> 2 | AB67: =5000/AB74^2 -> 0.5 | AC67: =5000/AC74^2 -> 0.22222222 | AD67: =5000/AD74^2 -> 0.125 | AE67: =5000/AE74^2 -> 0.055555556 | AF67: =5000/AF74^2 -> 0.03125 | AG67: =5000/AG74^2 -> 0.02
F68: less damage but longer pulses, vastly less waste heat, deposits heat on target | X68: =X$67*($C76^2) -> #REF! | Y68: =Y$67*($C76^2) -> #REF! | Z68: =Z$67*($C76^2) -> #REF! | AA68: pow = (5000*input*lens²) / (distance²)
F69: less weight because of small internal heat sink | P69: x = 2 AB / ( pi ( 0.305* 10^4 * CD / E )² ) | X69: =X$67*($C77^2) -> #REF! | Y69: =Y$67*($C77^2) -> #REF! | Z69: =Z$67*($C77^2) -> #REF! | AA69: (distance/10)² = power at 10 km / power at target
W70: =700/500 -> 1.4 | X70: =X$67*($C78^2) -> #REF! | Y70: =Y$67*($C78^2) -> #REF! | Z70: =Z$67*($C78^2) -> #REF! | AA70: distance = sqrt(ref/pow)*10
AA71: =SQRT(50/AA75) -> 86.961571 | AB71: =SQRT(50/AB75) -> 108.70196 | AC71: =SQRT(50/AC75) -> 217.40393 | AD71: =SQRT(50/AD75) -> 326.10589
C72: Power | F72: 100 | G72: MW
K73: Pulse power (MW/cm²) | Y73: =#REF!/F74 -> #REF! | AC73: Pulse power (MW/cm²) * heat cap (0.5) * slope
C74: Distance | D74: 1 | E74: 20 | F74: 40 | G74: 60 | H74: 80 | I74: 100 | J74: 200 | K74: 300 | L74: 400 | M74: 500 | N74: 1000 | O74: 1500 | P74: 2000 | Q74: 3000 | R74: 4000 | S74: 5000 | T74: Long | U74: Med | V74: Short | W74: /succes | AA74: 50 | AB74: 100 | AC74: 150 | AD74: 200 | AE74: 300 | AF74: 400 | AG74: 500 | AH74: 600 | AI74: 700 | AJ74: 800 | AK74: 900 | AL74: 1000
B75: Lens radius | C75: 1 | D75: =2*10^-9*$F$72*$N$14 / (PI()*(0.305*10^-7*$F$14*D$74 / ($C75))^2) -> 4231.5086 | E75: =2*10^-9*$F$72*$N$14 / (PI()*(0.305*10^-7*$F$14*E$74 / ($C75))^2) -> 10.578772 | F75: =2*10^-9*$F$72*$N$14 / (PI()*(0.305*10^-7*$F$14*F$74 / ($C75))^2) -> 2.6446929 | G75: =2*10^-9*$F$72*$N$14 / (PI()*(0.305*10^-7*$F$14*G$74 / ($C75))^2) -> 1.1754191 | H75: =2*10^-9*$F$72*$N$14 / (PI()*(0.305*10^-7*$F$14*H$74 / ($C75))^2) -> 0.66117322 | I75: =2*10^-9*$F$72*$N$14 / (PI()*(0.305*10^-7*$F$14*I$74 / ($C75))^2) -> 0.42315086 | J75: =2*10^-9*$F$72*$N$14 / (PI()*(0.305*10^-7*$F$14*J$74 / ($C75))^2) -> 0.10578772 | K75: =2*10^-9*$F$72*$N$14 / (PI()*(0.305*10^-7*$F$14*K$74 / ($C75))^2) -> 0.047016762 | ... S75: =2*10^-9*$F$72*$N$14 / (PI()*(0.305*10^-7*$F$14*S$74 / ($C75))^2) -> 0.00016926034 | T75: =($C75) / (0.0000000305 * $F$14) * SQRT( (0.000000002 * $F$72 * $N$14) / (0.1 * PI()) ) -> 205.70631 | U75: =($C75) / (0.0000000305 * $F$14) * SQRT( (0.000000002 * $F$72 * $N$14) / PI() ) -> 65.050047 | V75: =($C75) / (0.0000000305 * $F$14) * SQRT( (0.000000002 * $F$72 * $N$14) / (10 * PI()) ) -> 20.570631 | W75: =#REF!/10 -> #REF! | X75: =T75/20 -> 10.285316 | Y75: =U75/20 -> 3.2525023 | Z75: =V75/20 -> 1.0285316 | AA75: =H75/($F$72*$C75) -> 0.0066117322 | AB75: =I75/($F$72*$C75) -> 0.0042315086 | AC75: =J75/($F$72*$C75) -> 0.0010578772 | AD75: =K75/($F$72*$C75) -> 0.00047016762 | AE75: =L75/($F$72*$C75) -> 0.00026446929 | AF75: =M75/($F$72*$C75) -> 0.00016926034 | AG75: =N75/($F$72*$C75) -> 4.2315086e-05 | AH75: =O75/($F$72*$C75) -> 1.8806705e-05
C76: 2 | D76: =2*10^-9*$F$72*$N$14 / (PI()*(0.305*10^-7*$F$14*D$74 / ($C76))^2) -> 16926.034 | E76: =2*10^-9*$F$72*$N$14 / (PI()*(0.305*10^-7*$F$14*E$74 / ($C76))^2) -> 42.315086 | F76: =2*10^-9*$F$72*$N$14 / (PI()*(0.305*10^-7*$F$14*F$74 / ($C76))^2) -> 10.578772 | G76: =2*10^-9*$F$72*$N$14 / (PI()*(0.305*10^-7*$F$14*G$74 / ($C76))^2) -> 4.7016762 | H76: =2*10^-9*$F$72*$N$14 / (PI()*(0.305*10^-7*$F$14*H$74 / ($C76))^2) -> 2.6446929 | I76: =2*10^-9*$F$72*$N$14 / (PI()*(0.305*10^-7*$F$14*I$74 / ($C76))^2) -> 1.6926034 | J76: =2*10^-9*$F$72*$N$14 / (PI()*(0.305*10^-7*$F$14*J$74 / ($C76))^2) -> 0.42315086 | K76: =2*10^-9*$F$72*$N$14 / (PI()*(0.305*10^-7*$F$14*K$74 / ($C76))^2) -> 0.18806705 | ... S76: =2*10^-9*$F$72*$N$14 / (PI()*(0.305*10^-7*$F$14*S$74 / ($C76))^2) -> 0.00067704138 | T76: =($C76) / (0.0000000305 * $F$14) * SQRT( (0.000000002 * $F$72 * $N$14) / (0.1 * PI()) ) -> 411.41262 | U76: =($C76) / (0.0000000305 * $F$14) * SQRT( (0.000000002 * $F$72 * $N$14) / PI() ) -> 130.10009 | V76: =($C76) / (0.0000000305 * $F$14) * SQRT( (0.000000002 * $F$72 * $N$14) / (10 * PI()) ) -> 41.141262 | W76: =(T76-U76)/12 -> 23.442711 | X76: =T76/20 -> 20.570631 | Y76: =U76/20 -> 6.5050047 | Z76: =V76/20 -> 2.0570631 | AA76: =H76/($F$72*$C76) -> 0.013223464 | AB76: =I76/($F$72*$C76) -> 0.0084630172 | AC76: =J76/($F$72*$C76) -> 0.0021157543 | AD76: =K76/($F$72*$C76) -> 0.00094033525 | AE76: =L76/($F$72*$C76) -> 0.00052893858 | AF76: =M76/($F$72*$C76) -> 0.00033852069 | AG76: =N76/($F$72*$C76) -> 8.4630172e-05 | AH76: =O76/($F$72*$C76) -> 3.761341e-05
C77: 3 | D77: =2*10^-9*$F$72*$N$14 / (PI()*(0.305*10^-7*$F$14*D$74 / ($C77))^2) -> 38083.577 | E77: =2*10^-9*$F$72*$N$14 / (PI()*(0.305*10^-7*$F$14*E$74 / ($C77))^2) -> 95.208944 | F77: =2*10^-9*$F$72*$N$14 / (PI()*(0.305*10^-7*$F$14*F$74 / ($C77))^2) -> 23.802236 | G77: =2*10^-9*$F$72*$N$14 / (PI()*(0.305*10^-7*$F$14*G$74 / ($C77))^2) -> 10.578772 | H77: =2*10^-9*$F$72*$N$14 / (PI()*(0.305*10^-7*$F$14*H$74 / ($C77))^2) -> 5.950559 | I77: =2*10^-9*$F$72*$N$14 / (PI()*(0.305*10^-7*$F$14*I$74 / ($C77))^2) -> 3.8083577 | J77: =2*10^-9*$F$72*$N$14 / (PI()*(0.305*10^-7*$F$14*J$74 / ($C77))^2) -> 0.95208944 | K77: =2*10^-9*$F$72*$N$14 / (PI()*(0.305*10^-7*$F$14*K$74 / ($C77))^2) -> 0.42315086 | ... S77: =2*10^-9*$F$72*$N$14 / (PI()*(0.305*10^-7*$F$14*S$74 / ($C77))^2) -> 0.0015233431 | T77: =($C77) / (0.0000000305 * $F$14) * SQRT( (0.000000002 * $F$72 * $N$14) / (0.1 * PI()) ) -> 617.11893 | U77: =($C77) / (0.0000000305 * $F$14) * SQRT( (0.000000002 * $F$72 * $N$14) / PI() ) -> 195.15014 | V77: =($C77) / (0.0000000305 * $F$14) * SQRT( (0.000000002 * $F$72 * $N$14) / (10 * PI()) ) -> 61.711893 | W77: =(T77-U77)/12 -> 35.164066 | X77: =T77/20 -> 30.855947 | Y77: =U77/20 -> 9.757507 | Z77: =V77/20 -> 3.0855947 | AD77: =AB75/4 -> 0.0010578772 | AF77: =AD75/4 -> 0.00011754191 | AH77: =AF75/4 -> 4.2315086e-05
C78: 4 | D78: =2*10^-9*$F$72*$N$14 / (PI()*(0.305*10^-7*$F$14*D$74 / ($C78))^2) -> 67704.138 | E78: =2*10^-9*$F$72*$N$14 / (PI()*(0.305*10^-7*$F$14*E$74 / ($C78))^2) -> 169.26034 | F78: =2*10^-9*$F$72*$N$14 / (PI()*(0.305*10^-7*$F$14*F$74 / ($C78))^2) -> 42.315086 | G78: =2*10^-9*$F$72*$N$14 / (PI()*(0.305*10^-7*$F$14*G$74 / ($C78))^2) -> 18.806705 | H78: =2*10^-9*$F$72*$N$14 / (PI()*(0.305*10^-7*$F$14*H$74 / ($C78))^2) -> 10.578772 | I78: =2*10^-9*$F$72*$N$14 / (PI()*(0.305*10^-7*$F$14*I$74 / ($C78))^2) -> 6.7704138 | J78: =2*10^-9*$F$72*$N$14 / (PI()*(0.305*10^-7*$F$14*J$74 / ($C78))^2) -> 1.6926034 | K78: =2*10^-9*$F$72*$N$14 / (PI()*(0.305*10^-7*$F$14*K$74 / ($C78))^2) -> 0.7522682 | ... S78: =2*10^-9*$F$72*$N$14 / (PI()*(0.305*10^-7*$F$14*S$74 / ($C78))^2) -> 0.0027081655 | T78: =($C78) / (0.0000000305 * $F$14) * SQRT( (0.000000002 * $F$72 * $N$14) / (0.1 * PI()) ) -> 822.82524 | U78: =($C78) / (0.0000000305 * $F$14) * SQRT( (0.000000002 * $F$72 * $N$14) / PI() ) -> 260.20019 | V78: =($C78) / (0.0000000305 * $F$14) * SQRT( (0.000000002 * $F$72 * $N$14) / (10 * PI()) ) -> 82.282524 | W78: =(T78-U78)/12 -> 46.885421 | X78: =T78/20 -> 41.141262 | Y78: =U78/20 -> 13.010009 | Z78: =V78/20 -> 4.1141262
C79: 5 | D79: =2*10^-9*$F$72*$N$14 / (PI()*(0.305*10^-7*$F$14*D$74 / ($C79))^2) -> 105787.72 | E79: =2*10^-9*$F$72*$N$14 / (PI()*(0.305*10^-7*$F$14*E$74 / ($C79))^2) -> 264.46929 | F79: =2*10^-9*$F$72*$N$14 / (PI()*(0.305*10^-7*$F$14*F$74 / ($C79))^2) -> 66.117322 | G79: =2*10^-9*$F$72*$N$14 / (PI()*(0.305*10^-7*$F$14*G$74 / ($C79))^2) -> 29.385476 | H79: =2*10^-9*$F$72*$N$14 / (PI()*(0.305*10^-7*$F$14*H$74 / ($C79))^2) -> 16.52933 | I79: =2*10^-9*$F$72*$N$14 / (PI()*(0.305*10^-7*$F$14*I$74 / ($C79))^2) -> 10.578772 | J79: =2*10^-9*$F$72*$N$14 / (PI()*(0.305*10^-7*$F$14*J$74 / ($C79))^2) -> 2.6446929 | K79: =2*10^-9*$F$72*$N$14 / (PI()*(0.305*10^-7*$F$14*K$74 / ($C79))^2) -> 1.1754191 | ... S79: =2*10^-9*$F$72*$N$14 / (PI()*(0.305*10^-7*$F$14*S$74 / ($C79))^2) -> 0.0042315086 | T79: =($C79) / (0.0000000305 * $F$14) * SQRT( (0.000000002 * $F$72 * $N$14) / (0.1 * PI()) ) -> 1028.5316 | U79: =($C79) / (0.0000000305 * $F$14) * SQRT( (0.000000002 * $F$72 * $N$14) / PI() ) -> 325.25023 | V79: =($C79) / (0.0000000305 * $F$14) * SQRT( (0.000000002 * $F$72 * $N$14) / (10 * PI()) ) -> 102.85316 | W79: =(T79-U79)/12 -> 58.606776 | X79: =T79/20 -> 51.426578 | Y79: =U79/20 -> 16.262512 | Z79: =V79/20 -> 5.1426578 | AA79: =AA74/#REF! -> #REF! | AB79: =AB74/AA74 -> 2
C80: 10 | D80: =2*10^-9*$F$72*$N$14 / (PI()*(0.305*10^-7*$F$14*D$74 / ($C80))^2) -> 423150.86 | E80: =2*10^-9*$F$72*$N$14 / (PI()*(0.305*10^-7*$F$14*E$74 / ($C80))^2) -> 1057.8772 | F80: =2*10^-9*$F$72*$N$14 / (PI()*(0.305*10^-7*$F$14*F$74 / ($C80))^2) -> 264.46929 | G80: =2*10^-9*$F$72*$N$14 / (PI()*(0.305*10^-7*$F$14*G$74 / ($C80))^2) -> 117.54191 | H80: =2*10^-9*$F$72*$N$14 / (PI()*(0.305*10^-7*$F$14*H$74 / ($C80))^2) -> 66.117322 | I80: =2*10^-9*$F$72*$N$14 / (PI()*(0.305*10^-7*$F$14*I$74 / ($C80))^2) -> 42.315086 | J80: =2*10^-9*$F$72*$N$14 / (PI()*(0.305*10^-7*$F$14*J$74 / ($C80))^2) -> 10.578772 | K80: =2*10^-9*$F$72*$N$14 / (PI()*(0.305*10^-7*$F$14*K$74 / ($C80))^2) -> 4.7016762 | ... S80: =2*10^-9*$F$72*$N$14 / (PI()*(0.305*10^-7*$F$14*S$74 / ($C80))^2) -> 0.016926034 | T80: =($C80) / (0.0000000305 * $F$14) * SQRT( (0.000000002 * $F$72 * $N$14) / (0.1 * PI()) ) -> 2057.0631 | U80: =($C80) / (0.0000000305 * $F$14) * SQRT( (0.000000002 * $F$72 * $N$14) / PI() ) -> 650.50047 | V80: =($C80) / (0.0000000305 * $F$14) * SQRT( (0.000000002 * $F$72 * $N$14) / (10 * PI()) ) -> 205.70631 | W80: =(T80-U80)/12 -> 117.21355 | X80: =T80/20 -> 102.85316 | Y80: =U80/20 -> 32.525023 | Z80: =V80/20 -> 10.285316 | AA80: =AA75/#REF! -> #REF! | AB80: =AB75/AA75 -> 0.64 | AC80: =AC75/AC74/4 -> 1.7631286e-06 | AD80: =AD75/AD74 -> 2.3508381e-06 | AE80: =AE75/AE74 -> 8.8156429e-07 | AF80: =AF75/AF74 -> 4.2315086e-07 | AG80: =AG75/AG74 -> 8.4630172e-08 | AH80: =AH75/AH74 -> 3.1344508e-08 | AI80: =AI75/AI74 -> 0
C81: 25 | D81: =2*10^-9*$F$72*$N$14 / (PI()*(0.305*10^-7*$F$14*D$74 / ($C81))^2) -> 2644692.9 | E81: =2*10^-9*$F$72*$N$14 / (PI()*(0.305*10^-7*$F$14*E$74 / ($C81))^2) -> 6611.7322 | F81: =2*10^-9*$F$72*$N$14 / (PI()*(0.305*10^-7*$F$14*F$74 / ($C81))^2) -> 1652.933 | G81: =2*10^-9*$F$72*$N$14 / (PI()*(0.305*10^-7*$F$14*G$74 / ($C81))^2) -> 734.63691 | H81: =2*10^-9*$F$72*$N$14 / (PI()*(0.305*10^-7*$F$14*H$74 / ($C81))^2) -> 413.23326 | I81: =2*10^-9*$F$72*$N$14 / (PI()*(0.305*10^-7*$F$14*I$74 / ($C81))^2) -> 264.46929 | J81: =2*10^-9*$F$72*$N$14 / (PI()*(0.305*10^-7*$F$14*J$74 / ($C81))^2) -> 66.117322 | K81: =2*10^-9*$F$72*$N$14 / (PI()*(0.305*10^-7*$F$14*K$74 / ($C81))^2) -> 29.385476 | ... S81: =2*10^-9*$F$72*$N$14 / (PI()*(0.305*10^-7*$F$14*S$74 / ($C81))^2) -> 0.10578772 | T81: =($C81) / (0.0000000305 * $F$14) * SQRT( (0.000000002 * $F$72 * $N$14) / (0.1 * PI()) ) -> 5142.6578 | U81: =($C81) / (0.0000000305 * $F$14) * SQRT( (0.000000002 * $F$72 * $N$14) / PI() ) -> 1626.2512 | V81: =($C81) / (0.0000000305 * $F$14) * SQRT( (0.000000002 * $F$72 * $N$14) / (10 * PI()) ) -> 514.26578 | W81: =(T81-U81)/12 -> 293.03388 | X81: =T81/20 -> 257.13289 | Y81: =U81/20 -> 81.312559 | Z81: =V81/20 -> 25.713289 | AA81: =AA74/10 -> 5 | AB81: =AB74/10 -> 10 | AC81: =AC80/AB80 -> 2.7548884e-06 | AD81: =AD80/AC80 -> 1.3333333 | AE81: =AE80/AD80 -> 0.375 | AF81: =AF80/AE80 -> 0.48 | AG81: =AG80/AF80 -> 0.2 | AH81: =AH80/AG80 -> 0.37037037 | AI81: =AI80/AH80 -> 0
C82: 50 | D82: =2*10^-9*$F$72*$N$14 / (PI()*(0.305*10^-7*$F$14*D$74 / ($C82))^2) -> 10578772 | E82: =2*10^-9*$F$72*$N$14 / (PI()*(0.305*10^-7*$F$14*E$74 / ($C82))^2) -> 26446.929 | F82: =2*10^-9*$F$72*$N$14 / (PI()*(0.305*10^-7*$F$14*F$74 / ($C82))^2) -> 6611.7322 | G82: =2*10^-9*$F$72*$N$14 / (PI()*(0.305*10^-7*$F$14*G$74 / ($C82))^2) -> 2938.5476 | H82: =2*10^-9*$F$72*$N$14 / (PI()*(0.305*10^-7*$F$14*H$74 / ($C82))^2) -> 1652.933 | I82: =2*10^-9*$F$72*$N$14 / (PI()*(0.305*10^-7*$F$14*I$74 / ($C82))^2) -> 1057.8772 | J82: =2*10^-9*$F$72*$N$14 / (PI()*(0.305*10^-7*$F$14*J$74 / ($C82))^2) -> 264.46929 | K82: =2*10^-9*$F$72*$N$14 / (PI()*(0.305*10^-7*$F$14*K$74 / ($C82))^2) -> 117.54191 | ... S82: =2*10^-9*$F$72*$N$14 / (PI()*(0.305*10^-7*$F$14*S$74 / ($C82))^2) -> 0.42315086 | T82: =($C82) / (0.0000000305 * $F$14) * SQRT( (0.000000002 * $F$72 * $N$14) / (0.1 * PI()) ) -> 10285.316 | U82: =($C82) / (0.0000000305 * $F$14) * SQRT( (0.000000002 * $F$72 * $N$14) / PI() ) -> 3252.5023 | V82: =($C82) / (0.0000000305 * $F$14) * SQRT( (0.000000002 * $F$72 * $N$14) / (10 * PI()) ) -> 1028.5316 | W82: =(T82-U82)/12 -> 586.06776 | X82: =T82/20 -> 514.26578 | Y82: =U82/20 -> 162.62512 | Z82: =V82/20 -> 51.426578 | AA82: =AA75/50 -> 0.00013223464 | AB82: =AB75/50 -> 8.4630172e-05 | AC82: =AC75/$AB$75 -> 0.25 | AD82: =AD75/$AB$75 -> 0.11111111 | AE82: =AE75/$AB$75 -> 0.0625
C83: 100 | D83: =2*10^-9*$F$72*$N$14 / (PI()*(0.305*10^-7*$F$14*D$74 / ($C83))^2) -> 42315086 | E83: =2*10^-9*$F$72*$N$14 / (PI()*(0.305*10^-7*$F$14*E$74 / ($C83))^2) -> 105787.72 | F83: =2*10^-9*$F$72*$N$14 / (PI()*(0.305*10^-7*$F$14*F$74 / ($C83))^2) -> 26446.929 | G83: =2*10^-9*$F$72*$N$14 / (PI()*(0.305*10^-7*$F$14*G$74 / ($C83))^2) -> 11754.191 | H83: =2*10^-9*$F$72*$N$14 / (PI()*(0.305*10^-7*$F$14*H$74 / ($C83))^2) -> 6611.7322 | I83: =2*10^-9*$F$72*$N$14 / (PI()*(0.305*10^-7*$F$14*I$74 / ($C83))^2) -> 4231.5086 | J83: =2*10^-9*$F$72*$N$14 / (PI()*(0.305*10^-7*$F$14*J$74 / ($C83))^2) -> 1057.8772 | K83: =2*10^-9*$F$72*$N$14 / (PI()*(0.305*10^-7*$F$14*K$74 / ($C83))^2) -> 470.16762 | ... S83: =2*10^-9*$F$72*$N$14 / (PI()*(0.305*10^-7*$F$14*S$74 / ($C83))^2) -> 1.6926034 | T83: =($C83) / (0.0000000305 * $F$14) * SQRT( (0.000000002 * $F$72 * $N$14) / (0.1 * PI()) ) -> 20570.631 | U83: =($C83) / (0.0000000305 * $F$14) * SQRT( (0.000000002 * $F$72 * $N$14) / PI() ) -> 6505.0047 | V83: =($C83) / (0.0000000305 * $F$14) * SQRT( (0.000000002 * $F$72 * $N$14) / (10 * PI()) ) -> 2057.0631 | W83: =(T83-U83)/12 -> 1172.1355 | X83: =T83/20 -> 1028.5316 | Y83: =U83/20 -> 325.25023 | Z83: =V83/20 -> 102.85316 | AA83: =1/AA81^2 -> 0.04 | AB83: =1/AB81^2 -> 0.01
C84: 500 | D84: =2*10^-9*$F$72*$N$14 / (PI()*(0.305*10^-7*$F$14*D$74 / ($C84))^2) -> 1057877151 | E84: =2*10^-9*$F$72*$N$14 / (PI()*(0.305*10^-7*$F$14*E$74 / ($C84))^2) -> 2644692.9 | F84: =2*10^-9*$F$72*$N$14 / (PI()*(0.305*10^-7*$F$14*F$74 / ($C84))^2) -> 661173.22 | G84: =2*10^-9*$F$72*$N$14 / (PI()*(0.305*10^-7*$F$14*G$74 / ($C84))^2) -> 293854.76 | H84: =2*10^-9*$F$72*$N$14 / (PI()*(0.305*10^-7*$F$14*H$74 / ($C84))^2) -> 165293.3 | I84: =2*10^-9*$F$72*$N$14 / (PI()*(0.305*10^-7*$F$14*I$74 / ($C84))^2) -> 105787.72 | J84: =2*10^-9*$F$72*$N$14 / (PI()*(0.305*10^-7*$F$14*J$74 / ($C84))^2) -> 26446.929 | K84: =2*10^-9*$F$72*$N$14 / (PI()*(0.305*10^-7*$F$14*K$74 / ($C84))^2) -> 11754.191 | ... S84: =2*10^-9*$F$72*$N$14 / (PI()*(0.305*10^-7*$F$14*S$74 / ($C84))^2) -> 42.315086 | T84: =($C84) / (0.0000000305 * $F$14) * SQRT( (0.000000002 * $F$72 * $N$14) / (0.1 * PI()) ) -> 102853.16 | U84: =($C84) / (0.0000000305 * $F$14) * SQRT( (0.000000002 * $F$72 * $N$14) / PI() ) -> 32525.023 | V84: =($C84) / (0.0000000305 * $F$14) * SQRT( (0.000000002 * $F$72 * $N$14) / (10 * PI()) ) -> 10285.316 | W84: =(T84-U84)/12 -> 5860.6776 | X84: =T84/20 -> 5142.6578 | Y84: =U84/20 -> 1626.2512 | Z84: =V84/20 -> 514.26578
C85: 1000 | D85: =2*10^-9*$F$72*$N$14 / (PI()*(0.305*10^-7*$F$14*D$74 / ($C85))^2) -> 4231508605 | E85: =2*10^-9*$F$72*$N$14 / (PI()*(0.305*10^-7*$F$14*E$74 / ($C85))^2) -> 10578772 | F85: =2*10^-9*$F$72*$N$14 / (PI()*(0.305*10^-7*$F$14*F$74 / ($C85))^2) -> 2644692.9 | G85: =2*10^-9*$F$72*$N$14 / (PI()*(0.305*10^-7*$F$14*G$74 / ($C85))^2) -> 1175419.1 | H85: =2*10^-9*$F$72*$N$14 / (PI()*(0.305*10^-7*$F$14*H$74 / ($C85))^2) -> 661173.22 | I85: =2*10^-9*$F$72*$N$14 / (PI()*(0.305*10^-7*$F$14*I$74 / ($C85))^2) -> 423150.86 | J85: =2*10^-9*$F$72*$N$14 / (PI()*(0.305*10^-7*$F$14*J$74 / ($C85))^2) -> 105787.72 | K85: =2*10^-9*$F$72*$N$14 / (PI()*(0.305*10^-7*$F$14*K$74 / ($C85))^2) -> 47016.762 | ... S85: =2*10^-9*$F$72*$N$14 / (PI()*(0.305*10^-7*$F$14*S$74 / ($C85))^2) -> 169.26034 | T85: =($C85) / (0.0000000305 * $F$14) * SQRT( (0.000000002 * $F$72 * $N$14) / (0.1 * PI()) ) -> 205706.31 | U85: =($C85) / (0.0000000305 * $F$14) * SQRT( (0.000000002 * $F$72 * $N$14) / PI() ) -> 65050.047 | V85: =($C85) / (0.0000000305 * $F$14) * SQRT( (0.000000002 * $F$72 * $N$14) / (10 * PI()) ) -> 20570.631 | W85: =(T85-U85)/12 -> 11721.355 | X85: =T85/1500000 -> 0.13713754 | Y85: =U85/1500000 -> 0.043366698 | Z85: =V85/1500000 -> 0.013713754 | AA85: Accuracy factors | AH85: Now, to use acceleration equation to calculate displacement:
AA86: Uncertain target location due to finite sensor resolution | AH86: t = (Dm / 299,792,458) + (Dm / Wv)
C87: 45342 | D87: =E74/20 -> 1 | H87: =I74/20 -> 5 | J87: =K74/20 -> 15 | M87: =N74/20 -> 50 | AA87: Uncertain target motion due to sensor glint or shape effects
C88: 5/100 | H88: =I74/20 -> 5 | L88: =M74/20 -> 25 | N88: =O74/20 -> 75 | R88: =S74/20 -> 250 | AA88: Sensor boresight error due to finite manufacturing tolerances | AH88: where:
AA89: Target motion during sensor integration time
AA90: Analog-to-digital conversion errors of sensor data | AH90: t = time it takes light from target to travel to targeting sensors plus time it takes weapon to travel to target (s)
AA91: Software errors in fire control system | AH91: t = time target has to jink before weapon arrives
AA92: Hardware errors in fire control system | AH92: Dm = range to target (m)
AA93: Digital-to-analog conversion errors of gunlaying servo commands | AH93: Wv = weapon velocity (m/s)
AA94: Target motion during weapon aiming time | AH94: 299,792,458 = meters in one light-second
AA95: Weapon boresight error due to finite manufacturing tolerances | AH95: Dm / 299,792,458 = time it takes light from target to travel to targeting sensors (s)
AA96: Weapon structural distortion due to inertial effects of rapid slew | AH96: Dm / Wv = time it takes weapon to travel to target (s)
AA97: Weapon structural distortion due to external or internal vibration
P98: H = maximum percent chance to hit target given light-speed lag (0.0 - 1.0 with 1.0 = 100%) | AA98: Weapon structural distortion due to thermal expansion during firing
P99: Cm = target ship's mean cross section (m2, for a purely convex object this is approximately 1/4 of the surface area)
B100: accuracy | C100: =5*5 / (0.7854 * 10000 * ((4000 + 4000)/300000)^4) -> 6294.6876 | P100: a = target's acceleration (m/s, where 9.81 = 1 g)
P101: Dm = range to target (m)
P102: Wv = weapon velocity (m/s)
...

Sheet shield
B2: 1 sheet | C2: 100 | D2: kj/m²
C3: =C2/10000 -> 0.01 | D3: kJ/cm²

Sheet Sheet27
C5: 3
C6: =C5+3 -> 6
C7: =C6+3 -> 9
C8: =C7+3 -> 12
C9: =C8+3 -> 15
C10: =C9+3 -> 18
C11: =C10+3 -> 21
C12: =C11+3 -> 24
C13: =C12+3 -> 27
C14: =C13+3 -> 30
C15: =C14+3 -> 33
C16: =C15+3 -> 36
C17: =C16+3 -> 39
C18: =C17+3 -> 42
C19: =C18+3 -> 45 | D19: =sum(C5:C19) -> 360
C20: =C19+3 -> 48
C21: =C20+3 -> 51
C22: =C21+3 -> 54
C23: =C22+3 -> 57
C24: =C23+3 -> 60
C25: =C24+3 -> 63
C26: =C25+3 -> 66
C27: =C26+3 -> 69
C28: =C27+3 -> 72
C29: =C28+3 -> 75
C30: =C29+3 -> 78
C31: =C30+3 -> 81
... C78: =C77+3 -> 222
C79: =C78+3 -> 225 | D79: =sum(C5:C79) -> 8550

Sheet Sheet26
C3: Volume of a spherical shell with outer and inner radii R and r
C4: 4π3(R3−r3) | D4: =4*Pi()* (10^3-9.5^3) -> 1792.2786 | E4: 0.05
H5: 3 | I5: earth radius
E7: =D4/D11 -> 0.427875 | G7: =E7*2 -> 0.85575 | H7: =H5/G7 -> 3.5056968 | I7: g
C10: Volume of sphere
C11: 4 / 3 * π r 3 | D11: =4/3 * pi() * 10^3 -> 4188.7902
D14: =4/3 * pi() * 63000^3 -> 1.04739e+15 | E14: earth volume | J14: km
B15: radius | C15: =63000*3 -> 189000 | D15: =4/3 * pi() * C15^3 -> 2.82796e+16 | E15: utopia volume
B17: shell ratio | C17: 0.01 | D17: =4*Pi()* (C15^3-(C15*(1-C17))^3) -> 2.5198e+15 | E17: mh volume
H18: distance to be at 1g
D19: =D17/D14*2 -> 4.811562 | E19: g | H19: =C15*(sqrt(D19)-1) -> 225576.66 | I19: km

Sheet gravity assist
I2: v = sqrt( G * m / r )
C3: Earth | D3: Mars | E3: Mercury | F3: Proxima b | J3: m = mass of star (kg)
B4: orbit radius | C4: 1 | F4: 0.05 | G4: AU | J4: r = radius of orbit (m)
B5: orbital velocity | C5: =sqrt(M9*M5/(C4*M8)) -> 29788.23 | F5: =sqrt(M9*M6/(F4*M8)) -> 46544.315 | G5: m/s | L5: Sun mass | M5: =1.989*10^30 -> 1.989e+30 | O5: 1.989 × 10^30 kg
C6: 107000 | D6: 86871 | E6: 170505 | F6: =F5*3600/1000 -> 167559.53 | G6: km/h | L6: Proxima mass | M6: =2.428 * 10^29 -> 2.428e+29 | O6: 2.428 × 10^29 kg
C7: =C6/60 -> 1783.3333 | D7: =D6/60 -> 1447.85 | E7: =E6/60 -> 2841.75 | F7: =F6/60 -> 2792.6589 | G7: km/m
C8: =C7/18 -> 99.074074 | D8: =D7/18 -> 80.436111 | E8: =E7/18 -> 157.875 | F8: =F7/18 -> 155.14772 | G8: cs | L8: AU | M8: =1.496*10^11 -> 149600000000 | N8: m
C9: =C7/60 -> 29.722222 | D9: =D7/60 -> 24.130833 | E9: =E7/60 -> 47.3625 | F9: =F7/60 -> 46.544315 | G9: km/s | L9: G | M9: =6.674 * 10^-11 -> 0 | N9: Nm² / kg²
B11: https://space.stackexchange.com/questions/23295/how-do-we-come-up-with-the-gravity-assist-or-slingshot-formula
B13: Final velocity = Initial velocity + 2 (velocity of the planet)
B16: gravity assist | C16: =2*C9 -> 59.444444 | D16: =2*D9 -> 48.261667 | E16: =2*E9 -> 94.725 | F16: =2*F9 -> 93.08863 | G16: km/s
C17: =C16/864 -> 0.06880144 | D17: =D16/864 -> 0.05585841 | E17: =E16/864 -> 0.10963542 | F17: =F16/864 -> 0.10774147 | G17: gj

Sheet Sheet8
C4: =30000/360 -> 83.333333
G5: RADIATORS
H6: heat cap | I6: 300 | J6: kW/m²
B7: mass flow | C7: 10 | D7: kg/s | H7: area | I7: 833 | J7: m²
B8: exhaust vel | C8: =10000000 -> 10000000 | D8: m/s | H8: mass | I8: 10 | J8: t
B9: momentum | C9: =C8*C7 -> 100000000 | D9: kg m/s | H9: cooling | I9: =833*300/1000 -> 249.9 | J9: MW
B10: mass | C10: 200 | D10: tons
B11: velocity | C11: =C9/(C10*1000) -> 500 | D11: m/s
G13: =100000/I9 -> 400.16006
H16: 1 newton = | I16: amount to accelerate 1kg at 1m/s²
A17: DELTA V
B18: deltaV | C18: Ve * ln ( R ) | G18: ACCEL
B19: exhaust (Ve) | C19: 20000000 | D19: m/s | H19: thrust | I19: 3000 | J19: kN
B20: mass ratio | C20: 3 | E20: 2 to 5 | H20: mass | I20: 60 | J20: tons
B21: deltaV | C21: =C19*ln(C20) -> 21972246 | D21: m/s | H21: accel | I21: =I19/(I20) -> 50 | J21: m/s²
C22: =C21/1000 -> 21972.246 | D22: km/s | I22: =I21/10 -> 5 | J22: g
C23: =C22*1000/299792458 -> 0.073291523 | D23: c
G25: SHIFTING GEARS | I25: Tp = (Ve * T) / 2
H26: Thrust power | I26: 10 | J26: TW
B27: ship width | C27: 18 | I27: =I26*1000000 -> 10000000 | J27: MW
B28: ship length | C28: 60 | H28: exhaust vel | I28: 20000 | J28: km/s
B29: ship surface | C29: =C27*C28*4 -> 4320 | H29: Thrust | I29: =2*I27/I28 -> 1000 | J29: kN
H31: waste heat | I31: =I27*0.05 -> 500000 | J31: MW
H32: radiators | I32: =I31/I6 -> 1666.6667 | J32: m²

Sheet Ship size  mass
A2: https://www.projectrho.com/public_html/rocket/spacewarship.php#id--Ship_Types--Quick-n-Dirty_Ship_Types | L2: frig | N2: NASA
E3: 9 | F3: dreadnaught | H3: 50 | I3: Mt | K3: Propulsion | L3: 20 | M3: % | N3: 3.7 | O3: % | P3: propulsion
C4: supertanker | D4: 500 kt | E4: 8 | F4: supertanker | H4: 2 | I4: MT | K4: Life support | L4: 5 | M4: % | N4: 3.4 | O4: % | P4: Thermal
C5: naval carrier | D5: 90 kt | E5: 7 | F5: carrier | H5: 500 | I5: kt | K5: Sensors | L5: 5 | M5: % | N5: 7.5 | O5: % | P5: Comms
C6: naval battleship | D6: 40 kt | E6: 6 | F6: battleship | H6: 100 | I6: kt | K6: CPU | L6: 5 | M6: % | N6: 8 | O6: % | P6: CPU
C7: naval cruiser | D7: 9 kt | E7: 5 | F7: battlecruiser | H7: 20 | I7: kt | K7: Structure | L7: 15 | M7: % | N7: 21.7 | O7: % | P7: Structure
C8: naval destroyer | D8: 7 kt | K8: Cooling | L8: 10 | M8: %
D9: 3 kt | E9: 4 | F9: cruiser | H9: 1 | I9: kt | K9: Power | L9: 5 | M9: % | N9: 28 | O9: % | P9: Power
C10: ISS | D10: 450 t | K10: Payload | L10: 35 | M10: % | N10: 26 | O10: % | P10: Payload
C11: Boeing 747 | D11: 100 t | E11: 3 | F11: frigate | H11: 300 | I11: t
D12: 50 t | E12: 2 | F12: fighter | H12: 50 | I12: t | L12: =sum(L3:L10) -> 100 | N12: =sum(N3:N10) -> 98.3
C13: Jet | D13: 10-15 t | E13: 2 | F13: shuttle | H13: 10 | I13: t
C14: Voiture | D14: 2 t | E14: 1 | F14: exo | H14: 2 | I14: t
K16: d = m/v
C17: size | D17: ratio | E17: wet (t) | F17: dry | G17: width | H17: length | I17: volume | K17: density (t/m3) | M17: prop | N17: power | O17: payload
B18: VISTA | C18: 170x100 m | D18: =E18/F18 -> 3.2258065 | E18: 6000 | F18: 1860 | G18: 170 | H18: 100 | I18: =(PI()*G18*G18/4)*H18 -> 2269800.7 | K18: =E18/I18 -> 0.0026434039 | M18: =$N$3/100*F18 -> 68.82
A19: fighter | B19: Exacting | C19: 4x60 m | D19: =E19/F19 -> 2 | E19: 40 | F19: 20 | G19: 4 | H19: 60 | I19: =(PI()*G19*G19/4)*H19 -> 753.98224 | J19: m3 | K19: =E19/I19 -> 0.053051648 | M19: =$L$3/100*F19 -> 4 | N19: =$L$9/100*F19 -> 1 | O19: =$L$10/100*F19 -> 7
A20: dread | B20: Leviathan | C20: 0.8x3 km | D20: =E20/F20 -> 18.095574 | E20: =K20*I20 -> 45238934 | F20: 2500000 | G20: 800 | H20: 3000 | I20: =(PI()*G20*G20/4)*H20 -> 1507964474 | J20: m3 | K20: 0.03 | M20: =$N$3/100*F20 -> 92500
A21: battleship | B21: Truman | C21: 110x376m | D21: =E21/F21 -> 2 | E21: =K21*I21 -> 107197.42 | F21: =E21/2 -> 53598.712 | G21: 110 | H21: 376 | I21: =(PI()*G21*G21/4)*H21 -> 3573247.5 | J21: m3 | K21: 0.03 | M21: =$N$3/100*F21 -> 1983.1524
A22: destro | B22: Morrigan | C22: 9x31m | D22: =E22/F22 -> 2 | E22: =K22*I22 -> 59.164044 | F22: =E22/2 -> 29.582022 | G22: 9 | H22: 31 | I22: =(PI()*G22*G22/4)*H22 -> 1972.1348 | J22: m3 | K22: 0.03 | M22: =$N$3/100*F22 -> 1.0945348
A23: fighter | B23: Razorback | C23: 8x20m | D23: =E23/F23 -> 2 | E23: =K23*I23 -> 50.265482 | F23: =E23/2 -> 25.132741 | G23: 8 | H23: 20 | I23: =(PI()*G23*G23/4)*H23 -> 1005.3096 | J23: m3 | K23: 0.05 | M23: =$N$3/100*F23 -> 0.92991143
A24: cruiser | B24: Leonidas | C24: 60*270m | D24: =E24/F24 -> 2 | E24: =K24*I24 -> 22902.21 | F24: =E24/2 -> 11451.105 | G24: 60 | H24: 270 | I24: =(PI()*G24*G24/4)*H24 -> 763407.01 | J24: m3 | K24: 0.03 | M24: =$N$3/100*F24 -> 423.69089
A25: dread | B25: Behemoth | C25: 960x2460m | D25: =E25/F25 -> 2 | E25: =K25*I25 -> 53418134 | F25: =E25/2 -> 26709067 | G25: 960 | H25: 2460 | I25: =(PI()*G25*G25/4)*H25 -> 1780604451 | J25: m3 | K25: 0.03 | M25: =$N$3/100*F25 -> 988235.47
A26: cruiser | B26: Scirocco | C26: 70x200m | D26: =E26/F26 -> 2 | E26: =K26*I26 -> 23090.706 | F26: =E26/2 -> 11545.353 | G26: 70 | H26: 200 | I26: =(PI()*G26*G26/4)*H26 -> 769690.2 | J26: m3 | K26: 0.03 | M26: =$N$3/100*F26 -> 427.17806
A27: frigate | B27: Amun-Ra | C27: 22x60m | D27: 1.5 | E27: =K27*I27 -> 684.23888 | F27: =E27/D27 -> 456.15925 | G27: 22 | H27: 60 | I27: =(PI()*G27*G27/4)*H27 -> 22807.963 | J27: m3 | K27: 0.03 | M27: =$N$3/100*F27 -> 16.877892
A28: frigate | B28: Stratios | C28: 18x60m | D28: 1.5 | E28: =K28*I28 -> 318.08626 | F28: =E28/D28 -> 212.0575 | G28: 15 | H28: 60 | I28: =(PI()*G28*G28/4)*H28 -> 10602.875 | J28: m3 | K28: 0.03 | M28: =$L$3/100*F28 -> 42.411501 | N28: =$L$9/100*F28 -> 10.602875 | O28: =$L$10/100*F28 -> 74.220126
A29: frigate | B29: Rocinante | D29: 1.5 | E29: =K29*I29 -> 108.38495 | F29: =E29/D29 -> 72.256631 | G29: 10 | H29: 46 | I29: =(PI()*G29*G29/4)*H29 -> 3612.8316 | J29: m3 | K29: 0.03 | M29: =$N$3/100*F29 -> 2.6734953
A30: carrier | D30: 1.5 | E30: =K30*I30 -> 471238.9 | F30: =E30/D30 -> 314159.27 | G30: 200 | H30: 500 | I30: =(PI()*G30*G30/4)*H30 -> 15707963 | J30: m3 | K30: 0.03 | M30: =$N$3/100*F30 -> 11623.893
A31: battleship | B31: Nestor | D31: 1.5 | E31: =K31*I31 -> 1256637.1 | F31: =E31/D31 -> 837758.04 | G31: 200 | H31: 800 | I31: =(PI()*G31*G31/4)*H31 -> 25132741 | J31: m3 | K31: 0.05 | M31: =$N$3/100*F31 -> 30997.048
A32: supertanker | D32: 3 | E32: =K32*I32 -> 2261946.7 | F32: =E32/D32 -> 753982.24 | G32: 400 | H32: 600 | I32: =(PI()*G32*G32/4)*H32 -> 75398224 | J32: m3 | K32: 0.03 | M32: =$N$3/100*F32 -> 27897.343
A33: Laserstar | D33: 1.5 | E33: =K33*I33 -> 1.0602875e+08 | F33: =E33/D33 -> 70685835 | G33: 3000 | H33: 500 | I33: =(PI()*G33*G33/4)*H33 -> 3534291735 | J33: m3 | K33: 0.03
A34: battlecruiser | B34: Scirocco | D34: 1.5 | E34: =K34*I34 -> 94247.78 | F34: =E34/D34 -> 62831.853 | G34: 100 | H34: 400 | I34: =(PI()*G34*G34/4)*H34 -> 3141592.7 | J34: m3 | K34: 0.03
A35: cruiser | D35: 1.5 | E35: =K35*I35 -> 2120.575 | F35: =E35/D35 -> 1413.7167 | G35: 30 | H35: 100 | I35: =(PI()*G35*G35/4)*H35 -> 70685.835 | J35: m3 | K35: 0.03
A36: Hub | D36: 1.5 | E36: =K36*I36 -> 2120575041 | F36: =E36/D36 -> 1413716694 | G36: 3000 | H36: 10000 | I36: =(PI()*G36*G36/4)*H36 -> 70685834706 | J36: m3 | K36: 0.03
A37: Spatioport | D37: 1.5 | E37: =K37*I37 -> 94247780 | F37: =E37/D37 -> 62831853 | G37: 1000 | H37: 4000 | I37: =(PI()*G37*G37/4)*H37 -> 3141592654 | J37: m3 | K37: 0.03
G38: =H24/G24 -> 4.5
G39: =H25/G25 -> 2.5625
G40: =H26/G26 -> 2.8571429
C41: density | D41: 0.05 | E41: t/m3 | G41: =H27/G27 -> 2.7272727
C42: Mass | D42: 1000 | E42: t | G42: =H28/G28 -> 4
C43: Volume | D43: =D42/D41 -> 20000 | E43: m3 | G43: =H29/G29 -> 4.6
B44: ratio 4 | C44: r | D44: =(D43/(6*PI()))^(1/3) -> 10.199439 | E44: m | G44: =H30/G30 -> 2.5
C45: h | D45: =8*D44 -> 81.595513 | E45: m | G45: =H31/G31 -> 4
G46: =H32/G32 -> 1.5
G47: =H33/G33 -> 0.16666667
G48: =H38/G38 -> 0
G49: =H39/G39 -> 0

Sheet Others
G4: Plasma windows
B5: Passager (militaire) | C5: 0.5 | D5: t | G5: https://www.projectrho.com/public_html/rocket/spacewardefense.php#id--Force_Fields--Considerations
B6: Passager (comfort) | C6: 1 | D6: t | G6: Erickson's Model
B7: Passager (luxe) | C7: 2 | D7: t | H7: P * V = k * E
B9: Anti-laser shield | D9: Kerr effect / Vacuum polarization | H9: where:
D10: https://arxiv.org/pdf/1012.1134
H11: P = pressure
H12: V = volume
H13: E energy
H14: k = constant
H16: Assuming k=1, you get something like 42 joules for a 1 meter radius sphere with 1 atmosphere of pressure inside. If you make k smaller, the energy requirements go up.
H22: https://en.wikipedia.org/wiki/Polariton_superfluid

Sheet coilgun
A1: u
L4: RODS
B5: Coilgun : | C5: lower power consumption
C6: coils are not eroded | L6: mass (kg) | M6: radius (mm) | N6: speed (kms) | O6: energy (MJ) | P6: Field (T) | Q6: barrel1 (m) | R6: barrelmin (m) | S6: Power (W) | T6: Graphene (kg) | U6: MH (kg) | V6: factor | W6: COILGUN stats
E7: =E9*1000000 -> 4500000000 | F7: J | H7: Rod | W7: L/W ratio | X7: 3 to 10
D8: Efficiency | E8: 0.9 | G8: mass | H8: 10 | I8: kg | J8: =H8*10^3 -> 10000 | K8: g | L8: e-9 | M8: 0.01 | N8: 3 | O8: e-9 | P8: 30 | Q8: 0.04 | R8: 0.04 | S8: e2 | T8: 0.005 | U8: e-6 | W8: Density | X8: 1 to 20
B9: kinetic energy = 0.5 * mass * velocity2 | E9: =10^-6*0.5*H8*(H12)^2 -> 4500 | F9: MJ | G9: radius | H9: 25 | I9: mm | J9: =H9/10 -> 2.5 | K9: cm | L9: e-6 | M9: 0.1 | N9: 3 | O9: e-6 | P9: 30 | Q9: 0.4 | R9: 0.04 | S9: e5 | T9: e0 | U9: e-4 | W9: Barrel length | X9: L = v² / 2a | AA9: L = barrel length (m)
E10: =E9/(PI()*J9^2) -> 229.18312 | F10: MJ/cm² | G10: velocity | H10: 30 | I10: km/s | AA10: v = exit velocity (m/s)
B11: heat energy = 0.5 * (1/e - 1) * (kinetic energy) | E11: =0.5 * (1/E8-1) * E9 -> 250 | F11: MJ | G11: radius | H11: =H9/1000 -> 0.025 | I11: m | L11: e-6 | M11: 0.1 | N11: 10 | O11: e-5 | P11: 100 | Q11: 0.4 | R11: 0.04 | S11: e6 | T11: 40 | U11: 0.007 | AA11: a = average acceleration (m/s²)
B12: projectile temperature = (heat energy) / (C * mass) | E12: =100*E11/(H13*H8) -> 55.555556 | F12: % | G12: velocity | H12: =H10*10^3 -> 30000 | I12: m/s | L12: 0.001 | M12: 1 | N12: 10 | O12: 0.05 | Q12: 1.8 | S12: e8 | T12: 4000 | U12: 0.7
B13: volume = kinetic energy / (K * (magnetic field)^2) | E13: =E9*10^6/(H20*(H22)^2) -> 0.50265482 | F13: m3 | G13: Heat cap | H13: 45 | J13: CNT | L13: 0.01 | M13: 2 | N13: 10 | O13: 0.5 | Q13: 4.5 | S13: e9 | T13: e4 | U13: e0 | V13: =Q13/Q12 -> 2.5 | W13: E = 1/2 LI² | X13: > not a limiting factor | AA13: E = energy stored in magnetic field (Joules)
B14: length = volume / area | E14: =E13/(PI()*H11^2) -> 256 | F14: m | G14: Density | H14: 20000 | I14: kg/m3 | L14: 0.1 | M14: 4.5 | N14: 10 | O14: 5 | Q14: 9 | T14: e5 | U14: e1 | V14: =Q14/Q13 -> 2 | AA14: L = inductance of the coil (Henrys)
G15: Length | H15: =H8/(H14* PI()*H11^2) -> 0.25464791 | I15: m | L15: 1 | M15: 10 | N15: 10 | O15: 50 | Q15: 18 | S15: e10 | V15: =Q15/Q14 -> 2 | AA15: I = current through the coil (Amps)
B16: mass = density * volume * ratio | E16: =H23*E13*H24 -> 502.65482 | F16: kg | G16: L/W ratio | H16: =H15/(H11*2) -> 5.0929582 | L16: 10 | M16: 20 | N16: 10 | O16: 500 | Q16: 45 | V16: =Q16/Q15 -> 2.5
E17: =E16*1000 -> 502654.82 | F17: g | W17: L ≈ μ0 N² A / l | AA17: μ0​=4π⋅10−7H/m
H18: Coil | L18: 0.1 | M18: 5 | N18: 30 | O18: 50 | Q18: 64 | S18: e10 | X18: μ0​= | Y18: =4*PI()*10^-7 -> 1.2566371e-06 | Z18: H/m | AA18: N = number of turns
B19: momentum p = m*V | E19: =H8*H10* 10^-3 -> 0.3 | G19: K (max) | H19: 400 | I19: kJ/m3/T2 | K19: metallic hydrogen | L19: 1 | M19: 10 | N19: 30 | O19: 500 | Q19: 160 | V19: =Q19/Q18 -> 2.5 | AA19: A = cross-sectional area of the coil (m²)
G20: K | H20: =1/ (2*Y18) -> 397887.36 | I20: T² m3 / J | L20: 10 | M20: 20 | N20: 30 | O20: 5000 | Q20: 400 | S20: e11 | V20: =Q20/Q19 -> 2.5 | AA20: l = length of the coil (m)
B21: accel | C21: for above L | D21: a = v²/ 2L | E21: =H12^2 / (2*E14) -> 1757812.5 | F21: m/s² | G21: field (max) | H21: 200 | I21: teslas | W21: Imax = 10^7 A
E22: =E21/10 -> 175781.25 | F22: g | G22: field | H22: 150 | I22: teslas | L22: e-6 | M22: 0.1 | U22: 2e-05
B23: barrel min | C23: for a = e6 gs | D23: L = v² / 2a | E23: =H12^2 / (2*10^8) -> 4.5 | F23: m | G23: Density | H23: 10000 | I23: kg/m3 | L23: 0.1 | M23: 6 | N23: 0.3 | O23: 0.005 | P23: 10 | Q23: 1 | S23: e6 | T23: e1 | U23: e-3 | W23: P = B² / 2μ0 | AA23: P = Magnetic pressure inside the coil
G24: Volume ratio | H24: 0.1 | L24: 1 | M24: 10 | N24: 0.3 | O24: 0.05 | R24: 0.16 | X24: P= | Y24: =H22^2 / (2*Y18) -> 8952465549 | Z24: Pascals | AA24: B = field strength
B25: time in barrel | C25: t = v/a | E25: =H12/E21 -> 0.017066667 | F25: s | L25: 10 | M25: 20 | N25: 0.3 | O25: 0.5 | R25: 0.4 | S25: e9 | Y25: =Y24*10^-9 -> 8.9524655 | Z25: GPa
B26: Power | C26: P = Ek / t | E26: =E9*10^6 /E25 -> 263671875000 | F26: W | L26: 100 | M26: 45 | N26: 0.3 | O26: 5 | R26: 0.8 | Y26: carbon nanotubes > 10 GPa
B27: Capacitor | C27: graphene | D27: 360000 J/kg | E27: =E26/360000 -> 732421.88 | F27: kg
B28: Battery | C28: MH | D28: 200 MJ/kg | E28: =E26/(2*10^8) -> 1318.3594 | F28: kg | L28: 0.001 | M28: 1 | N28: 3 | O28: 0.005 | P28: 50 | Q28: 1.4 | S28: e6 | T28: e2 | U28: e-2
B29: Pulse system | C29: 1 shot / second (1Hz) for 150T, 10Hz for 30T | L29: 0.01 | M29: 2 | N29: 3 | O29: 0.05 | P29: 50 | Q29: 3.6 | V29: =Q29/Q28 -> 2.5714286
L30: 0.1 | M30: 5 | N30: 3 | O30: 0.5 | Q30: 0.6 | V30: =Q30/Q29 -> 0.16666667
L31: 1 | M31: 10 | N31: 3 | O31: 5 | Q31: 1.5 | S31: e9 | V31: =Q31/Q30 -> 2.5
B32: 🎯 Survivable g-ranges by Projectile Type | L32: 10 | M32: 20 | N32: 3 | O32: 50 | Q32: 4 | V32: =Q32/Q31 -> 2.6666667
B33: Projectile Type | D33: Survivable Acceleration (g) | F33: Notes | L33: 100 | M33: 45 | N33: 3 | O33: 500 | Q33: 8 | V33: =Q33/Q32 -> 2
B34: Kinetic dart (tungsten rod) | D34: >1,000,000 g | F34: Solid metal penetrators can handle extreme shocks.
B35: Simple coilgun slug (no payload) | D35: 100,000 – 500,000 g | F35: Reasonable target for high-speed systems. | L35: e-12 | M35: 0.001 | N35: 2 | O35: e-12 | Q35: 0
B36: Miniaturized electronics inside | D36: 1,000 – 10,000 g | F36: With careful shock mounting and hardening.
B37: Guided munitions / sensors | D37: 100 – 1,000 g | F37: Close to artillery-grade limits.
B38: Delicate optics, MEMS | D38: <100 g | F38: May fail even under modest acceleration. | T38: hydrodynamic penetration | V38: Lp​ = projectile length
T39: d = Lp * ρp / ρt | V39: ρp = projectile density
T40: ρ | V40: ρt​ = target density
T41: CNT | W41: 1
A42: Pistol | T42: steel | U42: 7850 | V42: kg/m3 | W42: 8
E43: =E44*10^6 -> 20 | F43: J | T43: hull | W43: 10
B44: kinetic energy = 0.5 * mass * velocity2 | E44: =10^-6*0.5*K45*(K47*10^3)^2 -> 2e-05 | F44: MJ | N44: field | O44: 30 | P44: T | T44: tungsten | W44: 20
E45: =E44/(PI()*(K46/20)^2) -> 0.010185916 | F45: MJ/cm² | J45: mass | K45: 1e-05 | L45: kg | N45: barrel : | O45: 0.4 | P45: m
C46: impact area | E46: =3.14*K48^2 -> 1.9625e-07 | F46: m² | J46: caliber | K46: 0.5 | L46: mm | N46: Battery | O46: 0.5 | P46: kg | Q46: graphene
B47: hydrodynamic penetration | D47: CNT | E47: =K51*(K50)/($W$41)*0.6 -> 3.0557749 | F47: cm | J47: velocity | K47: 2 | L47: km/s | R47: Damage | S47: 0 | T47: delivers nanites under the skin
D48: Steel | E48: =K51*(K50)/($W$42)*0.6 -> 0.38197186 | F48: cm | J48: radius | K48: =K46/2000 -> 0.00025 | L48: m | R48: AP | S48: 3
D49: hull | E49: =K51*(K50)/($W$43)*0.6 -> 0.30557749 | F49: cm | J49: velocity | K49: =K47*10^3 -> 2000 | L49: m/s | R49: RAF | S49: x1
D50: tungsten | E50: =K51*(K50)/($W$44)*0.6 -> 0.15278875 | F50: cm | K50: 20 | L50: g/cm3 | N50: Impact | O50: 106 | P50: dB
J51: Length | K51: =100*K45/(K50*1000* PI()*K48^2) -> 0.25464791 | L51: cm | N51: Sonic boom | O51: negligible
J52: L/W ratio | K52: =K51/(K46/10) -> 5.0929582
A54: Sniper
E55: =E56*10^6 -> 50000 | F55: J
B56: kinetic energy = 0.5 * mass * velocity2 | E56: =10^-6*0.5*K57*(K59*10^3)^2 -> 0.05 | F56: MJ | N56: field | O56: 150 | P56: T | R56: Damage | S56: 5+
E57: =E56/(PI()*(K58/20)^2) -> 1.5915494 | F57: MJ/cm² | J57: mass | K57: 0.001 | L57: kg | N57: barrel : | O57: 1.8 | P57: m | R57: AP | S57: 4
C58: impact area | E58: =3.14*K60^2 -> 3.14e-06 | F58: m² | J58: caliber | K58: 2 | L58: mm | N58: Coil | P58: kg | R58: RAF | S58: 1/sec
B59: hydrodynamic penetration | D59: CNT | E59: =K63*(K62)/($W$41) -> 31.830989 | F59: cm | J59: velocity | K59: 10 | L59: km/s | N59: Battery | O59: 1 | P59: kg | Q59: MH
D60: Steel | E60: =K63*(K62)/($W$42) -> 3.9788736 | F60: cm | J60: radius | K60: =K58/2000 -> 0.001 | L60: m
D61: hull | E61: =K63*(K62)/($W$43) -> 3.1830989 | F61: cm | J61: velocity | K61: =K59*10^3 -> 10000 | L61: m/s
D62: tungsten | E62: =K63*(K62)/($W$44) -> 1.5915494 | F62: cm | K62: 20 | L62: g/cm3
B63: Immediate cavitation >10× rod size | J63: Length | K63: =100*K57/(K62*1000* PI()*K60^2) -> 1.5915494 | L63: cm
J64: L/W ratio | K64: =K63/(K58/10) -> 7.9577472
A66: Rifle | E66: =E68*10^6 -> 4500 | F66: J
E67: =E68*1000 -> 4.5 | F67: kJ | R67: Damage | S67: 3+
B68: kinetic energy = 0.5 * mass * velocity2 | E68: =10^-6*0.5*K69*(K71*10^3)^2 -> 0.0045 | F68: MJ | N68: field | O68: 50 | P68: T | R68: AP | S68: 4
E69: =E68/(PI()*(K70/20)^2) -> 0.14323945 | F69: MJ/cm² | J69: mass | K69: 0.001 | L69: kg | N69: barrel : | O69: 1 | P69: m | R69: RAF | S69: x1
C70: impact area | E70: =3.14*K72^2 -> 3.14e-06 | F70: m² | J70: caliber | K70: 2 | L70: mm | N70: Coil | P70: kg
B71: hydrodynamic penetration | D71: CNT | E71: =K75*(K74)/($W$41)*0.8 -> 25.464791 | F71: cm | J71: velocity | K71: 3 | L71: km/s | N71: Battery | O71: 0.02 | P71: kg | Q71: MH
D72: Steel | E72: =K75*(K74)/($W$42)*0.8 -> 3.1830989 | F72: cm | J72: radius | K72: =K70/2000 -> 0.001 | L72: m | N72: Rods x100 | O72: =K69*100 -> 0.1 | P72: kg
D73: hull | E73: =K75*(K74)/($W$43)*0.8 -> 2.5464791 | F73: cm | J73: velocity | K73: =K71*10^3 -> 3000 | L73: m/s
D74: tungsten | E74: =K75*(K74)/($W$44)*0.8 -> 1.2732395 | F74: cm | K74: 20 | L74: g/cm3 | N74: Impact | O74: >130 | P74: dB
B75: flesh | C75: 1 cm hole | J75: Length | K75: =100*K69/(K74*1000* PI()*K72^2) -> 1.5915494 | L75: cm | N75: Sonic boom | O75: >130 | P75: dB
C76: 4 cm ripple | J76: L/W ratio | K76: =K75/(K70/10) -> 7.9577472 | O76: lightning crack
A78: Sniper | E78: =E80*10^6 -> 4500000 | F78: J
E79: =E80*1000 -> 4500 | F79: kJ
B80: kinetic energy = 0.5 * mass * velocity2 | E80: =10^-6*0.5*K81*(K83*10^3)^2 -> 4.5 | F80: MJ | N80: field | O80: 150 | P80: T
E81: =E80/(PI()*(K82/20)^2) -> 1.7683883 | F81: MJ/cm² | J81: mass | K81: 1 | L81: kg | N81: barrel : | O81: 2 | P81: m | R81: Damage
C82: impact area | E82: =3.14*K84^2 -> 0.00025434 | F82: m² | J82: caliber | K82: 18 | L82: mm | N82: Coil | O82: 0.5 | P82: kg | R82: AP | S82: 5
B83: hydrodynamic penetration | D83: CNT | E83: =K87*(K86)/($W$41)*0.8 -> 314.38013 | F83: cm | J83: velocity | K83: 3 | L83: km/s | R83: RAF | S83: 1/sec
D84: Steel | E84: =K87*(K86)/($W$42)*0.8 -> 39.297517 | F84: cm | J84: radius | K84: =K82/2000 -> 0.009 | L84: m | N84: Battery | O84: 20 | P84: kg | Q84: MH
D85: hull | E85: =K87*(K86)/($W$43)*0.8 -> 31.438013 | F85: cm | J85: velocity | K85: =K83*10^3 -> 3000 | L85: m/s | N85: Rods x30 | O85: 30 | P85: kg
D86: tungsten | E86: =K87*(K86)/($W$44)*0.8 -> 15.719007 | F86: cm | K86: 20 | L86: g/cm3 | N86: Impact | O86: 160 | P86: dB
J87: Length | K87: =100*K81/(K86*1000* PI()*K84^2) -> 19.648758 | L87: cm | N87: Sonic boom | O87: 160 | P87: dB | Q87: at 10m
J88: L/W ratio | K88: =K87/(K82/10) -> 10.915977 | O88: Boom/crack combo, shatter glass
A90: Tank buster | E90: =E92*10^6 -> 4500000 | F90: J
E91: =E92*1000 -> 4500 | F91: kJ
B92: kinetic energy = 0.5 * mass * velocity2 | E92: =10^-6*0.5*K93*(K95*10^3)^2 -> 4.5 | F92: MJ | N92: field | O92: 50 | P92: T
E93: =E92/(PI()*(K94/20)^2) -> 1.7683883 | F93: MJ/cm² | J93: mass | K93: 1 | L93: kg | N93: barrel : | O93: 5 | P93: m | R93: Damage
C94: impact area | E94: =3.14*K96^2 -> 0.00025434 | F94: m² | J94: caliber | K94: 18 | L94: mm | N94: Coil | O94: 2 | P94: kg | R94: AP
B95: hydrodynamic penetration | D95: CNT | E95: =K99*(K98)/($W$41)*0.8 -> 314.38013 | F95: cm | J95: velocity | K95: 3 | L95: km/s | R95: RAF | S95: 1/sec
D96: Steel | E96: =K99*(K98)/($W$42)*0.8 -> 39.297517 | F96: cm | J96: radius | K96: =K94/2000 -> 0.009 | L96: m | N96: Battery | O96: 8 | P96: kg | Q96: MH
D97: hull | E97: =K99*(K98)/($W$43)*0.8 -> 31.438013 | F97: cm | J97: velocity | K97: =K95*10^3 -> 3000 | L97: m/s | N97: Rods x100 | P97: kg
D98: tungsten | E98: =K99*(K98)/($W$44)*0.8 -> 15.719007 | F98: cm | K98: 20 | L98: g/cm3
J99: Length | K99: =100*K93/(K98*1000* PI()*K96^2) -> 19.648758 | L99: cm
J100: L/W ratio | K100: =K99/(K94/10) -> 10.915977
A101: Frigate | E101: =E103*10^6 -> 45000000 | F101: J
E102: =E103*1000 -> 45000 | F102: kJ
B103: kinetic energy = 0.5 * mass * velocity2 | E103: =10^-6*0.5*K104*(K106*10^3)^2 -> 45 | F103: MJ | N103: field | O103: 50 | P103: T
E104: =E103/(PI()*(K105/20)^2) -> 70.73553 | F104: MJ/cm² | J104: mass | K104: 0.1 | L104: kg | N104: barrel : | P104: m | R104: Damage
C105: impact area | E105: =3.14*K107^2 -> 6.3585e-05 | F105: m² | J105: caliber | K105: 9 | L105: mm | N105: Coil | P105: kg | R105: AP
B106: hydrodynamic penetration | D106: CNT | E106: =K110*(K109)/($W$41)*0.8 -> 125.75205 | F106: cm | J106: velocity | K106: 30 | L106: km/s | R106: RAF
...

Sheet Kinetic
B3: https://www.projectrho.com/public_html/rocket/sidearmintro.php#bettergun
Q4: Ke = 0.5 * M * V2
B6: https://www.projectrho.com/public_html/rocket/spacegunconvent.php#id--Kinetic_Kill_Weapons--Railguns | Q6: where: | U6: Accuracy factors
U7: Uncertain target location due to finite sensor resolution
Q8: Ke = kinetic energy (Joules) | U8: Uncertain target motion due to sensor glint or shape effects
B9: 1 kg at 9.98 km/sec is packing 50 megajoules of energy. | Q9: M = mass of projectile (kg) | U9: Sensor boresight error due to finite manufacturing tolerances
Q10: V = velocity of projectile relative to target (m/s) | U10: Target motion during sensor integration time
U11: Analog-to-digital conversion errors of sensor data
J12: critical temp | K12: 100 | L12: - | M12: 300 | N12: K | Q12: Wp = Ke * (1 / We) | U12: Software errors in fire control system
J13: critical field | K13: 100 | L13: - | M13: 200 | N13: Tesla | U13: Hardware errors in fire control system
B14: Coilgun : | C14: lower power consumption | Q14: where: | U14: Digital-to-analog conversion errors of gunlaying servo commands
C15: coils are not eroded | U15: Target motion during weapon aiming time
D16: Efficiency | E16: 0.99 | K16: Rod | Q16: Wp = power required by weapon to fire one projectile (Joules) | U16: Weapon boresight error due to finite manufacturing tolerances
E17: =10^-3*0.5*K17*(K19*10^3)^2 -> 0.0625 | F17: kJ | J17: mass | K17: 5 | L17: kg | N17: =K19*3 -> 0.015 | O17: cs | Q17: Ke = kinetic energy of one weapon projectile (Joules) | U17: Weapon structural distortion due to inertial effects of rapid slew
B18: kinetic energy = 0.5 * mass * velocity2 | E18: =10^-6*0.5*K17*(K19*10^3)^2 -> 6.25e-05 | F18: MJ | J18: radius | K18: 1.5 | L18: cm | N18: =K17/18*N17^2 -> 6.25e-05 | O18: MJ | Q18: We = efficiency of the weapon (0.0 = 0%, 1.0 = 100%) | U18: Weapon structural distortion due to external or internal vibration
E19: =E18/(PI()*K18^2) -> 8.8419413e-06 | F19: MJ/cm² | J19: velocity | K19: 0.005 | L19: km/s | U19: Weapon structural distortion due to thermal expansion during firing
B20: heat energy = 0.5 * (1/e - 1) * (kinetic energy) | E20: =0.5 * (1/E16-1) * E18 -> 3.1565657e-07 | F20: MJ | J20: radius | K20: =K18/100 -> 0.015 | M20: m
B21: projectile temperature = (heat energy) / (C * mass) | E21: =100*E20/(K22*K17) -> 1.4029181e-07 | F21: % | J21: velocity | K21: =K19*10^3 -> 5 | M21: m/s
B22: volume = kinetic energy / (K * (magnetic field)2) | E22: =E18*10^3/(K29*(K31)^2) -> 9.2592593e-09 | F22: m3 | J22: Heat cap | K22: 45 | N22: CNT
B23: length = volume / area | E23: =E22/(PI()*K20^2) -> 1.3099172e-05 | F23: m | J23: Density | K23: 4500 | L23: kg/m3
J24: Length | K24: =K17/(K23* PI()*K20^2) -> 1.5719007 | L24: m | N24: =K24 -> 1.5719007 | Q24: =1500*8 -> 12000
B25: mass = density * volume * ratio | E25: =K32*E22*K33 -> 2.7777778e-07 | F25: t | J25: L/W ratio | K25: =K24/(K20*2) -> 52.396689
Q26: Enemy position | R26: The location of the enemy when your shot arrives.
K27: Coil | Q27: Weapon performance | R27: The actual flight path of your shot as affected by the physical characteristics of the weapon itself and the environment through which the shot passes.
B28: momentum p = m*V | E28: =K17*K19* 10^-3 -> 2.5e-05 | J28: K (max) | K28: 400 | L28: kJ/m3/T2 | Q28: Weapon control | R28: The degree to which you can precisely control the aiming of the weapon.
J29: K | K29: 300 | L29: kJ/m3/T2 | N29: metallic hydrogen
J30: field (max) | K30: 200 | L30: teslas | R30: TITANIUM | T30: DIAMOND | U30: GRAPHITE
J31: field | K31: 150 | L31: teslas | Q31: specific heat C | R31: 0.5 | S31: J/g | T31: 0.5 | U31: 0.7
J32: Density | K32: 300 | L32: kg/m3 | Q32: specific heat C | R32: =R31*1000*10^-6 -> 0.0005 | S32: MJ/kg | T32: =T31*1000*10^-6 -> 0.0005 | U32: =U31*1000*10^-6 -> 0.0007
J33: Volume ratio | K33: 0.1 | Q33: Melting point | R33: 1725 | S33: °C | T33: 4500 | U33: 3500
A34: Taille | Q34: Heat cap | R34: =R32*R33 -> 0.8625 | T34: =T32*T33 -> 2.25 | U34: =U32*U33 -> 2.45
A35: 0 | B35: kinetic energy = 0.5 * mass * velocity2 | E35: =10^-3*0.5*K36*(K38*10^3)^2 -> 5 | F35: kJ | K35: 5.6 mm Handgun (M16)
E36: =E35/(PI()*(K37/20)^2) -> 20.300375 | F36: kJ/cm² | J36: mass | K36: 0.01 | L36: kg | N36: =K38*3 -> 3 | O36: cs
C37: Nanofiber mass needed to stop | E37: =E35*1000/100 -> 50 | F37: g | J37: caliber | K37: 5.6 | L37: mm | N37: =K36/18*N36^2 -> 0.005 | O37: MJ | P37: https://en.wikipedia.org/wiki/Impact_depth
C38: Mass of steel to stop | E38: =10^-3*E35/0.13 -> 0.038461538 | F38: g/cm² | H38: =E38/8 -> 0.0048076923 | I38: cm | J38: velocity | K38: 1 | L38: km/s | N38: =E41/N36/sqrt(K36) -> 5.8691268 | O38: pen/cs/kg | P38: penetration depth D = L×A/B | U38: penetrate skull | V38: 200 | W38: J
